Workbook

Sheet Case Summary
A1: Sidney Garber Offer Case Summary
G2: Seller Liquidation Floor Bridge
A3: Purpose | B3: Compare downside/base/upside offer structures against 35% investor IRR target and 25% searcher equity target. Related-party debt balance remains an open input.
A4: Model basis | B4: Value tab copied into three case tabs. Original Value tab left intact. Charity/contributions are not added back to EBITDA because they appear below EBITDA in the source statement; pause is noted only for post-EBITDA cash flow thinking. | G4: Input / Inference | H4: Low | I4: Base | J4: High | K4: Notes
A5: Hold period | B5: 5 years | G5: Gross cash per source image | H5: 5500 | I5: 5500 | J5: 5500 | K5: $000s; source image
A6: Base multiple policy | B6: Base case assumes no multiple expansion: exit multiple equals entry multiple. | G6: Seller-estimated net cash after debt | H6: 3000 | I6: 3500 | J6: 4000 | K6: $000s; working assumption from seller discussion
G7: Implied related-party debt | H7: =H5-H6 | I7: =I5-I6 | J7: =J5-J6 | K7: Derived only, not confirmed debt balance
A8: Open seller-cash input | B8: Related-party debt balance is unknown. Seller expected to use excess cash to repay it before close. | G8: Seller liquidation floor | H8: 8000 | I8: 8000 | J8: 8000 | K8: $000s; total walk-away value
A9: Manual input needed | B9: Enter related-party debt balance once known to calculate net cash retained by seller from company cash. | C9: Related-party debt balance | G9: Implied inventory liquidation value | H9: =H8-H6 | I9: =I8-I6 | J9: =J8-J6 | K9: $000s; not book value
G10: Inventory book value | H10: 13100 | I10: 13100 | J10: 13100 | K10: $000s; source image
A11: Metric | B11: Downside | C11: Base | D11: Upside | E11: Notes | G11: Liquidation value as % of book | H11: =H9/H10 | I11: =I9/I10 | J11: =J9/J10 | K11: For orientation only; diligence later
A12: Entry multiple | B12: ='Downside Case'!N15/'Downside Case'!E40 | C12: ='Base Case'!N15/'Base Case'!E40 | D12: ='Upside Case'!N15/'Upside Case'!E40 | E12: Scenario input
A13: TEV / purchase price | B13: ='Downside Case'!N15 | C13: ='Base Case'!N15 | D13: ='Upside Case'!N15 | E13: $000s; recalculated from reported EBITDA, not charity-adjusted EBITDA
A14: 2025 reported EBITDA | B14: ='Downside Case'!E40 | C14: ='Base Case'!E40 | D14: ='Upside Case'!E40 | E14: $000s; charity/contributions are below EBITDA in source statement and are not added back to EBITDA | G14: Modeling conclusion | H14: Use $4M-$5M implied inventory liquidation value, $4.5M midpoint, as seller floor bridge. Do not use $13.1M book inventory value as liquidation value. Keep related-party debt as diligence item until exact balance is confirmed.
A15: Term debt x EBITDA | B15: ='Downside Case'!N20 | C15: ='Base Case'!N20 | D15: ='Upside Case'!N20 | E15: Scenario input
A16: Seller note | B16: ='Downside Case'!N21 | C16: ='Base Case'!N21 | D16: ='Upside Case'!N21 | E16: $000s; standard model mechanics
A17: Cash left in business | B17: ='Downside Case'!N22 | C17: ='Base Case'!N22 | D17: ='Upside Case'!N22 | E17: $000s | G17: V6 EBITDA Correction
A18: Exit multiple | B18: ='Downside Case'!N131 | C18: ='Base Case'!N131 | D18: ='Upside Case'!N131 | E18: Base = entry multiple | G18: Correction | H18: Charity / contributions appear below EBITDA in the source income statements, so they should not be added back to EBITDA. V6 reverts Value and all case tabs to reported EBITDA.
A19: Year 1 revenue growth | B19: ='Downside Case'!F38 | C19: ='Base Case'!F38 | D19: ='Upside Case'!F38 | E19: Assumption | G19: 2025 EBITDA used | H19: 3,363
A20: Year 1 EBITDA margin | B20: ='Downside Case'!F41 | C20: ='Base Case'!F41 | D20: ='Upside Case'!F41 | E20: Assumption | G20: 2025 contribution line | H20: 601, below EBITDA, relevant to post-EBITDA cash flow only
A21: Investor IRR | B21: ='Downside Case'!J146 | C21: ='Base Case'!J146 | D21: ='Upside Case'!J146 | E21: Target >= 35% for full performance vest | G21: High case valuation math | H21: 3.5x * $3.363M = ~$11.8M, not $13.9M
A22: Investor MOIC | B22: ='Downside Case'!J147 | C22: ='Base Case'!J147 | D22: ='Upside Case'!J147 | E22: Formula output
A23: Searcher proceeds | B23: ='Downside Case'!J148 | C23: ='Base Case'!J148 | D23: ='Upside Case'!J148 | E23: $000s formula output
A24: Total searcher common equity target | B24: ='Downside Case'!D102 | C24: ='Base Case'!D102 | D24: ='Upside Case'!D102 | E24: Target = 25%
A25: Max IRR hurdle | B25: ='Downside Case'!D111 | C25: ='Base Case'!D111 | D25: ='Upside Case'!D111 | E25: Full performance vest at 35%
A26: Cash in business before debt payoff | B26: 5500 | C26: 5500 | D26: 5500 | E26: $000s gross cash from source image; seller likely mentally netting related-party debt to $3M-$4M cash
A27: Less related-party debt balance | B27: =$D$9 | C27: =$D$9 | D27: =$D$9 | E27: Exact balance still missing; bridge implies ~$1.5M-$2.5M but do not treat as confirmed
A28: Less cash left in business | B28: ='Downside Case'!N22 | C28: ='Base Case'!N22 | D28: ='Upside Case'!N22 | E28: $000s
A29: Estimated excess cash to seller | B29: =IF($D$9="","Missing debt balance",5500-B26-B27) | C29: =IF($D$9="","Missing debt balance",5500-C26-C27) | D29: =IF($D$9="","Missing debt balance",5500-D26-D27) | E29: Not included in TEV; seller cash proceeds after debt payoff
A30: Stated seller liquidation floor | B30: 8000 | C30: 8000 | D30: 8000 | E30: $000s; seller-estimated total walk-away value, including net cash after debt plus inventory liquidation value

Sheet Model Notes
A1: Purpose | B1: Document the limited source-backed updates made from photo-transcribed financials.
A2: Selected model tab | B2: Value
A3: Reason | B3: Sidney Garber should be underwritten as an EBITDA / cash-flow deal, not an ARR growth-multiple deal. Growth tab left untouched.
A4: Source basis | B4: Only values visible in the four uploaded financial-statement photos and transcribed workbook were used.
A5: No invented data | B5: No missing model inputs were filled where source data was unavailable.
A7: Cell | B7: Tab | C7: Value | D7: Source
A8: C37 | B8: Value | C8: 12300 | D8: 2024 Income Statement: 2023 Actual Core Sales
A9: D37 | B9: Value | C9: 18117 | D9: 2024/2025 Income Statement: 2024 Actual Core Sales
A10: E37 | B10: Value | C10: 18575 | D10: 2025 Income Statement: 2025 Actual Core Sales
A11: C40 | B11: Value | C11: 1190 | D11: 2024 Income Statement / 2024 Cash Flow: 2023 Actual EBITDA
A12: D40 | B12: Value | C12: 3224 | D12: 2024 Income Statement / 2025 Cash Flow: 2024 Actual EBITDA
A13: E40 | B13: Value | C13: 3363 | D13: 2025 Income Statement / 2025 Cash Flow: 2025 Actual EBITDA
A15: Open model inputs not populated | B15: Purchase price / TEV, normalized EBITDA add-backs, debt terms, seller financing, rollover, earnout, working-capital peg, inventory treatment, tax treatment, owner compensation normalization, forecast growth, forecast margins, capex, NWC needs.
A17: Updated assumption | B17: Charity / contributions held post-close
A18: Rationale | B18: Owner-directed charitable giving is not an obligation. For offer modeling, assume contributions are paused while initial acquisition debt is paid down, then restarted later at a smaller legacy-compatible level.
A19: Model impact | B19: Value tab row 40 changed from reported GAAP EBITDA to Normalized EBITDA by adding back visible charity/contribution amounts from source financials.
A20: 2023 add-back | B20: 339
A21: 2024 add-back | B21: 558
A22: 2025 add-back | B22: 601
A23: Open diligence | B23: Confirm legal/nonprofit commitments, donor expectations, tax treatment, and timing/amount of any restarted charitable program.
A25: Scenario cases added | B25: V4 adds Downside Case, Base Case, Upside Case, and Case Summary. Original Value tab remains intact.
A26: Case purpose | B26: Solve offer range against 35% investor IRR target and 25% searcher equity target while beating seller stated ~$8M liquidation alternative.
A27: Important open input | B27: Related-party debt balance remains missing; Case Summary leaves this blank rather than assuming a debt payoff amount.
A29: V5 liquidation bridge update | B29: Added seller liquidation floor bridge to Case Summary: $8M walk-away value equals estimated $3M-$4M net cash after debt plus implied $4M-$5M inventory liquidation value. $13.1M remains book inventory value, not liquidation value.
... A34: Charity treatment | B34: Pause of charitable contributions remains a post-close cash-flow / debt-paydown note, not an EBITDA normalization item.

Sheet Model Template
A2: x | B2: G&B Model Template
B4: Instructions
B5: 1. Fill out historical Revenue and EBITDA. Project Revenue and EBITDA for the 5 year period.
B6: 2. Fill out the transaction assumptions with TEV & leverage and other key structure information.
B7: 3. Adjust the remaining assumptions in the yellow boxes for the cash flow statement and debt schedule as appropriate.
B8: 4. Check the "check" to make sure your business has the cash flow profile to support your capital structure.
B9: 5. Modify the deal structure and exit assumptions if needed. Note: If the model is getting errors, turn the circuit breaker to 0 and back to 1.
B10: 6. Evaluate the returns.
B12: $000s unless otherwise indicated | L12: Check | N12: =IF(SUM(F67:J67)>0,"Cash Shortfall","OK") | O12: *Check here to make sure your business has enough cash flow to support the capital structure.
A14: x | B14: Sources | G14: Uses | L14: Transaction Assumptions
C15: Amount | D15: =CONCATENATE("x",$N$16) | E15: % of Total | H15: Amount | I15: =CONCATENATE("x",$N$16) | J15: % of Total | L15: TEV | N15: 8500 | O15: *Refer to the Search Fund Study to understand median multiples, revenue, EBITDA, and more.
B16: Term Debt | C16: =D16*N17 | D16: =N20 | E16: =C16/C25 | G16: TEV | H16: =N15 | I16: =H16/$N$17 | J16: =H16/$H$25 | L16: Entry Multiple | N16: EBITDA
B17: Seller Debt | C17: =N21 | D17: =C17/$N$17 | E17: =C17/C25 | G17: Fees | H17: =H16*N19 | I17: =H17/$N$17 | J17: =H17/$H$25 | L17: =IF(N16="ARR","Ending ARR","LTM EBITDA") | N17: =IF(N16="ARR",E34,E40)
B18: Total Debt | C18: =SUM(C16:C17) | D18: =C18/$N$17 | E18: =C18/$C$25 | G18: Cash to B/S | H18: =N22 | I18: =H18/$N$17 | J18: =H18/$H$25 | L18: LTM Period | N18: 46022 | O18: 2024 Search Fund Study | Stanford Graduate School of Business
L19: Transaction Costs | N19: 0.05
B20: Equity | D20: % of Equity | L20: =CONCATENATE("Term Debt x",N16) | N20: 2.5
B21: Seller Equity Rollover | C21: =D21*C23 | D21: =N25 | E21: =C21/C25 | L21: Seller Debt Quantum | N21: 1000
B22: Investor Equity | C22: =D22*C23 | D22: =1-D21 | E22: =C22/C25 | L22: Cash to B/S | N22: 200 | O22: *Typically, searcher(s) put de minimis cash on the balance sheet.
B23: Total Equity | C23: =C25-C18 | D23: =SUM(C21:C22)/C23 | E23: =C23/C25 | L23: ECF Distribution | N23: 0 | O23: *Toggle this to distribute 1/3 of accumulated cash in Year 3 & 4.
L24: LLC/C-corp | N24: C-corp | O24: *To qualify for QSBS, TEV must be <$70M you must be a C-corp and fit certain industry requirements (many except financial and professional services firms, certain categories of healthcare, and certain other excluded businesses).
B25: Total Sources | C25: =H25 | D25: =C25/$N$17 | E25: =C25/$H$25 | G25: Total Uses | H25: =SUM(H16:H18) | I25: =H25/$N$17 | J25: =H25/$H$25 | L25: Seller Equity Rollover | N25: 0.1 | O25: QSBS | Insights | Holland & Knight
L26: Earnout | N26: 0 | O26: *This is meant to be a simple example of an earnout; earnout structures can vary.
L27: Earnout Amount | N27: 500
B28: Summary Financials | L28: Y1 Revenue Threshold | N28: 5000
E30: TXN Close | J30: TXN + 5
A31: x | B31: Income Statement | L31: Assumptions & BK Growth Notes
C33: =EDATE(D33,-12) | D33: =EDATE(E33,-12) | E33: =N18 | F33: =EDATE(E33,12) | G33: =EDATE(F33,12) | H33: =EDATE(G33,12) | I33: =EDATE(H33,12) | J33: =EDATE(I33,12) | L33: CAGR
B34: Ending ARR | C34: 2684 | D34: 3720 | E34: 4750 | F34: =E34*(1+F35) | G34: =F34*(1+G35) | H34: =G34*(1+H35) | I34: =H34*(1+I35) | J34: =I34*(1+J35) | L34: =_xlfn.RRI(2,C34,E34) | O34: *Use this if you are looking at an ARR multiple deal. Revenue for a period is calculated as the average of beginning and ending ARR.
B35: Growth | D35: =D34/C34-1 | E35: =E34/D34-1 | F35: 0.22894737 | G35: 0.26713062 | H35: 0.29015632 | I35: 0.30762984 | J35: 0.31181256
B37: GAAP Revenue | C37: 2123 | D37: 3202 | E37: 4235 | F37: =IF(N16="ARR",AVERAGE(F34,E34),E37*(1+F38)) | G37: =IF(O16="ARR",AVERAGE(G34,F34),F37*(1+G38)) | H37: =IF(P16="ARR",AVERAGE(H34,G34),G37*(1+H38)) | I37: =IF(Q16="ARR",AVERAGE(I34,H34),H37*(1+I38)) | J37: =IF(R16="ARR",AVERAGE(J34,I34),I37*(1+J38)) | L37: =_xlfn.RRI(2,C37,E37) | O37: *It is difficult to accelerate the growth of a business that is not already consistently growing at a solid pace.
B38: Growth | D38: =D37/C37-1 | E38: =E37/D37-1 | F38: 0.25 | G38: 0.25 | H38: 0.28 | I38: 0.3 | J38: 0.31 | O38: *Forecast revenue here if you are looking at an EBITDA multiple deal. For an ARR deal, you do not need historical revenue numbers.
B40: GAAP EBITDA | C40: 465 | D40: 689 | E40: 1256 | F40: =F41*F37 | G40: =G41*G37 | H40: =H41*H37 | I40: =I41*I37 | J40: =J41*J37 | L40: =_xlfn.RRI(2,C40,E40) | O40: *In the short/medium run, margins in ETA often decline and remain lower than historical margins (see research linked below for more). We rarely see a search fund business of scale with margins greater than 35%.
B41: Margin | C41: =C40/C37 | D41: =D40/D37 | E41: =E40/E37 | F41: 0.22 | G41: 0.22 | H41: 0.25 | I41: 0.28 | J41: 0.29 | O41: Research on EBITDA Margins in ETA - Thomas, Stevens, & Wasserstein
B43: GAAP EBITDA | F43: =F40 | G43: =G40 | H43: =H40 | I43: =I40 | J43: =J40
B44: Depreciation | F44: =-($L$44*F37) | G44: =-($L$44*G37) | H44: =-($L$44*H37) | I44: =-($L$44*I37) | J44: =-($L$44*J37) | L44: 0.01 | M44: % of Revenue | O44: *For asset-light search fund target businesses, depreciation will likely be minimal at around ~1-3% of revenue.
B45: EBIT | F45: =SUM(F43:F44) | G45: =SUM(G43:G44) | H45: =SUM(H43:H44) | I45: =SUM(I43:I44) | J45: =SUM(J43:J44)
B47: Interest | F47: =-F80-F89 | G47: =-G80-G89 | H47: =-H80-H89 | I47: =-I80-I89 | J47: =-J80-J89
B48: EBT | F48: =F45+F47 | G48: =G45+G47 | H48: =H45+H47 | I48: =I45+I47 | J48: =J45+J47
B50: Taxes Owed / Distributed | E50: =IF(N24="LLC",45%,26.5%) | F50: =-$E$50*F48 | G50: =-$E$50*G48 | H50: =-$E$50*H48 | I50: =-$E$50*I48 | J50: =-$E$50*J48
B51: Net Income | F51: =F48+F50 | G51: =G48+G50 | H51: =H48+H50 | I51: =I48+I50 | J51: =J48+J50
A53: x | B53: Cash Flow Statement
B55: Net Income | F55: =F51 | G55: =G51 | H55: =H51 | I55: =I51 | J55: =J51
B56: (+) D&A | F56: =-SUM(F44:F44) | G56: =-SUM(G44:G44) | H56: =-SUM(H44:H44) | I56: =-SUM(I44:I44) | J56: =-SUM(J44:J44) | O56: *You may be able to amortize a portion of the purchase price. This should be further diligenced with your legal counsel.
B57: (+) NWC | F57: =$L$57*F37 | G57: =$L$57*G37 | H57: =$L$57*H37 | I57: =$L$57*I37 | J57: =$L$57*J37 | L57: 0.01 | M57: % of Revenue | O57: *For asset-light search fund target businesses, we recommend modeling this as a 1% of revenue source of cash to be conservative.
B58: (-) CAPEX | F58: =-$L$58*F37 | G58: =-$L$58*G37 | H58: =-$L$58*H37 | I58: =-$L$58*I37 | J58: =-$L$58*J37 | L58: 0.01 | M58: % of Revenue | O58: *For asset-light search fund target businesses, CAPEX will likely be minimal at around ~1-3% of revenue.
B59: (-) Debt Paydown | F59: =F77+F86 | G59: =G77+G86 | H59: =H77+H86 | I59: =I77+I86 | J59: =J77+J86
B60: Cash after Debt | F60: =SUM(F55:F59) | G60: =SUM(G55:G59) | H60: =SUM(H55:H59) | I60: =SUM(I55:I59) | J60: =SUM(J55:J59)
B62: Cash for Earnout | F62: =-F122
B64: Beginning Cash | F64: =N22 | G64: =F70 | H64: =G70 | I64: =H70 | J64: =I70
B65: (+/-) Change in Cash | F65: =F60+F62 | G65: =G60++G62 | H65: =H60++H62 | I65: =I60++I62 | J65: =J60++J62
B66: Ending Cash before Distributions | F66: =SUM(F64:F65) | G66: =SUM(G64:G65) | H66: =SUM(H64:H65) | I66: =SUM(I64:I65) | J66: =SUM(J64:J65)
B67: Check | F67: =IF(F66<0,1,0) | G67: =IF(G66<0,1,0) | H67: =IF(H66<0,1,0) | I67: =IF(I66<0,1,0) | J67: =IF(J66<0,1,0)
B69: (-)Distributions | F69: 0 | G69: 0 | H69: =MAX(IF($N$23=1,1/3*H66,0),0) | I69: =MAX(IF($N$23=1,1/3*I66,0),0) | J69: 0
B70: Ending Cash after Distributions | F70: =F66-F69 | G70: =G66-G69 | H70: =H66-H69 | I70: =I66-I69 | J70: =J66-J69
A73: x | B73: Debt Schedule
B75: Term Loan
B76: Beginning Balance | F76: =C16 | G76: =F78 | H76: =G78 | I76: =H78 | J76: =I78
B77: (-) Mandatory Amortization | F77: =$F$76*-F82 | G77: =$F$76*-G82 | H77: =$F$76*-H82 | I77: =$F$76*-I82 | J77: =$F$76*-J82
B78: Ending Balance | F78: =SUM(F76:F77) | G78: =SUM(G76:G77) | H78: =SUM(H76:H77) | I78: =SUM(I76:I77) | J78: =SUM(J76:J77)
B80: Interest Expense | F80: =F76*$L$80 | G80: =G76*$L$80 | H80: =H76*$L$80 | I80: =I76*$L$80 | J80: =J76*$L$80 | L80: 0.1 | M80: Interest Rate
B82: Amortization Schedule | F82: 0 | G82: 0 | H82: 0 | I82: 0 | J82: 1 | L82: =IF(SUM(F82:J82)=100%,"Check","Paydown doesn't add to 100%") | O82: *Adjust amort schedule to account for term and amort of term loan debt. For bank lenders, we often see amortization schedules of 20%|20%|20%|20%|20% for non bank lenders we often see 0%|0%|0%|0%|100%.
B84: Seller Debt | N84: `
B85: Balance | F85: =C17 | G85: =F87 | H85: =G87 | I85: =H87 | J85: =I87
B86: (-) Paydown | F86: =$F$85*-F91 | G86: =$F$85*-G91 | H86: =$F$85*-H91 | I86: =$F$85*-I91 | J86: =$F$85*-J91
B87: Ending Balance | F87: =SUM(F85:F86) | G87: =SUM(G85:G86) | H87: =SUM(H85:H86) | I87: =SUM(I85:I86) | J87: =SUM(J85:J86)
B89: Interest Expense | F89: =$L$89*F85 | G89: =$L$89*G85 | H89: =$L$89*H85 | I89: =$L$89*I85 | J89: =$L$89*J85 | L89: 0.08 | M89: Interest Rate
B91: Amortization Schedule | F91: 0 | G91: 0 | H91: 0 | I91: 0 | J91: 1 | L91: =IF(SUM(F91:J91)=100%,"Check","Paydown doesn't add to 100%") | O91: *Adjust amort schedule to account for term and amort of seller debt. It is difficult to have seller debt amortize while term loan debt is still outstanding.
B93: Debt Metrics
B94: Total Senior Leverage | F94: =F78/F43 | G94: =G78/G43 | H94: =H78/H43 | I94: =I78/I43 | J94: =J78/J43 | O94: *These are examples of metrics that may be tested as covenants in term loan agreements. These are more typical for EBITDA based debt. ARR debt covenants may include tests of retention, profitability, and liquidity.
B95: Total Leverage | F95: =(F78+F87)/F43 | G95: =(G78+G87)/G43 | H95: =(H78+H87)/H43 | I95: =(I78+I87)/I43 | J95: =(J78+J87)/J43
B96: Fixed Charge Coverage Ratio | F96: =F40/(-F77+F80+-F86+F89-F58-F50+F69-F62) | G96: =G40/(-G77+G80+-G86+G89-G58-G50+G69-G62) | H96: =H40/(-H77+H80+-H86+H89-H58-H50+H69-H62) | I96: =I40/(-I77+I80+-I86+I89-I58-I50+I69-I62) | J96: =J40/(-J77+J80+-J86+J89-J58-J50+J69-J62)
B98: Returns Analysis - 5 Year Hold
A100: x | B100: Deal Structure
B102: Searcher(s) Common Equity | D102: 0.25 | F102: Circuit Breaker (0=Off) | H102: 1 | O102: *If the model is getting errors turn this to 0 and back to 1.
B103: Vested Employee Incentive Pool | D103: 0.05 | O103: *25% equity for solo searches and 30% for partnered searches.
F104: Search Capital | H104: 500
B105: Searcher(s) Equity (at close) | D105: =$D$102/3 | F105: Step-Up | H105: 1.5
B106: Searcher(s) Equity (time vest) | D106: =$D$102/3
B107: Searcher(s) Equity (performance) | D107: =$D$102/3 | F107: Investor Cap Gains Rate | H107: 0.3
B108: Total | D108: =SUM(D105:D107)
B110: Minimum IRR Hurdle | D110: 0.2 | H110: Vested | I110: Total | J110: %
B111: Maximum IRR Hurdle | D111: 0.35 | F111: Preferred Units | H111: =I111 | I111: =F117*1000 | J111: =1-D102
F112: Common Units | H112: =I112*D114/D108 | I112: =I113-I111 | J112: =I112/I113
B113: Vested Performance Equity | D113: =IF(J146>D111,D107,IF(J146<D110,0,(J146-D110)/(D111-D110))*D107) | F113: Total | H113: =SUM(H111:H112) | I113: =I111/J111 | J113: =I113/I113
B114: Total Searcher Vested Equity | D114: =D113+D106+D105
B116: Preferred Equity
B117: Beginning Balance | F117: =C23+(H105*H104) | G117: =F120 | H117: =G120 | I117: =H120 | J117: =I120
B118: (+) Preferred Return | D118: 0.08 | F118: =F117*$D$118 | G118: =G117*$D$118 | H118: =H117*$D$118 | I118: =I117*$D$118 | J118: =J117*$D$118
B119: (-) Distributions | F119: =-F69 | G119: =-G69 | H119: =-H69 | I119: =-I69 | J119: =-J69
B120: Ending Balance | F120: =SUM(F117:F119) | G120: =SUM(G117:G119) | H120: =SUM(H117:H119) | I120: =SUM(I117:I119) | J120: =SUM(J117:J119)
B122: Earnout | F122: =IF(N26=1,IF(F37>N28,N27,0),0)
A124: x | B124: Exit Waterfall & Returns
B126: =CONCATENATE("LTM "&N129&"") | J126: =IF(N128="EBITDA",J40,J34) | L126: Exit Assumptions
B127: (x) Multiple | J127: =N131 | L127: TEV @ Entry | N127: =N15
B128: Total Enterprise Value | J128: =J126*J127 | L128: Multiple @ Entry | N128: =N16
B129: (+) Cash | J129: =J70 | L129: Multiple @ Exit | N129: =N128
B130: (-) Debt | J130: =-J78-J87 | L130: Entry Multiple | N130: =IF(N128="EBITDA",N127/E40,N127/E34)
B131: Total Equity Value | J131: =SUM(J128:J130) | L131: Exit Multiple | N131: =N130 | O131: *For base case, we don't recommend underwriting to multiple expansion; this can be upside at exit.
B132: (-) Preferred Return | J132: =MAX(MIN(J120-F117,J131),0) | L132: Searcher(s) Catch Up | N132: 1
B133: (-) Return of Capital | J133: =MIN(MIN(F117,J131-J132),J120)
...

Sheet Growth
A2: x | B2: G&B Model Template
B4: Instructions
B5: 1. Fill out historical Revenue and EBITDA. Project Revenue and EBITDA for the 5 year period.
B6: 2. Fill out the transaction assumptions with TEV & leverage and other key structure information.
B7: 3. Adjust the remaining assumptions in the yellow boxes for the cash flow statement and debt schedule as appropriate.
B8: 4. Check the "check" to make sure your business has the cash flow profile to support your capital structure.
B9: 5. Modify the deal structure and exit assumptions if needed. Note: If the model is getting errors, turn the circuit breaker to 0 and back to 1.
B10: 6. Evaluate the returns.
B12: $000s unless otherwise indicated | L12: Check | N12: =IF(SUM(F67:J67)>0,"Cash Shortfall","OK") | O12: *Check here to make sure your business has enough cash flow to support the capital structure.
A14: x | B14: Sources | G14: Uses | L14: Transaction Assumptions
C15: Amount | D15: =CONCATENATE("x",$N$16) | E15: % of Total | H15: Amount | I15: =CONCATENATE("x",$N$16) | J15: % of Total | L15: TEV | N15: 15000 | O15: *Refer to the Search Fund Study to understand median multiples, revenue, EBITDA, and more.
B16: Term Debt | C16: =D16*N17 | D16: =N20 | E16: =C16/C25 | G16: TEV | H16: =N15 | I16: =H16/$N$17 | J16: =H16/$H$25 | L16: Entry Multiple | N16: ARR
B17: Seller Debt | C17: =N21 | D17: =C17/$N$17 | E17: =C17/C25 | G17: Fees | H17: =H16*N19 | I17: =H17/$N$17 | J17: =H17/$H$25 | L17: =IF(N16="ARR","Ending ARR","LTM EBITDA") | N17: =IF(N16="ARR",E34,E40)
B18: Total Debt | C18: =SUM(C16:C17) | D18: =C18/$N$17 | E18: =C18/$C$25 | G18: Cash to B/S | H18: =N22 | I18: =H18/$N$17 | J18: =H18/$H$25 | L18: LTM Period | N18: 46022 | O18: 2024 Search Fund Study | Stanford Graduate School of Business
L19: Transaction Costs | N19: 0.05
B20: Equity | D20: % of Equity | L20: =CONCATENATE("Term Debt x",N16) | N20: 0.5
B21: Seller Equity Rollover | C21: =D21*C23 | D21: =N25 | E21: =C21/C25 | L21: Seller Debt Quantum | N21: 1000
B22: Investor Equity | C22: =D22*C23 | D22: =1-D21 | E22: =C22/C25 | L22: Cash to B/S | N22: 350 | O22: *Typically, searcher(s) put de minimis cash on the balance sheet.
B23: Total Equity | C23: =C25-C18 | D23: =SUM(C21:C22)/C23 | E23: =C23/C25 | L23: ECF Distribution | N23: 0 | O23: *Toggle this to distribute 1/3 of accumulated cash in Year 3 & 4.
L24: LLC/C-corp | N24: C-corp | O24: *To qualify for QSBS, TEV must be <$70M you must be a C-corp and fit certain industry requirements (many except financial and professional services firms, certain categories of healthcare, and certain other excluded businesses).
B25: Total Sources | C25: =H25 | D25: =C25/$N$17 | E25: =C25/$H$25 | G25: Total Uses | H25: =SUM(H16:H18) | I25: =H25/$N$17 | J25: =H25/$H$25 | L25: Seller Equity Rollover | N25: 0.1 | O25: QSBS | Insights | Holland & Knight
L26: Earnout | N26: 0 | O26: *This is meant to be a simple example of an earnout; earnout structures can vary.
L27: Earnout Amount | N27: 500
B28: Summary Financials | L28: Y1 Revenue Threshold | N28: 5000
E30: TXN Close | J30: TXN + 5
A31: x | B31: Income Statement | L31: Assumptions & BK Growth Notes
C33: =EDATE(D33,-12) | D33: =EDATE(E33,-12) | E33: =N18 | F33: =EDATE(E33,12) | G33: =EDATE(F33,12) | H33: =EDATE(G33,12) | I33: =EDATE(H33,12) | J33: =EDATE(I33,12) | L33: CAGR
B34: Ending ARR | C34: 2138 | D34: 3392 | E34: 5078 | F34: =E34*(1+F35) | G34: =F34*(1+G35) | H34: =G34*(1+H35) | I34: =H34*(1+I35) | J34: =I34*(1+J35) | L34: =_xlfn.RRI(2,C34,E34) | O34: *Use this if you are looking at an ARR multiple deal. Revenue for a period is calculated as the average of beginning and ending ARR.
B35: Growth | D35: =D34/C34-1 | E35: =E34/D34-1 | F35: 0.4185703 | G35: 0.38690914 | H35: 0.354 | I35: 0.33955411 | J35: 0.28793735
B37: GAAP Revenue | C37: 1657 | D37: 2765 | E37: 4235 | F37: =IF(N16="ARR",AVERAGE(F34,E34),E37*(1+F38)) | G37: =IF(O16="ARR",AVERAGE(G34,F34),F37*(1+G38)) | H37: =IF(P16="ARR",AVERAGE(H34,G34),G37*(1+H38)) | I37: =IF(Q16="ARR",AVERAGE(I34,H34),H37*(1+I38)) | J37: =IF(R16="ARR",AVERAGE(J34,I34),I37*(1+J38)) | L37: =_xlfn.RRI(2,C37,E37) | O37: *It is difficult to accelerate the growth of a business that is not already consistently growing at a solid pace.
B38: Growth | D38: =D37/C37-1 | E38: =E37/D37-1 | F38: 0.45 | G38: 0.4 | H38: 0.36 | I38: 0.34 | J38: 0.31 | O38: *Forecast revenue here if you are looking at an EBITDA multiple deal. For an ARR deal, you do not need historical revenue numbers.
B40: GAAP EBITDA | C40: -34 | D40: 105 | E40: 405 | F40: =F41*F37 | G40: =G41*G37 | H40: =H41*H37 | I40: =I41*I37 | J40: =J41*J37 | L40: =IFERROR(_xlfn.RRI(2,C40,E40),"N/A") | O40: *In the short/medium run, margins in ETA often decline and remain lower than historical margins (see research linked below for more). We rarely see a search fund business of scale with margins greater than 35%.
B41: Margin | C41: =C40/C37 | D41: =D40/D37 | E41: =E40/E37 | F41: 0.03 | G41: 0.05 | H41: 0.114 | I41: 0.12 | J41: 0.14 | O41: Research on EBITDA Margins in ETA - Thomas, Stevens, & Wasserstein
B43: GAAP EBITDA | F43: =F40 | G43: =G40 | H43: =H40 | I43: =I40 | J43: =J40
B44: Depreciation | F44: =-($L$44*F37) | G44: =-($L$44*G37) | H44: =-($L$44*H37) | I44: =-($L$44*I37) | J44: =-($L$44*J37) | L44: 0.01 | M44: % of Revenue | O44: *For asset-light search fund target businesses, depreciation will likely be minimal at around ~1-3% of revenue.
B45: EBIT | F45: =SUM(F43:F44) | G45: =SUM(G43:G44) | H45: =SUM(H43:H44) | I45: =SUM(I43:I44) | J45: =SUM(J43:J44)
B47: Interest | F47: =-F80-F89 | G47: =-G80-G89 | H47: =-H80-H89 | I47: =-I80-I89 | J47: =-J80-J89
B48: EBT | F48: =F45+F47 | G48: =G45+G47 | H48: =H45+H47 | I48: =I45+I47 | J48: =J45+J47
B50: Taxes Owed / Distributed | E50: =IF(N24="LLC",45%,26.5%) | F50: =-$E$50*F48 | G50: =-$E$50*G48 | H50: =-$E$50*H48 | I50: =-$E$50*I48 | J50: =-$E$50*J48
B51: Net Income | F51: =F48+F50 | G51: =G48+G50 | H51: =H48+H50 | I51: =I48+I50 | J51: =J48+J50
A53: x | B53: Cash Flow Statement
B55: Net Income | F55: =F51 | G55: =G51 | H55: =H51 | I55: =I51 | J55: =J51
B56: (+) D&A | F56: =-SUM(F44:F44) | G56: =-SUM(G44:G44) | H56: =-SUM(H44:H44) | I56: =-SUM(I44:I44) | J56: =-SUM(J44:J44) | O56: *You may be able to amortize a portion of the purchase price. This should be further diligenced with your legal counsel.
B57: (+) NWC | F57: =$L$57*F37 | G57: =$L$57*G37 | H57: =$L$57*H37 | I57: =$L$57*I37 | J57: =$L$57*J37 | L57: 0.01 | M57: % of Revenue | O57: *For asset-light search fund target businesses, we recommend modeling this as a 1% of revenue source of cash to be conservative.
B58: (-) CAPEX | F58: =-$L$58*F37 | G58: =-$L$58*G37 | H58: =-$L$58*H37 | I58: =-$L$58*I37 | J58: =-$L$58*J37 | L58: 0.01 | M58: % of Revenue | O58: *For asset-light search fund target businesses, CAPEX will likely be minimal at around ~1-3% of revenue.
B59: (-) Debt Paydown | F59: =F77+F86 | G59: =G77+G86 | H59: =H77+H86 | I59: =I77+I86 | J59: =J77+J86
B60: Cash after Debt | F60: =SUM(F55:F59) | G60: =SUM(G55:G59) | H60: =SUM(H55:H59) | I60: =SUM(I55:I59) | J60: =SUM(J55:J59)
B62: Cash for Earnout | F62: =-F122
B64: Beginning Cash | F64: =N22 | G64: =F70 | H64: =G70 | I64: =H70 | J64: =I70
B65: (+/-) Change in Cash | F65: =F60+F62 | G65: =G60++G62 | H65: =H60++H62 | I65: =I60++I62 | J65: =J60++J62
B66: Ending Cash before Distributions | F66: =SUM(F64:F65) | G66: =SUM(G64:G65) | H66: =SUM(H64:H65) | I66: =SUM(I64:I65) | J66: =SUM(J64:J65)
B67: Check | F67: =IF(F66<0,1,0) | G67: =IF(G66<0,1,0) | H67: =IF(H66<0,1,0) | I67: =IF(I66<0,1,0) | J67: =IF(J66<0,1,0)
B69: (-)Distributions | F69: 0 | G69: 0 | H69: =MAX(IF($N$23=1,1/3*H66,0),0) | I69: =MAX(IF($N$23=1,1/3*I66,0),0) | J69: 0
B70: Ending Cash after Distributions | F70: =F66-F69 | G70: =G66-G69 | H70: =H66-H69 | I70: =I66-I69 | J70: =J66-J69
A73: x | B73: Debt Schedule
B75: Term Loan
B76: Beginning Balance | F76: =C16 | G76: =F78 | H76: =G78 | I76: =H78 | J76: =I78
B77: (-) Mandatory Amortization | F77: =$F$76*-F82 | G77: =$F$76*-G82 | H77: =$F$76*-H82 | I77: =$F$76*-I82 | J77: =$F$76*-J82
B78: Ending Balance | F78: =SUM(F76:F77) | G78: =SUM(G76:G77) | H78: =SUM(H76:H77) | I78: =SUM(I76:I77) | J78: =SUM(J76:J77)
B80: Interest Expense | F80: =F76*$L$80 | G80: =G76*$L$80 | H80: =H76*$L$80 | I80: =I76*$L$80 | J80: =J76*$L$80 | L80: 0.14 | M80: Interest Rate
B82: Amortization Schedule | F82: 0 | G82: 0 | H82: 0.33333333 | I82: 0.33333333 | J82: 0.33333333 | L82: =IF(SUM(F82:J82)=100%,"Check","Paydown doesn't add to 100%") | O82: *Adjust amort schedule to account for term and amort of term loan debt. For bank lenders, we often see amortization schedules of 20%|20%|20%|20%|20% for non bank lenders we often see 0%|0%|0%|0%|100%.
B84: Seller Debt | N84: `
B85: Balance | F85: =C17 | G85: =F87 | H85: =G87 | I85: =H87 | J85: =I87
B86: (-) Paydown | F86: =$F$85*-F91 | G86: =$F$85*-G91 | H86: =$F$85*-H91 | I86: =$F$85*-I91 | J86: =$F$85*-J91
B87: Ending Balance | F87: =SUM(F85:F86) | G87: =SUM(G85:G86) | H87: =SUM(H85:H86) | I87: =SUM(I85:I86) | J87: =SUM(J85:J86)
B89: Interest Expense | F89: =$L$89*F85 | G89: =$L$89*G85 | H89: =$L$89*H85 | I89: =$L$89*I85 | J89: =$L$89*J85 | L89: 0.08 | M89: Interest Rate
B91: Amortization Schedule | F91: 0 | G91: 0 | H91: 0 | I91: 0 | J91: 1 | L91: =IF(SUM(F91:J91)=100%,"Check","Paydown doesn't add to 100%") | O91: *Adjust amort schedule to account for term and amort of seller debt. It is difficult to have seller debt amortize while term loan debt is still outstanding.
B93: Debt Metrics
B94: Total Senior Leverage | F94: =F78/F43 | G94: =G78/G43 | H94: =H78/H43 | I94: =I78/I43 | J94: =J78/J43 | O94: *These are examples of metrics that may be tested as covenants in term loan agreements. These are more typical for EBITDA based debt. ARR debt covenants may include tests of retention, profitability, and liquidity.
B95: Total Leverage | F95: =(F78+F87)/F43 | G95: =(G78+G87)/G43 | H95: =(H78+H87)/H43 | I95: =(I78+I87)/I43 | J95: =(J78+J87)/J43
B96: Fixed Charge Coverage Ratio | F96: =F40/(-F77+F80+-F86+F89-F58-F50+F69-F62) | G96: =G40/(-G77+G80+-G86+G89-G58-G50+G69-G62) | H96: =H40/(-H77+H80+-H86+H89-H58-H50+H69-H62) | I96: =I40/(-I77+I80+-I86+I89-I58-I50+I69-I62) | J96: =J40/(-J77+J80+-J86+J89-J58-J50+J69-J62)
B98: Returns Analysis - 5 Year Hold
A100: x | B100: Deal Structure
B102: Searcher(s) Common Equity | D102: 0.25 | F102: Circuit Breaker (0=Off) | H102: 1 | O102: *If the model is getting errors turn this to 0 and back to 1.
B103: Vested Employee Incentive Pool | D103: 0.05 | O103: *25% equity for solo searches and 30% for partnered searches.
F104: Search Capital | H104: 500
B105: Searcher(s) Equity (at close) | D105: =$D$102/3 | F105: Step-Up | H105: 1.5
B106: Searcher(s) Equity (time vest) | D106: =$D$102/3
B107: Searcher(s) Equity (performance) | D107: =$D$102/3 | F107: Investor Cap Gains Rate | H107: 0.3
B108: Total | D108: =SUM(D105:D107)
B110: Minimum IRR Hurdle | D110: 0.2 | H110: Vested | I110: Total | J110: %
B111: Maximum IRR Hurdle | D111: 0.35 | F111: Preferred Units | H111: =I111 | I111: =F117*1000 | J111: =1-D102
F112: Common Units | H112: =I112*D114/D108 | I112: =I113-I111 | J112: =I112/I113
B113: Vested Performance Equity | D113: =IF(J146>D111,D107,IF(J146<D110,0,(J146-D110)/(D111-D110))*D107) | F113: Total | H113: =SUM(H111:H112) | I113: =I111/J111 | J113: =I113/I113
B114: Total Searcher Vested Equity | D114: =D113+D106+D105
B116: Preferred Equity
B117: Beginning Balance | F117: =C23+(H105*H104) | G117: =F120 | H117: =G120 | I117: =H120 | J117: =I120
B118: (+) Preferred Return | D118: 0.08 | F118: =F117*$D$118 | G118: =G117*$D$118 | H118: =H117*$D$118 | I118: =I117*$D$118 | J118: =J117*$D$118
B119: (-) Distributions | F119: =-F69 | G119: =-G69 | H119: =-H69 | I119: =-I69 | J119: =-J69
B120: Ending Balance | F120: =SUM(F117:F119) | G120: =SUM(G117:G119) | H120: =SUM(H117:H119) | I120: =SUM(I117:I119) | J120: =SUM(J117:J119)
B122: Earnout | F122: =IF(N26=1,IF(F37>N28,N27,0),0)
A124: x | B124: Exit Waterfall & Returns
B126: =CONCATENATE("LTM "&N129&"") | J126: =IF(N128="EBITDA",J40,J34) | L126: Exit Assumptions
B127: (x) Multiple | J127: =N131 | L127: TEV @ Entry | N127: =N15
B128: Total Enterprise Value | J128: =J126*J127 | L128: Multiple @ Entry | N128: =N16
B129: (+) Cash | J129: =J70 | L129: Multiple @ Exit | N129: =N128
B130: (-) Debt | J130: =-J78-J87 | L130: Entry Multiple | N130: =IF(N128="EBITDA",N127/E40,N127/E34)
B131: Total Equity Value | J131: =SUM(J128:J130) | L131: Exit Multiple | N131: =N130 | O131: *For base case, we don't recommend underwriting to multiple expansion; this can be upside at exit.
B132: (-) Preferred Return | J132: =MAX(MIN(J120-F117,J131),0) | L132: Searcher(s) Catch Up | N132: 1
B133: (-) Return of Capital | J133: =MIN(MIN(F117,J131-J132),J120)
...

Sheet Value
A2: x | B2: G&B Model Template
B4: Instructions
B5: 1. Fill out historical Revenue and EBITDA. Project Revenue and EBITDA for the 5 year period.
B6: 2. Fill out the transaction assumptions with TEV & leverage and other key structure information.
B7: 3. Adjust the remaining assumptions in the yellow boxes for the cash flow statement and debt schedule as appropriate.
B8: 4. Check the "check" to make sure your business has the cash flow profile to support your capital structure.
B9: 5. Modify the deal structure and exit assumptions if needed. Note: If the model is getting errors, turn the circuit breaker to 0 and back to 1.
B10: 6. Evaluate the returns.
B12: $000s unless otherwise indicated | L12: Check | N12: =IF(SUM(F67:J67)>0,"Cash Shortfall","OK") | O12: *Check here to make sure your business has enough cash flow to support the capital structure.
A14: x | B14: Sources | G14: Uses | L14: Transaction Assumptions
C15: Amount | D15: =CONCATENATE("x",$N$16) | E15: % of Total | H15: Amount | I15: =CONCATENATE("x",$N$16) | J15: % of Total | L15: TEV | N15: =E40*8 | O15: *Refer to the Search Fund Study to understand median multiples, revenue, EBITDA, and more.
B16: Term Debt | C16: =D16*E40 | D16: =N20 | E16: =C16/C25 | G16: TEV | H16: =N15 | I16: =H16/$N$17 | J16: =H16/$H$25 | L16: Entry Multiple | N16: EBITDA
B17: Seller Debt | C17: =N21 | D17: =C17/$N$17 | E17: =C17/C25 | G17: Fees | H17: =H16*N19 | I17: =H17/$N$17 | J17: =H17/$H$25 | L17: =IF(N16="ARR","Ending ARR","LTM EBITDA") | N17: =IF(N16="ARR",E34,E40)
B18: Total Debt | C18: =SUM(C16:C17) | D18: =C18/$N$17 | E18: =C18/$C$25 | G18: Cash to B/S | H18: =N22 | I18: =H18/$N$17 | J18: =H18/$H$25 | L18: LTM Period | N18: 46022 | O18: 2024 Search Fund Study | Stanford Graduate School of Business
L19: Transaction Costs | N19: 0.05
B20: Equity | D20: % of Equity | L20: =CONCATENATE("Term Debt x",N16) | N20: 3
B21: Seller Equity Rollover | C21: =D21*C23 | D21: =N25 | E21: =C21/C25 | L21: Seller Debt Quantum | N21: 1500
B22: Investor Equity | C22: =D22*C23 | D22: =1-D21 | E22: =C22/C25 | L22: Cash to B/S | N22: 200 | O22: *Typically, searcher(s) put de minimis cash on the balance sheet.
B23: Total Equity | C23: =C25-C18 | D23: =SUM(C21:C22)/C23 | E23: =C23/C25 | L23: ECF Distribution | N23: 0 | O23: *Toggle this to distribute 1/3 of accumulated cash in Year 3 & 4.
L24: LLC/C-corp | N24: C-corp | O24: *To qualify for QSBS, TEV must be <$70M you must be a C-corp and fit certain industry requirements (many except financial and professional services firms, certain categories of healthcare, and certain other excluded businesses).
B25: Total Sources | C25: =H25 | D25: =C25/$N$17 | E25: =C25/$H$25 | G25: Total Uses | H25: =SUM(H16:H18) | I25: =H25/$N$17 | J25: =H25/$H$25 | L25: Seller Equity Rollover | N25: 0.1 | O25: QSBS | Insights | Holland & Knight
L26: Earnout | N26: 0 | O26: *This is meant to be a simple example of an earnout; earnout structures can vary.
L27: Earnout Amount | N27: 500
B28: Summary Financials | L28: Y1 Revenue Threshold | N28: 6000
E30: TXN Close | J30: TXN + 5
A31: x | B31: Income Statement | L31: Assumptions & BK Growth Notes
C33: =EDATE(D33,-12) | D33: =EDATE(E33,-12) | E33: =N18 | F33: =EDATE(E33,12) | G33: =EDATE(F33,12) | H33: =EDATE(G33,12) | I33: =EDATE(H33,12) | J33: =EDATE(I33,12) | L33: CAGR
B34: Ending ARR | C34: 9796 | D34: 11304 | E34: 12700 | F34: =E34*(1+F35) | G34: =F34*(1+G35) | H34: =G34*(1+H35) | I34: =H34*(1+I35) | J34: =I34*(1+J35) | L34: =_xlfn.RRI(2,C34,E34) | O34: *Use this if you are looking at an ARR multiple deal. Revenue for a period is calculated as the average of beginning and ending ARR.
B35: Growth | D35: =D34/C34-1 | E35: =E34/D34-1 | F35: 0.060185827 | G35: 0.17641857 | H35: 0.10904284 | I35: 0.20594697 | J35: 0.12189968
B37: GAAP Revenue | C37: 12300 | D37: 18117 | E37: 18575 | F37: =IF(N16="ARR",AVERAGE(F34,E34),E37*(1+F38)) | G37: =IF(O16="ARR",AVERAGE(G34,F34),F37*(1+G38)) | H37: =IF(P16="ARR",AVERAGE(H34,G34),G37*(1+H38)) | I37: =IF(Q16="ARR",AVERAGE(I34,H34),H37*(1+I38)) | J37: =IF(R16="ARR",AVERAGE(J34,I34),I37*(1+J38)) | L37: =_xlfn.RRI(2,C37,E37) | O37: *It is difficult to accelerate the growth of a business that is not already consistently growing at a solid pace.
B38: Growth | D38: =D37/C37-1 | E38: =E37/D37-1 | F38: 0.05 | G38: 0.2 | H38: 0.2 | I38: 0.2 | J38: 0.2 | O38: *Forecast revenue here if you are looking at an EBITDA multiple deal. For an ARR deal, you do not need historical revenue numbers.
B40: GAAP EBITDA | C40: 1190 | D40: 3224 | E40: 3363 | F40: =F41*F37 | G40: =G41*G37 | H40: =H41*H37 | I40: =I41*I37 | J40: =J41*J37 | L40: =_xlfn.RRI(2,C40,E40) | O40: *In the short/medium run, margins in ETA often decline and remain lower than historical margins (see research linked below for more). We rarely see a search fund business of scale with margins greater than 35%.
B41: Margin | C41: =C40/C37 | D41: =D40/D37 | E41: =E40/E37 | F41: 0.2 | G41: 0.25 | H41: 0.25 | I41: 0.3 | J41: 0.33 | O41: Research on EBITDA Margins in ETA - Thomas, Stevens, & Wasserstein
B43: GAAP EBITDA | F43: =F40 | G43: =G40 | H43: =H40 | I43: =I40 | J43: =J40
B44: Depreciation | F44: =-($L$44*F37) | G44: =-($L$44*G37) | H44: =-($L$44*H37) | I44: =-($L$44*I37) | J44: =-($L$44*J37) | L44: 0.01 | M44: % of Revenue | O44: *For asset-light search fund target businesses, depreciation will likely be minimal at around ~1-3% of revenue.
B45: EBIT | F45: =SUM(F43:F44) | G45: =SUM(G43:G44) | H45: =SUM(H43:H44) | I45: =SUM(I43:I44) | J45: =SUM(J43:J44)
B47: Interest | F47: =-F80-F89 | G47: =-G80-G89 | H47: =-H80-H89 | I47: =-I80-I89 | J47: =-J80-J89
B48: EBT | F48: =F45+F47 | G48: =G45+G47 | H48: =H45+H47 | I48: =I45+I47 | J48: =J45+J47
B50: Taxes Owed / Distributed | E50: =IF(N24="LLC",45%,26.5%) | F50: =-$E$50*F48 | G50: =-$E$50*G48 | H50: =-$E$50*H48 | I50: =-$E$50*I48 | J50: =-$E$50*J48
B51: Net Income | F51: =F48+F50 | G51: =G48+G50 | H51: =H48+H50 | I51: =I48+I50 | J51: =J48+J50
A53: x | B53: Cash Flow Statement
B55: Net Income | F55: =F51 | G55: =G51 | H55: =H51 | I55: =I51 | J55: =J51
B56: (+) D&A | F56: =-SUM(F44:F44) | G56: =-SUM(G44:G44) | H56: =-SUM(H44:H44) | I56: =-SUM(I44:I44) | J56: =-SUM(J44:J44) | O56: *You may be able to amortize a portion of the purchase price. This should be further diligenced with your legal counsel.
B57: (+) NWC | F57: =$L$57*F37 | G57: =$L$57*G37 | H57: =$L$57*H37 | I57: =$L$57*I37 | J57: =$L$57*J37 | L57: 0.01 | M57: % of Revenue | O57: *For asset-light search fund target businesses, we recommend modeling this as a 1% of revenue source of cash to be conservative.
B58: (-) CAPEX | F58: =-$L$58*F37 | G58: =-$L$58*G37 | H58: =-$L$58*H37 | I58: =-$L$58*I37 | J58: =-$L$58*J37 | L58: 0.01 | M58: % of Revenue | O58: *For asset-light search fund target businesses, CAPEX will likely be minimal at around ~1-3% of revenue.
B59: (-) Debt Paydown | F59: =F77+F86 | G59: =G77+G86 | H59: =H77+H86 | I59: =I77+I86 | J59: =J77+J86
B60: Cash after Debt | F60: =SUM(F55:F59) | G60: =SUM(G55:G59) | H60: =SUM(H55:H59) | I60: =SUM(I55:I59) | J60: =SUM(J55:J59)
B62: Cash for Earnout | F62: =-F122
B64: Beginning Cash | F64: =N22 | G64: =F70 | H64: =G70 | I64: =H70 | J64: =I70
B65: (+/-) Change in Cash | F65: =F60+F62 | G65: =G60++G62 | H65: =H60++H62 | I65: =I60++I62 | J65: =J60++J62
B66: Ending Cash before Distributions | F66: =SUM(F64:F65) | G66: =SUM(G64:G65) | H66: =SUM(H64:H65) | I66: =SUM(I64:I65) | J66: =SUM(J64:J65)
B67: Check | F67: =IF(F66<0,1,0) | G67: =IF(G66<0,1,0) | H67: =IF(H66<0,1,0) | I67: =IF(I66<0,1,0) | J67: =IF(J66<0,1,0)
B69: (-)Distributions | F69: 0 | G69: 0 | H69: =MAX(IF($N$23=1,1/3*H66,0),0) | I69: =MAX(IF($N$23=1,1/3*I66,0),0) | J69: 0
B70: Ending Cash after Distributions | F70: =F66-F69 | G70: =G66-G69 | H70: =H66-H69 | I70: =I66-I69 | J70: =J66-J69
A73: x | B73: Debt Schedule
B75: Term Loan
B76: Beginning Balance | F76: =C16 | G76: =F78 | H76: =G78 | I76: =H78 | J76: =I78
B77: (-) Mandatory Amortization | F77: =$F$76*-F82 | G77: =$F$76*-G82 | H77: =$F$76*-H82 | I77: =$F$76*-I82 | J77: =$F$76*-J82
B78: Ending Balance | F78: =SUM(F76:F77) | G78: =SUM(G76:G77) | H78: =SUM(H76:H77) | I78: =SUM(I76:I77) | J78: =SUM(J76:J77)
B80: Interest Expense | F80: =F76*$L$80 | G80: =G76*$L$80 | H80: =H76*$L$80 | I80: =I76*$L$80 | J80: =J76*$L$80 | L80: 0.12 | M80: Interest Rate
B82: Amortization Schedule | F82: 0 | G82: 0 | H82: 0 | I82: 0 | J82: 1 | L82: =IF(SUM(F82:J82)=100%,"Check","Paydown doesn't add to 100%") | O82: *Adjust amort schedule to account for term and amort of term loan debt. For bank lenders, we often see amortization schedules of 20%|20%|20%|20%|20% for non bank lenders we often see 0%|0%|0%|0%|100%.
B84: Seller Debt | N84: `
B85: Balance | F85: =C17 | G85: =F87 | H85: =G87 | I85: =H87 | J85: =I87
B86: (-) Paydown | F86: =$F$85*-F91 | G86: =$F$85*-G91 | H86: =$F$85*-H91 | I86: =$F$85*-I91 | J86: =$F$85*-J91
B87: Ending Balance | F87: =SUM(F85:F86) | G87: =SUM(G85:G86) | H87: =SUM(H85:H86) | I87: =SUM(I85:I86) | J87: =SUM(J85:J86)
B89: Interest Expense | F89: =$L$89*F85 | G89: =$L$89*G85 | H89: =$L$89*H85 | I89: =$L$89*I85 | J89: =$L$89*J85 | L89: 0.08 | M89: Interest Rate
B91: Amortization Schedule | F91: 0 | G91: 0 | H91: 0 | I91: 0 | J91: 1 | L91: =IF(SUM(F91:J91)=100%,"Check","Paydown doesn't add to 100%") | O91: *Adjust amort schedule to account for term and amort of seller debt. It is difficult to have seller debt amortize while term loan debt is still outstanding.
B93: Debt Metrics
B94: Total Senior Leverage | F94: =F78/F43 | G94: =G78/G43 | H94: =H78/H43 | I94: =I78/I43 | J94: =J78/J43 | O94: *These are examples of metrics that may be tested as covenants in term loan agreements. These are more typical for EBITDA based debt. ARR debt covenants may include tests of retention, profitability, and liquidity.
B95: Total Leverage | F95: =(F78+F87)/F43 | G95: =(G78+G87)/G43 | H95: =(H78+H87)/H43 | I95: =(I78+I87)/I43 | J95: =(J78+J87)/J43
B96: Fixed Charge Coverage Ratio | F96: =F40/(-F77+F80+-F86+F89-F58-F50+F69-F62) | G96: =G40/(-G77+G80+-G86+G89-G58-G50+G69-G62) | H96: =H40/(-H77+H80+-H86+H89-H58-H50+H69-H62) | I96: =I40/(-I77+I80+-I86+I89-I58-I50+I69-I62) | J96: =J40/(-J77+J80+-J86+J89-J58-J50+J69-J62)
B98: Returns Analysis - 5 Year Hold
A100: x | B100: Deal Structure
B102: Searcher(s) Common Equity | D102: 0.25 | F102: Circuit Breaker (0=Off) | H102: 1 | O102: *If the model is getting errors turn this to 0 and back to 1.
B103: Vested Employee Incentive Pool | D103: 0.05 | O103: *25% equity for solo searches and 30% for partnered searches.
F104: Search Capital | H104: 500
B105: Searcher(s) Equity (at close) | D105: =$D$102/3 | F105: Step-Up | H105: 1.5
B106: Searcher(s) Equity (time vest) | D106: =$D$102/3
B107: Searcher(s) Equity (performance) | D107: =$D$102/3 | F107: Investor Cap Gains Rate | H107: 0.3
B108: Total | D108: =SUM(D105:D107)
B110: Minimum IRR Hurdle | D110: 0.2 | H110: Vested | I110: Total | J110: %
B111: Maximum IRR Hurdle | D111: 0.35 | F111: Preferred Units | H111: =I111 | I111: =F117*1000 | J111: =1-D102
F112: Common Units | H112: =I112*D114/D108 | I112: =I113-I111 | J112: =I112/I113
B113: Vested Performance Equity | D113: =IF(J146>D111,D107,IF(J146<D110,0,(J146-D110)/(D111-D110))*D107) | F113: Total | H113: =SUM(H111:H112) | I113: =I111/J111 | J113: =I113/I113
B114: Total Searcher Vested Equity | D114: =D113+D106+D105
B116: Preferred Equity
B117: Beginning Balance | F117: =C23+(H105*H104) | G117: =F120 | H117: =G120 | I117: =H120 | J117: =I120
B118: (+) Preferred Return | D118: 0.08 | F118: =F117*$D$118 | G118: =G117*$D$118 | H118: =H117*$D$118 | I118: =I117*$D$118 | J118: =J117*$D$118
B119: (-) Distributions | F119: =-F69 | G119: =-G69 | H119: =-H69 | I119: =-I69 | J119: =-J69
B120: Ending Balance | F120: =SUM(F117:F119) | G120: =SUM(G117:G119) | H120: =SUM(H117:H119) | I120: =SUM(I117:I119) | J120: =SUM(J117:J119)
B122: Earnout | F122: =IF(N26=1,IF(F37>N28,N27,0),0)
A124: x | B124: Exit Waterfall & Returns
B126: =CONCATENATE("LTM "&N129&"") | J126: =IF(N128="EBITDA",J40,J34) | L126: Exit Assumptions
B127: (x) Multiple | J127: =N131 | L127: TEV @ Entry | N127: =N15
B128: Total Enterprise Value | J128: =J126*J127 | L128: Multiple @ Entry | N128: =N16
B129: (+) Cash | J129: =J70 | L129: Multiple @ Exit | N129: =N128
B130: (-) Debt | J130: =-J78-J87 | L130: Entry Multiple | N130: =IF(N128="EBITDA",N127/E40,N127/E34)
B131: Total Equity Value | J131: =SUM(J128:J130) | L131: Exit Multiple | N131: 8 | O131: *For base case, we don't recommend underwriting to multiple expansion; this can be upside at exit.
B132: (-) Preferred Return | J132: =MAX(MIN(J120-F117,J131),0) | L132: Searcher(s) Catch Up | N132: 1
B133: (-) Return of Capital | J133: =MIN(MIN(F117,J131-J132),J120)
...

Sheet Raw 2025 IS
A1: 2025 Income Statement
A3: (in 000's) | B3: 2025 Actual | C3: 2025 Plan | D3: 2025 Actual vs Plan Variance | E3: % | F3: 2024 Actual | G3: 2025 Actual vs 2024 Actual | H3: %
A4: Core Sales | B4: 18575 | C4: 18500 | D4: 75 | E4: 0 | F4: 18117 | G4: 457 | H4: 0.03
A5: Net Other | B5: -13 | C5: 76 | D5: -88 | E5: -1.17 | F5: 158 | G5: -171 | H5: -1.08
A6: Gross Margin | B6: 11647 | C6: 11592 | D6: 55 | E6: 0 | F6: 11401 | G6: 246 | H6: 0.02
A7: Core Magin % | B7: 0.628 | C7: 0.623 | D7: 0.005 | E7: 0.01 | F7: 0.621 | G7: 0.007 | H7: 0.01
A8: Employee | B8: 3796 | C8: 3859 | D8: -64 | E8: -0.02 | F8: 3922 | G8: -127 | H8: -0.03
A9: Marketing | B9: 1551 | C9: 1800 | D9: -249 | E9: -0.14 | F9: 1376 | G9: 175 | H9: 0.13
A10: Admin | B10: 1731 | C10: 1753 | D10: -22 | E10: -0.01 | F10: 1688 | G10: 43 | H10: 0.03
A11: Consulting | B11: 494 | C11: 522 | D11: -29 | E11: -0.05 | F11: 575 | G11: -81 | H11: -0.14
A12: Fees | B12: 600 | C12: 476 | D12: 124 | E12: 0.26 | F12: 455 | G12: 146 | H12: 0.32
A13: Travel | B13: 113 | C13: 181 | D13: -68 | E13: -0.38 | F13: 162 | G13: -49 | H13: -0.3
A14: EBITDA | B14: 3363 | C14: 3000 | D14: 363 | E14: 0.12 | F14: 3224 | G14: 140 | H14: 0.04
A15: Charity | B15: 601 | C15: 557 | D15: 44 | E15: 0.08 | F15: 558 | G15: 43 | H15: 0.08
... A17: Net Income | B17: 2717 | C17: 2399 | D17: 318 | E17: 0.13 | F17: 2616 | G17: 101 | H17: 0.04

Sheet Raw 2024 CF
A1: 2024 Cash Flow Statement
A3: (in 000's) | B3: 2024 Actual | C3: 2023 Actual | D3: Change YOY
A4: Beginning Cash | B4: 2836 | C4: 5033 | D4: -2197
A5: EBITDA | B5: 3224 | C5: 1190 | D5: 2034
A6: Increase in Receivables | B6: -651 | C6: -261 | D6: -390
A7: Purchases of inventory | B7: -501 | C7: -1584 | D7: 1083
A8: Change in Payables | B8: 305 | C8: -101 | D8: 406
A9: Other working capital | B9: 328 | C9: -750 | D9: 1077
A10: Free cash generated (used) | B10: 2705 | C10: -1506 | D10: 4210
A11: Contributions | B11: -558 | C11: -339 | D11: -219
A12: Fixed asset additions | B12: -25 | C12: -20 | D12: -5
A13: Repayment of loan | B13: -486 | C13: -348 | D13: -138
A14: State income tax payments | B14: -46 | C14: 16 | D14: -62
A15: Total cash generated (used) | B15: 1589 | C15: -2197 | D15: 3786
A16: End Cash | B16: 4426 | C16: 2836 | D16: 1589

Sheet Raw 2024 IS
A1: 2024 Income Statement
A3: (in 000's) | B3: 2024 Actual | C3: 2024 Plan | D3: 2024 Actual vs Plan Variance | E3: % | F3: 2023 Actual | G3: 2024 Actual vs 2023 Actual | H3: %
A4: Core Sales | B4: 18117 | C4: 13750 | D4: 4367 | E4: 0.32 | F4: 12300 | G4: 5817 | H4: 0.47
A5: Net Other | B5: 158 | C5: 96 | D5: 62 | E5: 0.64 | F5: -21 | G5: 179 | H5: --
A6: Gross Margin | B6: 11401 | C6: 8726 | D6: 2675 | E6: 0.31 | F6: 7675 | G6: 3726 | H6: 0.49
A7: Core Magin % | B7: 0.621 | C7: 0.628 | D7: -0.007 | E7: -0.01 | F7: 0.626 | G7: -0.005 | H7: -0.01
A8: Employee | B8: 3922 | C8: 3562 | D8: 360 | E8: 0.1 | F8: 3193 | G8: 729 | H8: 0.23
A9: Marketing | B9: 1376 | C9: 1374 | D9: 1 | E9: 0 | F9: 887 | G9: 488 | H9: 0.55
A10: Admin | B10: 1688 | C10: 1636 | D10: 52 | E10: 0.03 | F10: 1572 | G10: 116 | H10: 0.07
A11: Consulting | B11: 575 | C11: 492 | D11: 83 | E11: 0.17 | F11: 408 | G11: 167 | H11: 0.41
A12: Fees | B12: 455 | C12: 375 | D12: 80 | E12: 0.21 | F12: 344 | G12: 111 | H12: 0.32
A13: Travel | B13: 162 | C13: 170 | D13: -8 | E13: -0.05 | F13: 81 | G13: 81 | H13: 0.99
A14: EBITDA | B14: 3224 | C14: 1118 | D14: 2106 | E14: 1.88 | F14: 1190 | G14: 2034 | H14: 1.71
A15: Charity | B15: 558 | C15: 350 | D15: 208 | E15: 0.59 | F15: 339 | G15: 219 | H15: 0.65
A16: Depreciation | B16: 49 | C16: 61 | D16: -12 | E16: -0.19 | F16: 71 | G16: -21 | H16: -0.3
A17: Net Income | B17: 2616 | C17: 707 | D17: 1909 | E17: 2.7 | F17: 780 | G17: 1836 | H17: 2.35

Sheet Raw 2025 CF
A1: 2025 Cash Flow Statement
A3: (in 000's) | B3: 2025 Actual | C3: 2024 Actual | D3: Change YOY
A4: Beginning Cash | B4: 4426 | C4: 2836 | D4: 1589
A5: EBITDA | B5: 3363 | C5: 3224 | D5: 140
A6: Change in Receivables | B6: 539 | C6: -651 | D6: 1190
A7: Purchases of inventory | B7: -282 | C7: -501 | D7: 218
A8: Change in Payables | B8: -501 | C8: 305 | D8: -806
A9: Other working capital | B9: 148 | C9: 328 | D9: -180
A10: Free cash generated (used) | B10: 3267 | C10: 2705 | D10: 562
A11: Contributions | B11: -601 | C11: -558 | D11: -43
A12: Fixed asset additions | B12: -12 | C12: -25 | D12: 13
A13: Repayment of loan | B13: -435 | C13: -486 | D13: 51
A14: Income tax payments | B14: -1141 | C14: -46 | D14: -1095
A15: Total cash generated (used) | B15: 1078 | C15: 1589 | D15: -511
A16: End Cash | B16: 5504 | C16: 4426 | D16: 1078

Sheet Downside Case
A2: x | B2: G&B Model Template
B4: Instructions
B5: 1. Fill out historical Revenue and EBITDA. Project Revenue and EBITDA for the 5 year period.
B6: 2. Fill out the transaction assumptions with TEV & leverage and other key structure information.
B7: 3. Adjust the remaining assumptions in the yellow boxes for the cash flow statement and debt schedule as appropriate.
B8: 4. Check the "check" to make sure your business has the cash flow profile to support your capital structure.
B9: 5. Modify the deal structure and exit assumptions if needed. Note: If the model is getting errors, turn the circuit breaker to 0 and back to 1.
B10: 6. Evaluate the returns.
B12: $000s unless otherwise indicated | L12: Check | N12: =IF(SUM(F67:J67)>0,"Cash Shortfall","OK") | O12: *Check here to make sure your business has enough cash flow to support the capital structure.
A14: x | B14: Sources | G14: Uses | L14: Transaction Assumptions
C15: Amount | D15: =CONCATENATE("x",$N$16) | E15: % of Total | H15: Amount | I15: =CONCATENATE("x",$N$16) | J15: % of Total | L15: TEV | N15: =E40*2.5 | O15: *Refer to the Search Fund Study to understand median multiples, revenue, EBITDA, and more.
B16: Term Debt | C16: =D16*E40 | D16: =N20 | E16: =C16/C25 | G16: TEV | H16: =N15 | I16: =H16/$N$17 | J16: =H16/$H$25 | L16: Entry Multiple | N16: EBITDA
B17: Seller Debt | C17: =N21 | D17: =C17/$N$17 | E17: =C17/C25 | G17: Fees | H17: =H16*N19 | I17: =H17/$N$17 | J17: =H17/$H$25 | L17: =IF(N16="ARR","Ending ARR","LTM EBITDA") | N17: =IF(N16="ARR",E34,E40)
B18: Total Debt | C18: =SUM(C16:C17) | D18: =C18/$N$17 | E18: =C18/$C$25 | G18: Cash to B/S | H18: =N22 | I18: =H18/$N$17 | J18: =H18/$H$25 | L18: LTM Period | N18: 46022 | O18: 2024 Search Fund Study | Stanford Graduate School of Business
L19: Transaction Costs | N19: 0.05
B20: Equity | D20: % of Equity | L20: =CONCATENATE("Term Debt x",N16) | N20: 1.5
B21: Seller Equity Rollover | C21: =D21*C23 | D21: =N25 | E21: =C21/C25 | L21: Seller Debt Quantum | N21: 1000
B22: Investor Equity | C22: =D22*C23 | D22: =1-D21 | E22: =C22/C25 | L22: Cash to B/S | N22: 1500 | O22: *Typically, searcher(s) put de minimis cash on the balance sheet.
B23: Total Equity | C23: =C25-C18 | D23: =SUM(C21:C22)/C23 | E23: =C23/C25 | L23: ECF Distribution | N23: 0 | O23: *Toggle this to distribute 1/3 of accumulated cash in Year 3 & 4.
L24: LLC/C-corp | N24: C-corp | O24: *To qualify for QSBS, TEV must be <$70M you must be a C-corp and fit certain industry requirements (many except financial and professional services firms, certain categories of healthcare, and certain other excluded businesses).
B25: Total Sources | C25: =H25 | D25: =C25/$N$17 | E25: =C25/$H$25 | G25: Total Uses | H25: =SUM(H16:H18) | I25: =H25/$N$17 | J25: =H25/$H$25 | L25: Seller Equity Rollover | N25: 0.1 | O25: QSBS | Insights | Holland & Knight
L26: Earnout | N26: 0 | O26: *This is meant to be a simple example of an earnout; earnout structures can vary.
L27: Earnout Amount | N27: 0
B28: Summary Financials | L28: Y1 Revenue Threshold
E30: TXN Close | J30: TXN + 5
A31: x | B31: Income Statement | L31: Assumptions & BK Growth Notes
C33: =EDATE(D33,-12) | D33: =EDATE(E33,-12) | E33: =N18 | F33: =EDATE(E33,12) | G33: =EDATE(F33,12) | H33: =EDATE(G33,12) | I33: =EDATE(H33,12) | J33: =EDATE(I33,12) | L33: CAGR
B34: Ending ARR | C34: 9796 | D34: 11304 | E34: 12700 | F34: =E34*(1+F35) | G34: =F34*(1+G35) | H34: =G34*(1+H35) | I34: =H34*(1+I35) | J34: =I34*(1+J35) | L34: =_xlfn.RRI(2,C34,E34) | O34: *Use this if you are looking at an ARR multiple deal. Revenue for a period is calculated as the average of beginning and ending ARR.
B35: Growth | D35: =D34/C34-1 | E35: =E34/D34-1 | F35: 0.060185827 | G35: 0.17641857 | H35: 0.10904284 | I35: 0.20594697 | J35: 0.12189968
B37: GAAP Revenue | C37: 12300 | D37: 18117 | E37: 18575 | F37: =IF(N16="ARR",AVERAGE(F34,E34),E37*(1+F38)) | G37: =IF(O16="ARR",AVERAGE(G34,F34),F37*(1+G38)) | H37: =IF(P16="ARR",AVERAGE(H34,G34),G37*(1+H38)) | I37: =IF(Q16="ARR",AVERAGE(I34,H34),H37*(1+I38)) | J37: =IF(R16="ARR",AVERAGE(J34,I34),I37*(1+J38)) | L37: =_xlfn.RRI(2,C37,E37) | O37: *It is difficult to accelerate the growth of a business that is not already consistently growing at a solid pace.
B38: Growth | D38: =D37/C37-1 | E38: =E37/D37-1 | F38: 0 | G38: 0.01 | H38: 0.01 | I38: 0.01 | J38: 0.01 | O38: *Forecast revenue here if you are looking at an EBITDA multiple deal. For an ARR deal, you do not need historical revenue numbers.
B40: GAAP EBITDA | C40: 1190 | D40: 3224 | E40: 3363 | F40: =F41*F37 | G40: =G41*G37 | H40: =H41*H37 | I40: =I41*I37 | J40: =J41*J37 | L40: =_xlfn.RRI(2,C40,E40) | O40: *In the short/medium run, margins in ETA often decline and remain lower than historical margins (see research linked below for more). We rarely see a search fund business of scale with margins greater than 35%.
B41: Margin | C41: =C40/C37 | D41: =D40/D37 | E41: =E40/E37 | F41: 0.18 | G41: 0.18 | H41: 0.18 | I41: 0.18 | J41: 0.18 | O41: Research on EBITDA Margins in ETA - Thomas, Stevens, & Wasserstein
B43: GAAP EBITDA | F43: =F40 | G43: =G40 | H43: =H40 | I43: =I40 | J43: =J40
B44: Depreciation | F44: =-($L$44*F37) | G44: =-($L$44*G37) | H44: =-($L$44*H37) | I44: =-($L$44*I37) | J44: =-($L$44*J37) | L44: 0.01 | M44: % of Revenue | O44: *For asset-light search fund target businesses, depreciation will likely be minimal at around ~1-3% of revenue.
B45: EBIT | F45: =SUM(F43:F44) | G45: =SUM(G43:G44) | H45: =SUM(H43:H44) | I45: =SUM(I43:I44) | J45: =SUM(J43:J44)
B47: Interest | F47: =-F80-F89 | G47: =-G80-G89 | H47: =-H80-H89 | I47: =-I80-I89 | J47: =-J80-J89
B48: EBT | F48: =F45+F47 | G48: =G45+G47 | H48: =H45+H47 | I48: =I45+I47 | J48: =J45+J47
B50: Taxes Owed / Distributed | E50: =IF(N24="LLC",45%,26.5%) | F50: =-$E$50*F48 | G50: =-$E$50*G48 | H50: =-$E$50*H48 | I50: =-$E$50*I48 | J50: =-$E$50*J48
B51: Net Income | F51: =F48+F50 | G51: =G48+G50 | H51: =H48+H50 | I51: =I48+I50 | J51: =J48+J50
A53: x | B53: Cash Flow Statement
B55: Net Income | F55: =F51 | G55: =G51 | H55: =H51 | I55: =I51 | J55: =J51
B56: (+) D&A | F56: =-SUM(F44:F44) | G56: =-SUM(G44:G44) | H56: =-SUM(H44:H44) | I56: =-SUM(I44:I44) | J56: =-SUM(J44:J44) | O56: *You may be able to amortize a portion of the purchase price. This should be further diligenced with your legal counsel.
B57: (+) NWC | F57: =$L$57*F37 | G57: =$L$57*G37 | H57: =$L$57*H37 | I57: =$L$57*I37 | J57: =$L$57*J37 | L57: 0.01 | M57: % of Revenue | O57: *For asset-light search fund target businesses, we recommend modeling this as a 1% of revenue source of cash to be conservative.
B58: (-) CAPEX | F58: =-$L$58*F37 | G58: =-$L$58*G37 | H58: =-$L$58*H37 | I58: =-$L$58*I37 | J58: =-$L$58*J37 | L58: 0.01 | M58: % of Revenue | O58: *For asset-light search fund target businesses, CAPEX will likely be minimal at around ~1-3% of revenue.
B59: (-) Debt Paydown | F59: =F77+F86 | G59: =G77+G86 | H59: =H77+H86 | I59: =I77+I86 | J59: =J77+J86
B60: Cash after Debt | F60: =SUM(F55:F59) | G60: =SUM(G55:G59) | H60: =SUM(H55:H59) | I60: =SUM(I55:I59) | J60: =SUM(J55:J59)
B62: Cash for Earnout | F62: =-F122
B64: Beginning Cash | F64: =N22 | G64: =F70 | H64: =G70 | I64: =H70 | J64: =I70
B65: (+/-) Change in Cash | F65: =F60+F62 | G65: =G60++G62 | H65: =H60++H62 | I65: =I60++I62 | J65: =J60++J62
B66: Ending Cash before Distributions | F66: =SUM(F64:F65) | G66: =SUM(G64:G65) | H66: =SUM(H64:H65) | I66: =SUM(I64:I65) | J66: =SUM(J64:J65)
B67: Check | F67: =IF(F66<0,1,0) | G67: =IF(G66<0,1,0) | H67: =IF(H66<0,1,0) | I67: =IF(I66<0,1,0) | J67: =IF(J66<0,1,0)
B69: (-)Distributions | F69: 0 | G69: 0 | H69: =MAX(IF($N$23=1,1/3*H66,0),0) | I69: =MAX(IF($N$23=1,1/3*I66,0),0) | J69: 0
B70: Ending Cash after Distributions | F70: =F66-F69 | G70: =G66-G69 | H70: =H66-H69 | I70: =I66-I69 | J70: =J66-J69
A73: x | B73: Debt Schedule
B75: Term Loan
B76: Beginning Balance | F76: =C16 | G76: =F78 | H76: =G78 | I76: =H78 | J76: =I78
B77: (-) Mandatory Amortization | F77: =$F$76*-F82 | G77: =$F$76*-G82 | H77: =$F$76*-H82 | I77: =$F$76*-I82 | J77: =$F$76*-J82
B78: Ending Balance | F78: =SUM(F76:F77) | G78: =SUM(G76:G77) | H78: =SUM(H76:H77) | I78: =SUM(I76:I77) | J78: =SUM(J76:J77)
B80: Interest Expense | F80: =F76*$L$80 | G80: =G76*$L$80 | H80: =H76*$L$80 | I80: =I76*$L$80 | J80: =J76*$L$80 | L80: 0.12 | M80: Interest Rate
B82: Amortization Schedule | F82: 0 | G82: 0 | H82: 0 | I82: 0 | J82: 1 | L82: =IF(SUM(F82:J82)=100%,"Check","Paydown doesn't add to 100%") | O82: *Adjust amort schedule to account for term and amort of term loan debt. For bank lenders, we often see amortization schedules of 20%|20%|20%|20%|20% for non bank lenders we often see 0%|0%|0%|0%|100%.
B84: Seller Debt | N84: `
B85: Balance | F85: =C17 | G85: =F87 | H85: =G87 | I85: =H87 | J85: =I87
B86: (-) Paydown | F86: =$F$85*-F91 | G86: =$F$85*-G91 | H86: =$F$85*-H91 | I86: =$F$85*-I91 | J86: =$F$85*-J91
B87: Ending Balance | F87: =SUM(F85:F86) | G87: =SUM(G85:G86) | H87: =SUM(H85:H86) | I87: =SUM(I85:I86) | J87: =SUM(J85:J86)
B89: Interest Expense | F89: =$L$89*F85 | G89: =$L$89*G85 | H89: =$L$89*H85 | I89: =$L$89*I85 | J89: =$L$89*J85 | L89: 0.08 | M89: Interest Rate
B91: Amortization Schedule | F91: 0 | G91: 0 | H91: 0 | I91: 0 | J91: 1 | L91: =IF(SUM(F91:J91)=100%,"Check","Paydown doesn't add to 100%") | O91: *Adjust amort schedule to account for term and amort of seller debt. It is difficult to have seller debt amortize while term loan debt is still outstanding.
B93: Debt Metrics
B94: Total Senior Leverage | F94: =F78/F43 | G94: =G78/G43 | H94: =H78/H43 | I94: =I78/I43 | J94: =J78/J43 | O94: *These are examples of metrics that may be tested as covenants in term loan agreements. These are more typical for EBITDA based debt. ARR debt covenants may include tests of retention, profitability, and liquidity.
B95: Total Leverage | F95: =(F78+F87)/F43 | G95: =(G78+G87)/G43 | H95: =(H78+H87)/H43 | I95: =(I78+I87)/I43 | J95: =(J78+J87)/J43
B96: Fixed Charge Coverage Ratio | F96: =F40/(-F77+F80+-F86+F89-F58-F50+F69-F62) | G96: =G40/(-G77+G80+-G86+G89-G58-G50+G69-G62) | H96: =H40/(-H77+H80+-H86+H89-H58-H50+H69-H62) | I96: =I40/(-I77+I80+-I86+I89-I58-I50+I69-I62) | J96: =J40/(-J77+J80+-J86+J89-J58-J50+J69-J62)
B98: Returns Analysis - 5 Year Hold
A100: x | B100: Deal Structure
B102: Searcher(s) Common Equity | D102: 0.25 | F102: Circuit Breaker (0=Off) | H102: 1 | O102: *If the model is getting errors turn this to 0 and back to 1.
B103: Vested Employee Incentive Pool | D103: 0.05 | O103: *25% equity for solo searches and 30% for partnered searches.
F104: Search Capital | H104: 500
B105: Searcher(s) Equity (at close) | D105: =$D$102/3 | F105: Step-Up | H105: 1.5
B106: Searcher(s) Equity (time vest) | D106: =$D$102/3
B107: Searcher(s) Equity (performance) | D107: =$D$102/3 | F107: Investor Cap Gains Rate | H107: 0.3
B108: Total | D108: =SUM(D105:D107)
B110: Minimum IRR Hurdle | D110: 0.2 | H110: Vested | I110: Total | J110: %
B111: Maximum IRR Hurdle | D111: 0.35 | F111: Preferred Units | H111: =I111 | I111: =F117*1000 | J111: =1-D102
F112: Common Units | H112: =I112*D114/D108 | I112: =I113-I111 | J112: =I112/I113
B113: Vested Performance Equity | D113: =IF(J146>D111,D107,IF(J146<D110,0,(J146-D110)/(D111-D110))*D107) | F113: Total | H113: =SUM(H111:H112) | I113: =I111/J111 | J113: =I113/I113
B114: Total Searcher Vested Equity | D114: =D113+D106+D105
B116: Preferred Equity
B117: Beginning Balance | F117: =C23+(H105*H104) | G117: =F120 | H117: =G120 | I117: =H120 | J117: =I120
B118: (+) Preferred Return | D118: 0.08 | F118: =F117*$D$118 | G118: =G117*$D$118 | H118: =H117*$D$118 | I118: =I117*$D$118 | J118: =J117*$D$118
B119: (-) Distributions | F119: =-F69 | G119: =-G69 | H119: =-H69 | I119: =-I69 | J119: =-J69
B120: Ending Balance | F120: =SUM(F117:F119) | G120: =SUM(G117:G119) | H120: =SUM(H117:H119) | I120: =SUM(I117:I119) | J120: =SUM(J117:J119)
B122: Earnout | F122: =IF(N26=1,IF(F37>N28,N27,0),0)
A124: x | B124: Exit Waterfall & Returns
B126: =CONCATENATE("LTM "&N129&"") | J126: =IF(N128="EBITDA",J40,J34) | L126: Exit Assumptions
B127: (x) Multiple | J127: =N131 | L127: TEV @ Entry | N127: =N15
B128: Total Enterprise Value | J128: =J126*J127 | L128: Multiple @ Entry | N128: =N16
B129: (+) Cash | J129: =J70 | L129: Multiple @ Exit | N129: =N128
B130: (-) Debt | J130: =-J78-J87 | L130: Entry Multiple | N130: =IF(N128="EBITDA",N127/E40,N127/E34)
B131: Total Equity Value | J131: =SUM(J128:J130) | L131: Exit Multiple | N131: 2.5 | O131: *For base case, we don't recommend underwriting to multiple expansion; this can be upside at exit.
B132: (-) Preferred Return | J132: =MAX(MIN(J120-F117,J131),0) | L132: Searcher(s) Catch Up | N132: 1
B133: (-) Return of Capital | J133: =MIN(MIN(F117,J131-J132),J120)
...

Sheet Base Case
A2: x | B2: G&B Model Template
B4: Instructions
B5: 1. Fill out historical Revenue and EBITDA. Project Revenue and EBITDA for the 5 year period.
B6: 2. Fill out the transaction assumptions with TEV & leverage and other key structure information.
B7: 3. Adjust the remaining assumptions in the yellow boxes for the cash flow statement and debt schedule as appropriate.
B8: 4. Check the "check" to make sure your business has the cash flow profile to support your capital structure.
B9: 5. Modify the deal structure and exit assumptions if needed. Note: If the model is getting errors, turn the circuit breaker to 0 and back to 1.
B10: 6. Evaluate the returns.
B12: $000s unless otherwise indicated | L12: Check | N12: =IF(SUM(F67:J67)>0,"Cash Shortfall","OK") | O12: *Check here to make sure your business has enough cash flow to support the capital structure.
A14: x | B14: Sources | G14: Uses | L14: Transaction Assumptions
C15: Amount | D15: =CONCATENATE("x",$N$16) | E15: % of Total | H15: Amount | I15: =CONCATENATE("x",$N$16) | J15: % of Total | L15: TEV | N15: =E40*3.0 | O15: *Refer to the Search Fund Study to understand median multiples, revenue, EBITDA, and more.
B16: Term Debt | C16: =D16*E40 | D16: =N20 | E16: =C16/C25 | G16: TEV | H16: =N15 | I16: =H16/$N$17 | J16: =H16/$H$25 | L16: Entry Multiple | N16: EBITDA
B17: Seller Debt | C17: =N21 | D17: =C17/$N$17 | E17: =C17/C25 | G17: Fees | H17: =H16*N19 | I17: =H17/$N$17 | J17: =H17/$H$25 | L17: =IF(N16="ARR","Ending ARR","LTM EBITDA") | N17: =IF(N16="ARR",E34,E40)
B18: Total Debt | C18: =SUM(C16:C17) | D18: =C18/$N$17 | E18: =C18/$C$25 | G18: Cash to B/S | H18: =N22 | I18: =H18/$N$17 | J18: =H18/$H$25 | L18: LTM Period | N18: 46022 | O18: 2024 Search Fund Study | Stanford Graduate School of Business
L19: Transaction Costs | N19: 0.05
B20: Equity | D20: % of Equity | L20: =CONCATENATE("Term Debt x",N16) | N20: 2
B21: Seller Equity Rollover | C21: =D21*C23 | D21: =N25 | E21: =C21/C25 | L21: Seller Debt Quantum | N21: 1500
B22: Investor Equity | C22: =D22*C23 | D22: =1-D21 | E22: =C22/C25 | L22: Cash to B/S | N22: 1250 | O22: *Typically, searcher(s) put de minimis cash on the balance sheet.
B23: Total Equity | C23: =C25-C18 | D23: =SUM(C21:C22)/C23 | E23: =C23/C25 | L23: ECF Distribution | N23: 0 | O23: *Toggle this to distribute 1/3 of accumulated cash in Year 3 & 4.
L24: LLC/C-corp | N24: C-corp | O24: *To qualify for QSBS, TEV must be <$70M you must be a C-corp and fit certain industry requirements (many except financial and professional services firms, certain categories of healthcare, and certain other excluded businesses).
B25: Total Sources | C25: =H25 | D25: =C25/$N$17 | E25: =C25/$H$25 | G25: Total Uses | H25: =SUM(H16:H18) | I25: =H25/$N$17 | J25: =H25/$H$25 | L25: Seller Equity Rollover | N25: 0.1 | O25: QSBS | Insights | Holland & Knight
L26: Earnout | N26: 0 | O26: *This is meant to be a simple example of an earnout; earnout structures can vary.
L27: Earnout Amount | N27: 0
B28: Summary Financials | L28: Y1 Revenue Threshold
E30: TXN Close | J30: TXN + 5
A31: x | B31: Income Statement | L31: Assumptions & BK Growth Notes
C33: =EDATE(D33,-12) | D33: =EDATE(E33,-12) | E33: =N18 | F33: =EDATE(E33,12) | G33: =EDATE(F33,12) | H33: =EDATE(G33,12) | I33: =EDATE(H33,12) | J33: =EDATE(I33,12) | L33: CAGR
B34: Ending ARR | C34: 9796 | D34: 11304 | E34: 12700 | F34: =E34*(1+F35) | G34: =F34*(1+G35) | H34: =G34*(1+H35) | I34: =H34*(1+I35) | J34: =I34*(1+J35) | L34: =_xlfn.RRI(2,C34,E34) | O34: *Use this if you are looking at an ARR multiple deal. Revenue for a period is calculated as the average of beginning and ending ARR.
B35: Growth | D35: =D34/C34-1 | E35: =E34/D34-1 | F35: 0.060185827 | G35: 0.17641857 | H35: 0.10904284 | I35: 0.20594697 | J35: 0.12189968
B37: GAAP Revenue | C37: 12300 | D37: 18117 | E37: 18575 | F37: =IF(N16="ARR",AVERAGE(F34,E34),E37*(1+F38)) | G37: =IF(O16="ARR",AVERAGE(G34,F34),F37*(1+G38)) | H37: =IF(P16="ARR",AVERAGE(H34,G34),G37*(1+H38)) | I37: =IF(Q16="ARR",AVERAGE(I34,H34),H37*(1+I38)) | J37: =IF(R16="ARR",AVERAGE(J34,I34),I37*(1+J38)) | L37: =_xlfn.RRI(2,C37,E37) | O37: *It is difficult to accelerate the growth of a business that is not already consistently growing at a solid pace.
B38: Growth | D38: =D37/C37-1 | E38: =E37/D37-1 | F38: 0.02 | G38: 0.03 | H38: 0.03 | I38: 0.03 | J38: 0.03 | O38: *Forecast revenue here if you are looking at an EBITDA multiple deal. For an ARR deal, you do not need historical revenue numbers.
B40: GAAP EBITDA | C40: 1190 | D40: 3224 | E40: 3363 | F40: =F41*F37 | G40: =G41*G37 | H40: =H41*H37 | I40: =I41*I37 | J40: =J41*J37 | L40: =_xlfn.RRI(2,C40,E40) | O40: *In the short/medium run, margins in ETA often decline and remain lower than historical margins (see research linked below for more). We rarely see a search fund business of scale with margins greater than 35%.
B41: Margin | C41: =C40/C37 | D41: =D40/D37 | E41: =E40/E37 | F41: 0.21 | G41: 0.21 | H41: 0.21 | I41: 0.21 | J41: 0.21 | O41: Research on EBITDA Margins in ETA - Thomas, Stevens, & Wasserstein
B43: GAAP EBITDA | F43: =F40 | G43: =G40 | H43: =H40 | I43: =I40 | J43: =J40
B44: Depreciation | F44: =-($L$44*F37) | G44: =-($L$44*G37) | H44: =-($L$44*H37) | I44: =-($L$44*I37) | J44: =-($L$44*J37) | L44: 0.01 | M44: % of Revenue | O44: *For asset-light search fund target businesses, depreciation will likely be minimal at around ~1-3% of revenue.
B45: EBIT | F45: =SUM(F43:F44) | G45: =SUM(G43:G44) | H45: =SUM(H43:H44) | I45: =SUM(I43:I44) | J45: =SUM(J43:J44)
B47: Interest | F47: =-F80-F89 | G47: =-G80-G89 | H47: =-H80-H89 | I47: =-I80-I89 | J47: =-J80-J89
B48: EBT | F48: =F45+F47 | G48: =G45+G47 | H48: =H45+H47 | I48: =I45+I47 | J48: =J45+J47
B50: Taxes Owed / Distributed | E50: =IF(N24="LLC",45%,26.5%) | F50: =-$E$50*F48 | G50: =-$E$50*G48 | H50: =-$E$50*H48 | I50: =-$E$50*I48 | J50: =-$E$50*J48
B51: Net Income | F51: =F48+F50 | G51: =G48+G50 | H51: =H48+H50 | I51: =I48+I50 | J51: =J48+J50
A53: x | B53: Cash Flow Statement
B55: Net Income | F55: =F51 | G55: =G51 | H55: =H51 | I55: =I51 | J55: =J51
B56: (+) D&A | F56: =-SUM(F44:F44) | G56: =-SUM(G44:G44) | H56: =-SUM(H44:H44) | I56: =-SUM(I44:I44) | J56: =-SUM(J44:J44) | O56: *You may be able to amortize a portion of the purchase price. This should be further diligenced with your legal counsel.
B57: (+) NWC | F57: =$L$57*F37 | G57: =$L$57*G37 | H57: =$L$57*H37 | I57: =$L$57*I37 | J57: =$L$57*J37 | L57: 0.01 | M57: % of Revenue | O57: *For asset-light search fund target businesses, we recommend modeling this as a 1% of revenue source of cash to be conservative.
B58: (-) CAPEX | F58: =-$L$58*F37 | G58: =-$L$58*G37 | H58: =-$L$58*H37 | I58: =-$L$58*I37 | J58: =-$L$58*J37 | L58: 0.01 | M58: % of Revenue | O58: *For asset-light search fund target businesses, CAPEX will likely be minimal at around ~1-3% of revenue.
B59: (-) Debt Paydown | F59: =F77+F86 | G59: =G77+G86 | H59: =H77+H86 | I59: =I77+I86 | J59: =J77+J86
B60: Cash after Debt | F60: =SUM(F55:F59) | G60: =SUM(G55:G59) | H60: =SUM(H55:H59) | I60: =SUM(I55:I59) | J60: =SUM(J55:J59)
B62: Cash for Earnout | F62: =-F122
B64: Beginning Cash | F64: =N22 | G64: =F70 | H64: =G70 | I64: =H70 | J64: =I70
B65: (+/-) Change in Cash | F65: =F60+F62 | G65: =G60++G62 | H65: =H60++H62 | I65: =I60++I62 | J65: =J60++J62
B66: Ending Cash before Distributions | F66: =SUM(F64:F65) | G66: =SUM(G64:G65) | H66: =SUM(H64:H65) | I66: =SUM(I64:I65) | J66: =SUM(J64:J65)
B67: Check | F67: =IF(F66<0,1,0) | G67: =IF(G66<0,1,0) | H67: =IF(H66<0,1,0) | I67: =IF(I66<0,1,0) | J67: =IF(J66<0,1,0)
B69: (-)Distributions | F69: 0 | G69: 0 | H69: =MAX(IF($N$23=1,1/3*H66,0),0) | I69: =MAX(IF($N$23=1,1/3*I66,0),0) | J69: 0
B70: Ending Cash after Distributions | F70: =F66-F69 | G70: =G66-G69 | H70: =H66-H69 | I70: =I66-I69 | J70: =J66-J69
A73: x | B73: Debt Schedule
B75: Term Loan
B76: Beginning Balance | F76: =C16 | G76: =F78 | H76: =G78 | I76: =H78 | J76: =I78
B77: (-) Mandatory Amortization | F77: =$F$76*-F82 | G77: =$F$76*-G82 | H77: =$F$76*-H82 | I77: =$F$76*-I82 | J77: =$F$76*-J82
B78: Ending Balance | F78: =SUM(F76:F77) | G78: =SUM(G76:G77) | H78: =SUM(H76:H77) | I78: =SUM(I76:I77) | J78: =SUM(J76:J77)
B80: Interest Expense | F80: =F76*$L$80 | G80: =G76*$L$80 | H80: =H76*$L$80 | I80: =I76*$L$80 | J80: =J76*$L$80 | L80: 0.12 | M80: Interest Rate
B82: Amortization Schedule | F82: 0 | G82: 0 | H82: 0 | I82: 0 | J82: 1 | L82: =IF(SUM(F82:J82)=100%,"Check","Paydown doesn't add to 100%") | O82: *Adjust amort schedule to account for term and amort of term loan debt. For bank lenders, we often see amortization schedules of 20%|20%|20%|20%|20% for non bank lenders we often see 0%|0%|0%|0%|100%.
B84: Seller Debt | N84: `
B85: Balance | F85: =C17 | G85: =F87 | H85: =G87 | I85: =H87 | J85: =I87
B86: (-) Paydown | F86: =$F$85*-F91 | G86: =$F$85*-G91 | H86: =$F$85*-H91 | I86: =$F$85*-I91 | J86: =$F$85*-J91
B87: Ending Balance | F87: =SUM(F85:F86) | G87: =SUM(G85:G86) | H87: =SUM(H85:H86) | I87: =SUM(I85:I86) | J87: =SUM(J85:J86)
B89: Interest Expense | F89: =$L$89*F85 | G89: =$L$89*G85 | H89: =$L$89*H85 | I89: =$L$89*I85 | J89: =$L$89*J85 | L89: 0.08 | M89: Interest Rate
B91: Amortization Schedule | F91: 0 | G91: 0 | H91: 0 | I91: 0 | J91: 1 | L91: =IF(SUM(F91:J91)=100%,"Check","Paydown doesn't add to 100%") | O91: *Adjust amort schedule to account for term and amort of seller debt. It is difficult to have seller debt amortize while term loan debt is still outstanding.
B93: Debt Metrics
B94: Total Senior Leverage | F94: =F78/F43 | G94: =G78/G43 | H94: =H78/H43 | I94: =I78/I43 | J94: =J78/J43 | O94: *These are examples of metrics that may be tested as covenants in term loan agreements. These are more typical for EBITDA based debt. ARR debt covenants may include tests of retention, profitability, and liquidity.
B95: Total Leverage | F95: =(F78+F87)/F43 | G95: =(G78+G87)/G43 | H95: =(H78+H87)/H43 | I95: =(I78+I87)/I43 | J95: =(J78+J87)/J43
B96: Fixed Charge Coverage Ratio | F96: =F40/(-F77+F80+-F86+F89-F58-F50+F69-F62) | G96: =G40/(-G77+G80+-G86+G89-G58-G50+G69-G62) | H96: =H40/(-H77+H80+-H86+H89-H58-H50+H69-H62) | I96: =I40/(-I77+I80+-I86+I89-I58-I50+I69-I62) | J96: =J40/(-J77+J80+-J86+J89-J58-J50+J69-J62)
B98: Returns Analysis - 5 Year Hold
A100: x | B100: Deal Structure
B102: Searcher(s) Common Equity | D102: 0.25 | F102: Circuit Breaker (0=Off) | H102: 1 | O102: *If the model is getting errors turn this to 0 and back to 1.
B103: Vested Employee Incentive Pool | D103: 0.05 | O103: *25% equity for solo searches and 30% for partnered searches.
F104: Search Capital | H104: 500
B105: Searcher(s) Equity (at close) | D105: =$D$102/3 | F105: Step-Up | H105: 1.5
B106: Searcher(s) Equity (time vest) | D106: =$D$102/3
B107: Searcher(s) Equity (performance) | D107: =$D$102/3 | F107: Investor Cap Gains Rate | H107: 0.3
B108: Total | D108: =SUM(D105:D107)
B110: Minimum IRR Hurdle | D110: 0.2 | H110: Vested | I110: Total | J110: %
B111: Maximum IRR Hurdle | D111: 0.35 | F111: Preferred Units | H111: =I111 | I111: =F117*1000 | J111: =1-D102
F112: Common Units | H112: =I112*D114/D108 | I112: =I113-I111 | J112: =I112/I113
B113: Vested Performance Equity | D113: =IF(J146>D111,D107,IF(J146<D110,0,(J146-D110)/(D111-D110))*D107) | F113: Total | H113: =SUM(H111:H112) | I113: =I111/J111 | J113: =I113/I113
B114: Total Searcher Vested Equity | D114: =D113+D106+D105
B116: Preferred Equity
B117: Beginning Balance | F117: =C23+(H105*H104) | G117: =F120 | H117: =G120 | I117: =H120 | J117: =I120
B118: (+) Preferred Return | D118: 0.08 | F118: =F117*$D$118 | G118: =G117*$D$118 | H118: =H117*$D$118 | I118: =I117*$D$118 | J118: =J117*$D$118
B119: (-) Distributions | F119: =-F69 | G119: =-G69 | H119: =-H69 | I119: =-I69 | J119: =-J69
B120: Ending Balance | F120: =SUM(F117:F119) | G120: =SUM(G117:G119) | H120: =SUM(H117:H119) | I120: =SUM(I117:I119) | J120: =SUM(J117:J119)
B122: Earnout | F122: =IF(N26=1,IF(F37>N28,N27,0),0)
A124: x | B124: Exit Waterfall & Returns
B126: =CONCATENATE("LTM "&N129&"") | J126: =IF(N128="EBITDA",J40,J34) | L126: Exit Assumptions
B127: (x) Multiple | J127: =N131 | L127: TEV @ Entry | N127: =N15
B128: Total Enterprise Value | J128: =J126*J127 | L128: Multiple @ Entry | N128: =N16
B129: (+) Cash | J129: =J70 | L129: Multiple @ Exit | N129: =N128
B130: (-) Debt | J130: =-J78-J87 | L130: Entry Multiple | N130: =IF(N128="EBITDA",N127/E40,N127/E34)
B131: Total Equity Value | J131: =SUM(J128:J130) | L131: Exit Multiple | N131: 3 | O131: *For base case, we don't recommend underwriting to multiple expansion; this can be upside at exit.
B132: (-) Preferred Return | J132: =MAX(MIN(J120-F117,J131),0) | L132: Searcher(s) Catch Up | N132: 1
B133: (-) Return of Capital | J133: =MIN(MIN(F117,J131-J132),J120)
...

Sheet Upside Case
A2: x | B2: G&B Model Template
B4: Instructions
B5: 1. Fill out historical Revenue and EBITDA. Project Revenue and EBITDA for the 5 year period.
B6: 2. Fill out the transaction assumptions with TEV & leverage and other key structure information.
B7: 3. Adjust the remaining assumptions in the yellow boxes for the cash flow statement and debt schedule as appropriate.
B8: 4. Check the "check" to make sure your business has the cash flow profile to support your capital structure.
B9: 5. Modify the deal structure and exit assumptions if needed. Note: If the model is getting errors, turn the circuit breaker to 0 and back to 1.
B10: 6. Evaluate the returns.
B12: $000s unless otherwise indicated | L12: Check | N12: =IF(SUM(F67:J67)>0,"Cash Shortfall","OK") | O12: *Check here to make sure your business has enough cash flow to support the capital structure.
A14: x | B14: Sources | G14: Uses | L14: Transaction Assumptions
C15: Amount | D15: =CONCATENATE("x",$N$16) | E15: % of Total | H15: Amount | I15: =CONCATENATE("x",$N$16) | J15: % of Total | L15: TEV | N15: =E40*3.5 | O15: *Refer to the Search Fund Study to understand median multiples, revenue, EBITDA, and more.
B16: Term Debt | C16: =D16*E40 | D16: =N20 | E16: =C16/C25 | G16: TEV | H16: =N15 | I16: =H16/$N$17 | J16: =H16/$H$25 | L16: Entry Multiple | N16: EBITDA
B17: Seller Debt | C17: =N21 | D17: =C17/$N$17 | E17: =C17/C25 | G17: Fees | H17: =H16*N19 | I17: =H17/$N$17 | J17: =H17/$H$25 | L17: =IF(N16="ARR","Ending ARR","LTM EBITDA") | N17: =IF(N16="ARR",E34,E40)
B18: Total Debt | C18: =SUM(C16:C17) | D18: =C18/$N$17 | E18: =C18/$C$25 | G18: Cash to B/S | H18: =N22 | I18: =H18/$N$17 | J18: =H18/$H$25 | L18: LTM Period | N18: 46022 | O18: 2024 Search Fund Study | Stanford Graduate School of Business
L19: Transaction Costs | N19: 0.05
B20: Equity | D20: % of Equity | L20: =CONCATENATE("Term Debt x",N16) | N20: 2.5
B21: Seller Equity Rollover | C21: =D21*C23 | D21: =N25 | E21: =C21/C25 | L21: Seller Debt Quantum | N21: 2000
B22: Investor Equity | C22: =D22*C23 | D22: =1-D21 | E22: =C22/C25 | L22: Cash to B/S | N22: 1000 | O22: *Typically, searcher(s) put de minimis cash on the balance sheet.
B23: Total Equity | C23: =C25-C18 | D23: =SUM(C21:C22)/C23 | E23: =C23/C25 | L23: ECF Distribution | N23: 0 | O23: *Toggle this to distribute 1/3 of accumulated cash in Year 3 & 4.
L24: LLC/C-corp | N24: C-corp | O24: *To qualify for QSBS, TEV must be <$70M you must be a C-corp and fit certain industry requirements (many except financial and professional services firms, certain categories of healthcare, and certain other excluded businesses).
B25: Total Sources | C25: =H25 | D25: =C25/$N$17 | E25: =C25/$H$25 | G25: Total Uses | H25: =SUM(H16:H18) | I25: =H25/$N$17 | J25: =H25/$H$25 | L25: Seller Equity Rollover | N25: 0.1 | O25: QSBS | Insights | Holland & Knight
L26: Earnout | N26: 0 | O26: *This is meant to be a simple example of an earnout; earnout structures can vary.
L27: Earnout Amount | N27: 0
B28: Summary Financials | L28: Y1 Revenue Threshold
E30: TXN Close | J30: TXN + 5
A31: x | B31: Income Statement | L31: Assumptions & BK Growth Notes
C33: =EDATE(D33,-12) | D33: =EDATE(E33,-12) | E33: =N18 | F33: =EDATE(E33,12) | G33: =EDATE(F33,12) | H33: =EDATE(G33,12) | I33: =EDATE(H33,12) | J33: =EDATE(I33,12) | L33: CAGR
B34: Ending ARR | C34: 9796 | D34: 11304 | E34: 12700 | F34: =E34*(1+F35) | G34: =F34*(1+G35) | H34: =G34*(1+H35) | I34: =H34*(1+I35) | J34: =I34*(1+J35) | L34: =_xlfn.RRI(2,C34,E34) | O34: *Use this if you are looking at an ARR multiple deal. Revenue for a period is calculated as the average of beginning and ending ARR.
B35: Growth | D35: =D34/C34-1 | E35: =E34/D34-1 | F35: 0.060185827 | G35: 0.17641857 | H35: 0.10904284 | I35: 0.20594697 | J35: 0.12189968
B37: GAAP Revenue | C37: 12300 | D37: 18117 | E37: 18575 | F37: =IF(N16="ARR",AVERAGE(F34,E34),E37*(1+F38)) | G37: =IF(O16="ARR",AVERAGE(G34,F34),F37*(1+G38)) | H37: =IF(P16="ARR",AVERAGE(H34,G34),G37*(1+H38)) | I37: =IF(Q16="ARR",AVERAGE(I34,H34),H37*(1+I38)) | J37: =IF(R16="ARR",AVERAGE(J34,I34),I37*(1+J38)) | L37: =_xlfn.RRI(2,C37,E37) | O37: *It is difficult to accelerate the growth of a business that is not already consistently growing at a solid pace.
B38: Growth | D38: =D37/C37-1 | E38: =E37/D37-1 | F38: 0.04 | G38: 0.05 | H38: 0.05 | I38: 0.05 | J38: 0.05 | O38: *Forecast revenue here if you are looking at an EBITDA multiple deal. For an ARR deal, you do not need historical revenue numbers.
B40: GAAP EBITDA | C40: 1190 | D40: 3224 | E40: 3363 | F40: =F41*F37 | G40: =G41*G37 | H40: =H41*H37 | I40: =I41*I37 | J40: =J41*J37 | L40: =_xlfn.RRI(2,C40,E40) | O40: *In the short/medium run, margins in ETA often decline and remain lower than historical margins (see research linked below for more). We rarely see a search fund business of scale with margins greater than 35%.
B41: Margin | C41: =C40/C37 | D41: =D40/D37 | E41: =E40/E37 | F41: 0.23 | G41: 0.23 | H41: 0.23 | I41: 0.23 | J41: 0.23 | O41: Research on EBITDA Margins in ETA - Thomas, Stevens, & Wasserstein
B43: GAAP EBITDA | F43: =F40 | G43: =G40 | H43: =H40 | I43: =I40 | J43: =J40
B44: Depreciation | F44: =-($L$44*F37) | G44: =-($L$44*G37) | H44: =-($L$44*H37) | I44: =-($L$44*I37) | J44: =-($L$44*J37) | L44: 0.01 | M44: % of Revenue | O44: *For asset-light search fund target businesses, depreciation will likely be minimal at around ~1-3% of revenue.
B45: EBIT | F45: =SUM(F43:F44) | G45: =SUM(G43:G44) | H45: =SUM(H43:H44) | I45: =SUM(I43:I44) | J45: =SUM(J43:J44)
B47: Interest | F47: =-F80-F89 | G47: =-G80-G89 | H47: =-H80-H89 | I47: =-I80-I89 | J47: =-J80-J89
B48: EBT | F48: =F45+F47 | G48: =G45+G47 | H48: =H45+H47 | I48: =I45+I47 | J48: =J45+J47
B50: Taxes Owed / Distributed | E50: =IF(N24="LLC",45%,26.5%) | F50: =-$E$50*F48 | G50: =-$E$50*G48 | H50: =-$E$50*H48 | I50: =-$E$50*I48 | J50: =-$E$50*J48
B51: Net Income | F51: =F48+F50 | G51: =G48+G50 | H51: =H48+H50 | I51: =I48+I50 | J51: =J48+J50
A53: x | B53: Cash Flow Statement
B55: Net Income | F55: =F51 | G55: =G51 | H55: =H51 | I55: =I51 | J55: =J51
B56: (+) D&A | F56: =-SUM(F44:F44) | G56: =-SUM(G44:G44) | H56: =-SUM(H44:H44) | I56: =-SUM(I44:I44) | J56: =-SUM(J44:J44) | O56: *You may be able to amortize a portion of the purchase price. This should be further diligenced with your legal counsel.
B57: (+) NWC | F57: =$L$57*F37 | G57: =$L$57*G37 | H57: =$L$57*H37 | I57: =$L$57*I37 | J57: =$L$57*J37 | L57: 0.01 | M57: % of Revenue | O57: *For asset-light search fund target businesses, we recommend modeling this as a 1% of revenue source of cash to be conservative.
B58: (-) CAPEX | F58: =-$L$58*F37 | G58: =-$L$58*G37 | H58: =-$L$58*H37 | I58: =-$L$58*I37 | J58: =-$L$58*J37 | L58: 0.01 | M58: % of Revenue | O58: *For asset-light search fund target businesses, CAPEX will likely be minimal at around ~1-3% of revenue.
B59: (-) Debt Paydown | F59: =F77+F86 | G59: =G77+G86 | H59: =H77+H86 | I59: =I77+I86 | J59: =J77+J86
B60: Cash after Debt | F60: =SUM(F55:F59) | G60: =SUM(G55:G59) | H60: =SUM(H55:H59) | I60: =SUM(I55:I59) | J60: =SUM(J55:J59)
B62: Cash for Earnout | F62: =-F122
B64: Beginning Cash | F64: =N22 | G64: =F70 | H64: =G70 | I64: =H70 | J64: =I70
B65: (+/-) Change in Cash | F65: =F60+F62 | G65: =G60++G62 | H65: =H60++H62 | I65: =I60++I62 | J65: =J60++J62
B66: Ending Cash before Distributions | F66: =SUM(F64:F65) | G66: =SUM(G64:G65) | H66: =SUM(H64:H65) | I66: =SUM(I64:I65) | J66: =SUM(J64:J65)
B67: Check | F67: =IF(F66<0,1,0) | G67: =IF(G66<0,1,0) | H67: =IF(H66<0,1,0) | I67: =IF(I66<0,1,0) | J67: =IF(J66<0,1,0)
B69: (-)Distributions | F69: 0 | G69: 0 | H69: =MAX(IF($N$23=1,1/3*H66,0),0) | I69: =MAX(IF($N$23=1,1/3*I66,0),0) | J69: 0
B70: Ending Cash after Distributions | F70: =F66-F69 | G70: =G66-G69 | H70: =H66-H69 | I70: =I66-I69 | J70: =J66-J69
A73: x | B73: Debt Schedule
B75: Term Loan
B76: Beginning Balance | F76: =C16 | G76: =F78 | H76: =G78 | I76: =H78 | J76: =I78
B77: (-) Mandatory Amortization | F77: =$F$76*-F82 | G77: =$F$76*-G82 | H77: =$F$76*-H82 | I77: =$F$76*-I82 | J77: =$F$76*-J82
B78: Ending Balance | F78: =SUM(F76:F77) | G78: =SUM(G76:G77) | H78: =SUM(H76:H77) | I78: =SUM(I76:I77) | J78: =SUM(J76:J77)
B80: Interest Expense | F80: =F76*$L$80 | G80: =G76*$L$80 | H80: =H76*$L$80 | I80: =I76*$L$80 | J80: =J76*$L$80 | L80: 0.12 | M80: Interest Rate
B82: Amortization Schedule | F82: 0 | G82: 0 | H82: 0 | I82: 0 | J82: 1 | L82: =IF(SUM(F82:J82)=100%,"Check","Paydown doesn't add to 100%") | O82: *Adjust amort schedule to account for term and amort of term loan debt. For bank lenders, we often see amortization schedules of 20%|20%|20%|20%|20% for non bank lenders we often see 0%|0%|0%|0%|100%.
B84: Seller Debt | N84: `
B85: Balance | F85: =C17 | G85: =F87 | H85: =G87 | I85: =H87 | J85: =I87
B86: (-) Paydown | F86: =$F$85*-F91 | G86: =$F$85*-G91 | H86: =$F$85*-H91 | I86: =$F$85*-I91 | J86: =$F$85*-J91
B87: Ending Balance | F87: =SUM(F85:F86) | G87: =SUM(G85:G86) | H87: =SUM(H85:H86) | I87: =SUM(I85:I86) | J87: =SUM(J85:J86)
B89: Interest Expense | F89: =$L$89*F85 | G89: =$L$89*G85 | H89: =$L$89*H85 | I89: =$L$89*I85 | J89: =$L$89*J85 | L89: 0.08 | M89: Interest Rate
B91: Amortization Schedule | F91: 0 | G91: 0 | H91: 0 | I91: 0 | J91: 1 | L91: =IF(SUM(F91:J91)=100%,"Check","Paydown doesn't add to 100%") | O91: *Adjust amort schedule to account for term and amort of seller debt. It is difficult to have seller debt amortize while term loan debt is still outstanding.
B93: Debt Metrics
B94: Total Senior Leverage | F94: =F78/F43 | G94: =G78/G43 | H94: =H78/H43 | I94: =I78/I43 | J94: =J78/J43 | O94: *These are examples of metrics that may be tested as covenants in term loan agreements. These are more typical for EBITDA based debt. ARR debt covenants may include tests of retention, profitability, and liquidity.
B95: Total Leverage | F95: =(F78+F87)/F43 | G95: =(G78+G87)/G43 | H95: =(H78+H87)/H43 | I95: =(I78+I87)/I43 | J95: =(J78+J87)/J43
B96: Fixed Charge Coverage Ratio | F96: =F40/(-F77+F80+-F86+F89-F58-F50+F69-F62) | G96: =G40/(-G77+G80+-G86+G89-G58-G50+G69-G62) | H96: =H40/(-H77+H80+-H86+H89-H58-H50+H69-H62) | I96: =I40/(-I77+I80+-I86+I89-I58-I50+I69-I62) | J96: =J40/(-J77+J80+-J86+J89-J58-J50+J69-J62)
B98: Returns Analysis - 5 Year Hold
A100: x | B100: Deal Structure
B102: Searcher(s) Common Equity | D102: 0.25 | F102: Circuit Breaker (0=Off) | H102: 1 | O102: *If the model is getting errors turn this to 0 and back to 1.
B103: Vested Employee Incentive Pool | D103: 0.05 | O103: *25% equity for solo searches and 30% for partnered searches.
F104: Search Capital | H104: 500
B105: Searcher(s) Equity (at close) | D105: =$D$102/3 | F105: Step-Up | H105: 1.5
B106: Searcher(s) Equity (time vest) | D106: =$D$102/3
B107: Searcher(s) Equity (performance) | D107: =$D$102/3 | F107: Investor Cap Gains Rate | H107: 0.3
B108: Total | D108: =SUM(D105:D107)
B110: Minimum IRR Hurdle | D110: 0.2 | H110: Vested | I110: Total | J110: %
B111: Maximum IRR Hurdle | D111: 0.35 | F111: Preferred Units | H111: =I111 | I111: =F117*1000 | J111: =1-D102
F112: Common Units | H112: =I112*D114/D108 | I112: =I113-I111 | J112: =I112/I113
B113: Vested Performance Equity | D113: =IF(J146>D111,D107,IF(J146<D110,0,(J146-D110)/(D111-D110))*D107) | F113: Total | H113: =SUM(H111:H112) | I113: =I111/J111 | J113: =I113/I113
B114: Total Searcher Vested Equity | D114: =D113+D106+D105
B116: Preferred Equity
B117: Beginning Balance | F117: =C23+(H105*H104) | G117: =F120 | H117: =G120 | I117: =H120 | J117: =I120
B118: (+) Preferred Return | D118: 0.08 | F118: =F117*$D$118 | G118: =G117*$D$118 | H118: =H117*$D$118 | I118: =I117*$D$118 | J118: =J117*$D$118
B119: (-) Distributions | F119: =-F69 | G119: =-G69 | H119: =-H69 | I119: =-I69 | J119: =-J69
B120: Ending Balance | F120: =SUM(F117:F119) | G120: =SUM(G117:G119) | H120: =SUM(H117:H119) | I120: =SUM(I117:I119) | J120: =SUM(J117:J119)
B122: Earnout | F122: =IF(N26=1,IF(F37>N28,N27,0),0)
A124: x | B124: Exit Waterfall & Returns
B126: =CONCATENATE("LTM "&N129&"") | J126: =IF(N128="EBITDA",J40,J34) | L126: Exit Assumptions
B127: (x) Multiple | J127: =N131 | L127: TEV @ Entry | N127: =N15
B128: Total Enterprise Value | J128: =J126*J127 | L128: Multiple @ Entry | N128: =N16
B129: (+) Cash | J129: =J70 | L129: Multiple @ Exit | N129: =N128
B130: (-) Debt | J130: =-J78-J87 | L130: Entry Multiple | N130: =IF(N128="EBITDA",N127/E40,N127/E34)
B131: Total Equity Value | J131: =SUM(J128:J130) | L131: Exit Multiple | N131: 3.5 | O131: *For base case, we don't recommend underwriting to multiple expansion; this can be upside at exit.
B132: (-) Preferred Return | J132: =MAX(MIN(J120-F117,J131),0) | L132: Searcher(s) Catch Up | N132: 1
B133: (-) Return of Capital | J133: =MIN(MIN(F117,J131-J132),J120)
...
