Workbook

Sheet Pest Single Acquisition
A2: x | B2: G&B Model - Pest Single Acquisition Base Case
B4: Instructions
B5: 1. Fill out historical Revenue and EBITDA. Project Revenue and EBITDA for the 5 year period.
B6: 2. Fill out the transaction assumptions with TEV & leverage and other key structure information.
B7: 3. Adjust the remaining assumptions in the yellow boxes for the cash flow statement and debt schedule as appropriate.
B8: 4. Check the "check" to make sure your business has the cash flow profile to support your capital structure.
B9: 5. Modify the deal structure and exit assumptions if needed. Note: If the model is getting errors, turn the circuit breaker to 0 and back to 1.
B10: 6. Evaluate the returns.
B12: $000s unless otherwise indicated | L12: Check | N12: =IF(SUM(F67:J67)>0,"Cash Shortfall","OK") | O12: *Check here to make sure your business has enough cash flow to support the capital structure.
A14: x | B14: Sources | G14: Uses | L14: Transaction Assumptions
C15: Amount | D15: =CONCATENATE("x",$N$16) | E15: % of Total | H15: Amount | I15: =CONCATENATE("x",$N$16) | J15: % of Total | L15: TEV | N15: 2500 | O15: *Refer to the Search Fund Study to understand median multiples, revenue, EBITDA, and more.
B16: Term Debt | C16: =D16*N17 | D16: =N20 | E16: =C16/C25 | G16: TEV | H16: =N15 | I16: =H16/$N$17 | J16: =H16/$H$25 | L16: Entry Multiple | N16: EBITDA
B17: Seller Debt | C17: =N21 | D17: =C17/$N$17 | E17: =C17/C25 | G17: Fees | H17: =H16*N19 | I17: =H17/$N$17 | J17: =H17/$H$25 | L17: =IF(N16="ARR","Ending ARR","LTM EBITDA") | N17: =IF(N16="ARR",E34,E40)
B18: Total Debt | C18: =SUM(C16:C17) | D18: =C18/$N$17 | E18: =C18/$C$25 | G18: Cash to B/S | H18: =N22 | I18: =H18/$N$17 | J18: =H18/$H$25 | L18: LTM Period | N18: 2026-12-31 | O18: 2024 Search Fund Study | Stanford Graduate School of Business
L19: Transaction Costs | N19: 0.05
B20: Equity | D20: % of Equity | L20: =CONCATENATE("Term Debt x",N16) | N20: 0
B21: Seller Equity Rollover | C21: =D21*C23 | D21: =N25 | E21: =C21/C25 | L21: Seller Debt Quantum | N21: 750
B22: Investor Equity | C22: =D22*C23 | D22: =1-D21 | E22: =C22/C25 | L22: Cash to B/S | N22: 200 | O22: *Typically, searcher(s) put de minimis cash on the balance sheet.
B23: Total Equity | C23: =C25-C18 | D23: =SUM(C21:C22)/C23 | E23: =C23/C25 | L23: ECF Distribution | N23: 0 | O23: *Toggle this to distribute 1/3 of accumulated cash in Year 3 & 4.
L24: LLC/C-corp | N24: C-corp | O24: *To qualify for QSBS, TEV must be <$70M you must be a C-corp and fit certain industry requirements (many except financial and professional services firms, certain categories of healthcare, and certain other excluded businesses).
B25: Total Sources | C25: =H25 | D25: =C25/$N$17 | E25: =C25/$H$25 | G25: Total Uses | H25: =SUM(H16:H18) | I25: =H25/$N$17 | J25: =H25/$H$25 | L25: Seller Equity Rollover | N25: 0.125 | O25: QSBS | Insights | Holland & Knight
L26: Earnout | N26: 0 | O26: *This is meant to be a simple example of an earnout; earnout structures can vary.
L27: Earnout Amount | N27: 0
B28: Summary Financials | L28: Y1 Revenue Threshold | N28: 0
E30: TXN Close | J30: TXN + 5
A31: x | B31: Income Statement | L31: Assumptions & Source Notes
C33: =EDATE(D33,-12) | D33: =EDATE(E33,-12) | E33: =N18 | F33: =EDATE(E33,12) | G33: =EDATE(F33,12) | H33: =EDATE(G33,12) | I33: =EDATE(H33,12) | J33: =EDATE(I33,12) | L33: Melissa 6/17: core $1.5M revenue / $500K EBITDA; 5% organic growth; equity + seller note, no bank debt at close.
B34: Ending ARR | C34: 2684 | D34: 3720 | E34: 4750 | F34: =E34*(1+F35) | G34: =F34*(1+G35) | H34: =G34*(1+H35) | I34: =H34*(1+I35) | J34: =I34*(1+J35) | L34: Seller note base: 30% of TEV proxy, 7% interest. Rollover base: 12.5%. | O34: *Use this if you are looking at an ARR multiple deal. Revenue for a period is calculated as the average of beginning and ending ARR.
B35: Growth | D35: =D34/C34-1 | E35: =E34/D34-1 | F35: 0.22894737 | G35: 0.26713062 | H35: 0.29015632 | I35: 0.30762984 | J35: 0.31181256 | L35: Historical C/D periods are set to 0/TBD because source material did not provide them.
B37: GAAP Revenue | C37: 0 | D37: 0 | E37: 1500 | F37: =IF(N16="ARR",AVERAGE(F34,E34),E37*(1+F38)) | G37: =IF(O16="ARR",AVERAGE(G34,F34),F37*(1+G38)) | H37: =IF(P16="ARR",AVERAGE(H34,G34),G37*(1+H38)) | I37: =IF(Q16="ARR",AVERAGE(I34,H34),H37*(1+I38)) | J37: =IF(R16="ARR",AVERAGE(J34,I34),I37*(1+J38)) | L37: =_xlfn.RRI(2,C37,E37) | O37: *It is difficult to accelerate the growth of a business that is not already consistently growing at a solid pace.
B38: Growth | D38: =D37/C37-1 | E38: =E37/D37-1 | F38: 0.05 | G38: 0.05 | H38: 0.05 | I38: 0.05 | J38: 0.05 | O38: *Forecast revenue here if you are looking at an EBITDA multiple deal. For an ARR deal, you do not need historical revenue numbers.
B40: GAAP EBITDA | C40: 0 | D40: 0 | E40: 500 | F40: =F41*F37 | G40: =G41*G37 | H40: =H41*H37 | I40: =I41*I37 | J40: =J41*J37 | L40: =_xlfn.RRI(2,C40,E40) | O40: *In the short/medium run, margins in ETA often decline and remain lower than historical margins (see research linked below for more). We rarely see a search fund business of scale with margins greater than 35%.
B41: Margin | C41: =C40/C37 | D41: =D40/D37 | E41: =E40/E37 | F41: 0.33333333 | G41: 0.33333333 | H41: 0.33333333 | I41: 0.33333333 | J41: 0.33333333 | O41: Research on EBITDA Margins in ETA - Thomas, Stevens, & Wasserstein
B43: GAAP EBITDA | F43: =F40 | G43: =G40 | H43: =H40 | I43: =I40 | J43: =J40
B44: Depreciation | F44: =-($L$44*F37) | G44: =-($L$44*G37) | H44: =-($L$44*H37) | I44: =-($L$44*I37) | J44: =-($L$44*J37) | L44: 0.01 | M44: % of Revenue | O44: *For asset-light search fund target businesses, depreciation will likely be minimal at around ~1-3% of revenue.
B45: EBIT | F45: =SUM(F43:F44) | G45: =SUM(G43:G44) | H45: =SUM(H43:H44) | I45: =SUM(I43:I44) | J45: =SUM(J43:J44)
B47: Interest | F47: =-F80-F89 | G47: =-G80-G89 | H47: =-H80-H89 | I47: =-I80-I89 | J47: =-J80-J89
B48: EBT | F48: =F45+F47 | G48: =G45+G47 | H48: =H45+H47 | I48: =I45+I47 | J48: =J45+J47
B50: Taxes Owed / Distributed | E50: =IF(N24="LLC",45%,26.5%) | F50: =-$E$50*F48 | G50: =-$E$50*G48 | H50: =-$E$50*H48 | I50: =-$E$50*I48 | J50: =-$E$50*J48
B51: Net Income | F51: =F48+F50 | G51: =G48+G50 | H51: =H48+H50 | I51: =I48+I50 | J51: =J48+J50
A53: x | B53: Cash Flow Statement
B55: Net Income | F55: =F51 | G55: =G51 | H55: =H51 | I55: =I51 | J55: =J51
B56: (+) D&A | F56: =-SUM(F44:F44) | G56: =-SUM(G44:G44) | H56: =-SUM(H44:H44) | I56: =-SUM(I44:I44) | J56: =-SUM(J44:J44) | O56: *You may be able to amortize a portion of the purchase price. This should be further diligenced with your legal counsel.
B57: (+) NWC | F57: =$L$57*F37 | G57: =$L$57*G37 | H57: =$L$57*H37 | I57: =$L$57*I37 | J57: =$L$57*J37 | L57: 0.01 | M57: % of Revenue | O57: *For asset-light search fund target businesses, we recommend modeling this as a 1% of revenue source of cash to be conservative.
B58: (-) CAPEX | F58: =-$L$58*F37 | G58: =-$L$58*G37 | H58: =-$L$58*H37 | I58: =-$L$58*I37 | J58: =-$L$58*J37 | L58: 0.01 | M58: % of Revenue | O58: *For asset-light search fund target businesses, CAPEX will likely be minimal at around ~1-3% of revenue.
B59: (-) Debt Paydown | F59: =F77+F86 | G59: =G77+G86 | H59: =H77+H86 | I59: =I77+I86 | J59: =J77+J86
B60: Cash after Debt | F60: =SUM(F55:F59) | G60: =SUM(G55:G59) | H60: =SUM(H55:H59) | I60: =SUM(I55:I59) | J60: =SUM(J55:J59)
B62: Cash for Earnout | F62: =-F122
B64: Beginning Cash | F64: =N22 | G64: =F70 | H64: =G70 | I64: =H70 | J64: =I70
B65: (+/-) Change in Cash | F65: =F60+F62 | G65: =G60++G62 | H65: =H60++H62 | I65: =I60++I62 | J65: =J60++J62
B66: Ending Cash before Distributions | F66: =SUM(F64:F65) | G66: =SUM(G64:G65) | H66: =SUM(H64:H65) | I66: =SUM(I64:I65) | J66: =SUM(J64:J65)
B67: Check | F67: =IF(F66<0,1,0) | G67: =IF(G66<0,1,0) | H67: =IF(H66<0,1,0) | I67: =IF(I66<0,1,0) | J67: =IF(J66<0,1,0)
B69: (-)Distributions | F69: 0 | G69: 0 | H69: =MAX(IF($N$23=1,1/3*H66,0),0) | I69: =MAX(IF($N$23=1,1/3*I66,0),0) | J69: 0
B70: Ending Cash after Distributions | F70: =F66-F69 | G70: =G66-G69 | H70: =H66-H69 | I70: =I66-I69 | J70: =J66-J69
A73: x | B73: Debt Schedule
B75: Term Loan
B76: Beginning Balance | F76: =C16 | G76: =F78 | H76: =G78 | I76: =H78 | J76: =I78
B77: (-) Mandatory Amortization | F77: =$F$76*-F82 | G77: =$F$76*-G82 | H77: =$F$76*-H82 | I77: =$F$76*-I82 | J77: =$F$76*-J82
B78: Ending Balance | F78: =SUM(F76:F77) | G78: =SUM(G76:G77) | H78: =SUM(H76:H77) | I78: =SUM(I76:I77) | J78: =SUM(J76:J77)
B80: Interest Expense | F80: =F76*$L$80 | G80: =G76*$L$80 | H80: =H76*$L$80 | I80: =I76*$L$80 | J80: =J76*$L$80 | L80: 0 | M80: Interest Rate
B82: Amortization Schedule | F82: 0 | G82: 0 | H82: 0 | I82: 0 | J82: 1 | L82: =IF(SUM(F82:J82)=100%,"Check","Paydown doesn't add to 100%") | O82: *Adjust amort schedule to account for term and amort of term loan debt. For bank lenders, we often see amortization schedules of 20%|20%|20%|20%|20% for non bank lenders we often see 0%|0%|0%|0%|100%.
B84: Seller Debt | N84: `
B85: Balance | F85: =C17 | G85: =F87 | H85: =G87 | I85: =H87 | J85: =I87
B86: (-) Paydown | F86: =$F$85*-F91 | G86: =$F$85*-G91 | H86: =$F$85*-H91 | I86: =$F$85*-I91 | J86: =$F$85*-J91
B87: Ending Balance | F87: =SUM(F85:F86) | G87: =SUM(G85:G86) | H87: =SUM(H85:H86) | I87: =SUM(I85:I86) | J87: =SUM(J85:J86)
B89: Interest Expense | F89: =$L$89*F85 | G89: =$L$89*G85 | H89: =$L$89*H85 | I89: =$L$89*I85 | J89: =$L$89*J85 | L89: 0.07 | M89: Interest Rate
B91: Amortization Schedule | F91: 0 | G91: 0 | H91: 0 | I91: 0 | J91: 1 | L91: =IF(SUM(F91:J91)=100%,"Check","Paydown doesn't add to 100%") | O91: *Adjust amort schedule to account for term and amort of seller debt. It is difficult to have seller debt amortize while term loan debt is still outstanding.
B93: Debt Metrics
B94: Total Senior Leverage | F94: =F78/F43 | G94: =G78/G43 | H94: =H78/H43 | I94: =I78/I43 | J94: =J78/J43 | O94: *These are examples of metrics that may be tested as covenants in term loan agreements. These are more typical for EBITDA based debt. ARR debt covenants may include tests of retention, profitability, and liquidity.
B95: Total Leverage | F95: =(F78+F87)/F43 | G95: =(G78+G87)/G43 | H95: =(H78+H87)/H43 | I95: =(I78+I87)/I43 | J95: =(J78+J87)/J43
B96: Fixed Charge Coverage Ratio | F96: =F40/(-F77+F80+-F86+F89-F58-F50+F69-F62) | G96: =G40/(-G77+G80+-G86+G89-G58-G50+G69-G62) | H96: =H40/(-H77+H80+-H86+H89-H58-H50+H69-H62) | I96: =I40/(-I77+I80+-I86+I89-I58-I50+I69-I62) | J96: =J40/(-J77+J80+-J86+J89-J58-J50+J69-J62)
B98: Returns Analysis - 5 Year Hold
A100: x | B100: Deal Structure
B102: Searcher(s) Common Equity | D102: 0.25 | F102: Circuit Breaker (0=Off) | H102: 1 | O102: *If the model is getting errors turn this to 0 and back to 1.
B103: Vested Employee Incentive Pool | D103: 0.05 | O103: *25% equity for solo searches and 30% for partnered searches.
F104: Search Capital | H104: 500
B105: Searcher(s) Equity (at close) | D105: =$D$102/3 | F105: Step-Up | H105: 1.5
B106: Searcher(s) Equity (time vest) | D106: =$D$102/3
B107: Searcher(s) Equity (performance) | D107: =$D$102/3 | F107: Investor Cap Gains Rate | H107: 0.3
B108: Total | D108: =SUM(D105:D107)
B110: Minimum IRR Hurdle | D110: 0.2 | H110: Vested | I110: Total | J110: %
B111: Maximum IRR Hurdle | D111: 0.35 | F111: Preferred Units | H111: =I111 | I111: =F117*1000 | J111: =1-D102
F112: Common Units | H112: =I112*D114/D108 | I112: =I113-I111 | J112: =I112/I113
B113: Vested Performance Equity | D113: =IF(J146>D111,D107,IF(J146<D110,0,(J146-D110)/(D111-D110))*D107) | F113: Total | H113: =SUM(H111:H112) | I113: =I111/J111 | J113: =I113/I113
B114: Total Searcher Vested Equity | D114: =D113+D106+D105
B116: Preferred Equity
B117: Beginning Balance | F117: =C23+(H105*H104) | G117: =F120 | H117: =G120 | I117: =H120 | J117: =I120
B118: (+) Preferred Return | D118: 0.08 | F118: =F117*$D$118 | G118: =G117*$D$118 | H118: =H117*$D$118 | I118: =I117*$D$118 | J118: =J117*$D$118
B119: (-) Distributions | F119: =-F69 | G119: =-G69 | H119: =-H69 | I119: =-I69 | J119: =-J69
B120: Ending Balance | F120: =SUM(F117:F119) | G120: =SUM(G117:G119) | H120: =SUM(H117:H119) | I120: =SUM(I117:I119) | J120: =SUM(J117:J119)
B122: Earnout | F122: =IF(N26=1,IF(F37>N28,N27,0),0)
A124: x | B124: Exit Waterfall & Returns
B126: =CONCATENATE("LTM "&N129&"") | J126: =IF(N128="EBITDA",J40,J34) | L126: Exit Assumptions
B127: (x) Multiple | J127: =N131 | L127: TEV @ Entry | N127: =N15
B128: Total Enterprise Value | J128: =J126*J127 | L128: Multiple @ Entry | N128: =N16
B129: (+) Cash | J129: =J70 | L129: Multiple @ Exit | N129: =N128
B130: (-) Debt | J130: =-J78-J87 | L130: Entry Multiple | N130: =IF(N128="EBITDA",N127/E40,N127/E34)
B131: Total Equity Value | J131: =SUM(J128:J130) | L131: Exit Multiple | N131: =N130 | O131: *For base case, we don't recommend underwriting to multiple expansion; this can be upside at exit.
B132: (-) Preferred Return | J132: =MAX(MIN(J120-F117,J131),0) | L132: Searcher(s) Catch Up | N132: 1
B133: (-) Return of Capital | J133: =MIN(MIN(F117,J131-J132),J120)
...

Sheet Pest Base Case
B2: G&B Pest Multi-Acquisition Model - First Pass
B3: Built from G&B Financial Model Template.xlsx. $000s unless otherwise indicated. Yellow cells are inputs; green cells are formulas.
D6: Close | E6: Y1 | F6: Y2 | G6: Y3 | H6: Y4 | I6: Y5 | M6: Source / status | N6: Notes
B8: Core business assumptions
B9: Revenue | D9: 1500 | M9: Melissa call 2026-06-17 | N9: Core business: $1.5M revenue.
B10: EBITDA | D10: 500 | M10: Melissa call 2026-06-17 | N10: Core business: $500K EBITDA, 33.3% margin.
B11: Labor / COGS % revenue | D11: 0.4 | M11: Melissa call 2026-06-17 | N11: 40% labor / COGS.
B12: Organic growth | D12: 0.05 | M12: Melissa call 2026-06-17 | N12: Melissa recommended ~5% organic growth.
B13: Initial tech count | D13: 6 | M13: Guillermo/Carlos 2026-06-17 | N13: 6-person team; technician count still needs diligence.
B14: Revenue / tech proxy | D14: =D9/D13 | M14: Formula | N14: Useful only after technician count is verified.
B17: Transaction assumptions
B18: Prior offer / TEV proxy | D18: 2500 | M18: Melissa call 2026-06-17 | N18: Seller reportedly had $2.5M offer last year; use as proxy, not valuation conclusion.
B19: Entry multiple proxy | D19: =D18/D10 | M19: Formula | N19: Implied by prior-offer proxy and $500K EBITDA.
B20: Transaction costs | D20: 0.05 | M20: Baseline workbook | N20: Carryover placeholder from single-acquisition model; diligence needed.
B21: Cash to balance sheet | D21: 200 | M21: Baseline workbook | N21: Placeholder from baseline workbook; adjust after operating cash need is known.
B22: Seller note % of TEV | D22: 0.3 | M22: Model input / Melissa structure | N22: Structure lever; stress-tested on Stress Tests tab.
B23: Seller note interest rate | D23: 0.07 | M23: Melissa call 2026-06-17 | N23: Melissa range 6-8%; base at midpoint.
B24: Seller note tenor | D24: 6 | M24: Melissa call 2026-06-17 | N24: Melissa range 5-7 years; base at midpoint.
B25: Rollover equity % | D25: 0.125 | M25: Jay + Melissa 2026-06-17 | N25: Jay suggested 10-15% max; Melissa said minority governance risk is low.
B26: Term debt at close | D26: 0 | M26: Melissa call 2026-06-17 | N26: No bank debt expected at this size.
B27: Bank debt threshold EBITDA | D27: 2000 | M27: Melissa call 2026-06-17 | N27: ~$2M EBITDA minimum for bank debt.
B28: Indicative bank facility | D28: 5000 | M28: Melissa call 2026-06-17 | N28: ~$5M facility once threshold is reached.
B31: Sources & uses
B32: TEV | D32: =D18 | M32: Formula | N32: Capital stack is intentionally simple for the first pass.
B33: Transaction costs | D33: =D18*D20
B34: Cash to balance sheet | D34: =D21
B35: Total uses | D35: =SUM(D32:D34)
B36: Seller note | D36: =D18*D22
B37: Seller rollover | D37: =D18*D25
B38: Term debt | D38: =D26
B39: Investor equity required | D39: =D35-D36-D37-D38
B40: Check | D40: =D35-SUM(D36:D39)
B43: Operating forecast
D44: Close | E44: Y1 | F44: Y2 | G44: Y3 | H44: Y4 | I44: Y5
B45: Core revenue | D45: =D9 | E45: =D45*(1+$D$12) | F45: =E45*(1+$D$12) | G45: =F45*(1+$D$12) | H45: =G45*(1+$D$12) | I45: =H45*(1+$D$12)
B46: Acquired revenue | D46: ='M&A Schedule'!D22 | E46: ='M&A Schedule'!E22 | F46: ='M&A Schedule'!F22 | G46: ='M&A Schedule'!G22 | H46: ='M&A Schedule'!H22 | I46: ='M&A Schedule'!I22
B47: Total revenue | D47: =SUM(D45:D46) | E47: =SUM(E45:E46) | F47: =SUM(F45:F46) | G47: =SUM(G45:G46) | H47: =SUM(H45:H46) | I47: =SUM(I45:I46)
B48: Core EBITDA | D48: =D10 | E48: =D48*(1+$D$12) | F48: =E48*(1+$D$12) | G48: =F48*(1+$D$12) | H48: =G48*(1+$D$12) | I48: =H48*(1+$D$12)
B49: Acquired EBITDA | D49: ='M&A Schedule'!D46 | E49: ='M&A Schedule'!E46 | F49: ='M&A Schedule'!F46 | G49: ='M&A Schedule'!G46 | H49: ='M&A Schedule'!H46 | I49: ='M&A Schedule'!I46
B50: Corporate costs | D50: =SUM(D57:D60) | E50: =SUM(E57:E60) | F50: =SUM(F57:F60) | G50: =SUM(G57:G60) | H50: =SUM(H57:H60) | I50: =SUM(I57:I60)
B51: Adjusted EBITDA | D51: =SUM(D48:D49)-D50 | E51: =SUM(E48:E49)-E50 | F51: =SUM(F48:F49)-F50 | G51: =SUM(G48:G49)-G50 | H51: =SUM(H48:H49)-H50 | I51: =SUM(I48:I49)-I50
B52: EBITDA margin | D52: =D51/D47 | E52: =E51/E47 | F52: =F51/F47 | G52: =G51/G47 | H52: =H51/H47 | I52: =I51/I47
B56: Corporate cost build
B57: Kay salary / CEO comp | D57: 150 | E57: 150 | F57: 175 | G57: 200 | H57: 225 | I57: 250 | N57: Input needed; placeholder for cash-flow pressure only.
B58: GM / ops lead | D58: 0 | E58: 0 | F58: 125 | G58: 150 | H58: 175 | I58: 200 | N58: Layered future leadership per Melissa guidance.
B59: Accounting / software / admin | D59: 50 | E59: 60 | F59: 75 | G59: 90 | H59: 110 | I59: 130 | N59: Shared back-end cost pool; verify with operator quotes.
B60: Other corporate costs | D60: 0 | E60: 25 | F60: 50 | G60: 75 | H60: 100 | I60: 125 | N60: Placeholder for holding-company overhead.
B63: Cash flow / debt-service pressure
B64: Adjusted EBITDA | D64: =D51 | E64: =E51 | F64: =F51 | G64: =G51 | H64: =H51 | I64: =I51
B65: Estimated capex | D65: =D47*1.0% | E65: =E47*1.0% | F65: =F47*1.0% | G65: =G47*1.0% | H65: =H47*1.0% | I65: =I47*1.0%
B66: Cash taxes placeholder | D66: =MAX(D51-D68,0)*26.5% | E66: =MAX(E51-E68,0)*26.5% | F66: =MAX(F51-F68,0)*26.5% | G66: =MAX(G51-G68,0)*26.5% | H66: =MAX(H51-H68,0)*26.5% | I66: =MAX(I51-I68,0)*26.5%
B67: Seller note interest | D67: =(D36)*$D$23 | E67: =(D36)*$D$23 | F67: =(D36)*$D$23 | G67: =(D36)*$D$23 | H67: =(D36)*$D$23 | I67: =(D36)*$D$23
B68: Seller note amortization | D68: =D36/$D$24 | E68: =D36/$D$24 | F68: =D36/$D$24 | G68: =D36/$D$24 | H68: =D36/$D$24 | I68: =D36/$D$24
B69: Term debt service | D69: =0 | E69: =0 | F69: =0 | G69: =0 | H69: =0 | I69: =0
B70: Cash after debt service | D70: =D64-D65-D66-D67-D68-D69 | E70: =E64-E65-E66-E67-E68-E69 | F70: =F64-F65-F66-F67-F68-F69 | G70: =G64-G65-G66-G67-G68-G69 | H70: =H64-H65-H66-H67-H68-H69 | I70: =I64-I65-I66-I67-I68-I69
B71: Debt service coverage | D71: =D64/SUM(D67:D69) | E71: =E64/SUM(E67:E69) | F71: =F64/SUM(F67:F69) | G71: =G64/SUM(G67:G69) | H71: =H64/SUM(H67:H69) | I71: =I64/SUM(I67:I69)
B72: Bank debt eligible? | D72: =IF(D51>=$D$27,"Yes","No") | E72: =IF(E51>=$D$27,"Yes","No") | F72: =IF(F51>=$D$27,"Yes","No") | G72: =IF(G51>=$D$27,"Yes","No") | H72: =IF(H51>=$D$27,"Yes","No") | I72: =IF(I51>=$D$27,"Yes","No")
B76: CIO verdict logic
B77: Pest path supportability | D77: =IF(MIN(E70:I70)<0,"Does not support base structure",IF(MIN(E71:I71)<1.25,"Marginal debt-service cushion","Supports first-pass structure"))
B78: Buy-box fit | D78: Good niche / undersized platform: economics fit, but initial EBITDA is below preferred $750K+ floor. Needs multi-acquisition path or organic growth proof.

Sheet M&A Schedule
B2: M&A Schedule
B3: Acquisition cohorts use Melissa's first-pass structure. Inputs are deliberately average profiles, not target-level diligence.
D6: Close | E6: Y1 | F6: Y2 | G6: Y3 | H6: Y4 | I6: Y5 | J6: Source / status | K6: Notes
B8: Acquisition count by cohort
B9: Core platform | D9: 1 | E9: 0 | F9: 0 | G9: 0 | H9: 0 | I9: 0 | J9: Melissa / live target | K9: Existing $1.5M revenue, $500K EBITDA business.
B10: Aquihire / small book | D10: 0 | E10: 1 | F10: 2 | G10: 2 | H10: 2 | I10: 2 | J10: Melissa example | K10: $500K revenue, $100K EBITDA, 2 technicians.
B11: Platform tuck-in | D11: 0 | E11: 0 | F11: 0 | G11: 1 | H11: 1 | I11: 1 | J11: TBD | K11: Placeholder count only; profile needs real deal-flow evidence.
B12: De novo crews | D12: 0 | E12: 0 | F12: 0 | G12: 0 | H12: 0 | I12: 0 | J12: Lower priority | K12: Melissa reframed as organic growth; aquihire preferred.
B17: Annual acquired revenue contribution
B18: Core platform | D18: =D9*'Pest Base Case'!$D$9 | E18: =E9*'Pest Base Case'!$D$9 | F18: =F9*'Pest Base Case'!$D$9 | G18: =G9*'Pest Base Case'!$D$9 | H18: =H9*'Pest Base Case'!$D$9 | I18: =I9*'Pest Base Case'!$D$9
B19: Aquihire / small book | D19: =SUM($D10:D10)*$D$29 | E19: =SUM($D10:E10)*$D$29 | F19: =SUM($D10:F10)*$D$29 | G19: =SUM($D10:G10)*$D$29 | H19: =SUM($D10:H10)*$D$29 | I19: =SUM($D10:I10)*$D$29
B20: Platform tuck-in | D20: =SUM($D11:D11)*$D$30 | E20: =SUM($D11:E11)*$D$30 | F20: =SUM($D11:F11)*$D$30 | G20: =SUM($D11:G11)*$D$30 | H20: =SUM($D11:H11)*$D$30 | I20: =SUM($D11:I11)*$D$30
B21: De novo crews | D21: =SUM($D12:D12)*$D$31 | E21: =SUM($D12:E12)*$D$31 | F21: =SUM($D12:F12)*$D$31 | G21: =SUM($D12:G12)*$D$31 | H21: =SUM($D12:H12)*$D$31 | I21: =SUM($D12:I12)*$D$31
B22: Total acquired revenue | D22: =SUM(D19:D21) | E22: =SUM(E19:E21) | F22: =SUM(F19:F21) | G22: =SUM(G19:G21) | H22: =SUM(H19:H21) | I22: =SUM(I19:I21)
B26: Average acquisition profile
B27: Core platform revenue | D27: 1500 | J27: Melissa call
B28: Core platform EBITDA | D28: 500 | J28: Melissa call
B29: Aquihire revenue | D29: 500 | J29: Melissa example
B30: Platform tuck-in revenue | D30: 1500 | J30: TBD / placeholder
B31: De novo crew revenue | D31: 0 | J31: Not modeled
B32: Aquihire EBITDA | D32: 100 | J32: Melissa example
B33: Platform tuck-in EBITDA | D33: 300 | J33: TBD / placeholder
B34: De novo crew EBITDA | D34: 0 | J34: Not modeled
B35: Aquihire techs | D35: 2 | J35: Melissa example
B41: Annual acquired EBITDA contribution
B42: Core platform | D42: =D9*$D$28 | E42: =E9*$D$28 | F42: =F9*$D$28 | G42: =G9*$D$28 | H42: =H9*$D$28 | I42: =I9*$D$28
B43: Aquihire / small book | D43: =SUM($D10:D10)*$D$32 | E43: =SUM($D10:E10)*$D$32 | F43: =SUM($D10:F10)*$D$32 | G43: =SUM($D10:G10)*$D$32 | H43: =SUM($D10:H10)*$D$32 | I43: =SUM($D10:I10)*$D$32
B44: Platform tuck-in | D44: =SUM($D11:D11)*$D$33 | E44: =SUM($D11:E11)*$D$33 | F44: =SUM($D11:F11)*$D$33 | G44: =SUM($D11:G11)*$D$33 | H44: =SUM($D11:H11)*$D$33 | I44: =SUM($D11:I11)*$D$33
B45: De novo crews | D45: =SUM($D12:D12)*$D$34 | E45: =SUM($D12:E12)*$D$34 | F45: =SUM($D12:F12)*$D$34 | G45: =SUM($D12:G12)*$D$34 | H45: =SUM($D12:H12)*$D$34 | I45: =SUM($D12:I12)*$D$34
B46: Total acquired EBITDA | D46: =SUM(D43:D45) | E46: =SUM(E43:E45) | F46: =SUM(F43:F45) | G46: =SUM(G43:G45) | H46: =SUM(H43:H45) | I46: =SUM(I43:I45)
B50: Acquisition cash need
B51: Aquihire TEV multiple | D51: 3 | J51: TBD | K51: Placeholder only. Replace with broker / owner evidence.
B52: Tuck-in TEV multiple | D52: 5 | J52: TBD | K52: Placeholder only. Market notes suggest 7-10x tuck-ins, likely too high for G&B without a wedge.
B53: Annual aquihire TEV | D53: =SUM(D10:I10)*$D$51*$D$32
B54: Annual tuck-in TEV | D54: =SUM(D11:I11)*$D$52*$D$33
B55: Total modeled acquisition TEV | D55: =D53+D54 | K55: Use only as a directional capital need; no acquisition-by-acquisition timing yet.

Sheet Stress Tests
B2: Seller Note / Rollover / Interest-Rate Stress Tests
B3: All tests use the base-case adjusted EBITDA path and change structure levers only.
B6: Scenario | C6: Seller note % | D6: Rate | E6: Tenor | F6: Rollover % | G6: Min DSCR Y1-Y5 | H6: Verdict
B7: Low seller note / low rate | C7: 0.2 | D7: 0.06 | E7: 7 | F7: 0.1 | G7: =MIN('Pest Base Case'!E64/(('Pest Base Case'!$D$18*C7*D7)+('Pest Base Case'!$D$18*C7/E7)),'Pest Base Case'!F64/(('Pest Base Case'!$D$18*C7*D7)+('Pest Base Case'!$D$18*C7/E7)),'Pest Base Case'!G64/(('Pest Base Case'!$D$18*C7*D7)+('Pest Base Case'!$D$18*C7/E7)),'Pest Base Case'!H64/(('Pest Base Case'!$D$18*C7*D7)+('Pest Base Case'!$D$18*C7/E7)),'Pest Base Case'!I64/(('Pest Base Case'!$D$18*C7*D7)+('Pest Base Case'!$D$18*C7/E7))) | H7: =IF(G7<1,"Breaks cash flow",IF(G7<1.25,"Marginal cushion","Supported in first pass"))
B8: Base case | C8: 0.3 | D8: 0.07 | E8: 6 | F8: 0.125 | G8: =MIN('Pest Base Case'!E64/(('Pest Base Case'!$D$18*C8*D8)+('Pest Base Case'!$D$18*C8/E8)),'Pest Base Case'!F64/(('Pest Base Case'!$D$18*C8*D8)+('Pest Base Case'!$D$18*C8/E8)),'Pest Base Case'!G64/(('Pest Base Case'!$D$18*C8*D8)+('Pest Base Case'!$D$18*C8/E8)),'Pest Base Case'!H64/(('Pest Base Case'!$D$18*C8*D8)+('Pest Base Case'!$D$18*C8/E8)),'Pest Base Case'!I64/(('Pest Base Case'!$D$18*C8*D8)+('Pest Base Case'!$D$18*C8/E8))) | H8: =IF(G8<1,"Breaks cash flow",IF(G8<1.25,"Marginal cushion","Supported in first pass"))
B9: High seller note / high rate | C9: 0.4 | D9: 0.08 | E9: 5 | F9: 0.15 | G9: =MIN('Pest Base Case'!E64/(('Pest Base Case'!$D$18*C9*D9)+('Pest Base Case'!$D$18*C9/E9)),'Pest Base Case'!F64/(('Pest Base Case'!$D$18*C9*D9)+('Pest Base Case'!$D$18*C9/E9)),'Pest Base Case'!G64/(('Pest Base Case'!$D$18*C9*D9)+('Pest Base Case'!$D$18*C9/E9)),'Pest Base Case'!H64/(('Pest Base Case'!$D$18*C9*D9)+('Pest Base Case'!$D$18*C9/E9)),'Pest Base Case'!I64/(('Pest Base Case'!$D$18*C9*D9)+('Pest Base Case'!$D$18*C9/E9))) | H9: =IF(G9<1,"Breaks cash flow",IF(G9<1.25,"Marginal cushion","Supported in first pass"))
B10: No rollover / more cash need | C10: 0.3 | D10: 0.07 | E10: 6 | F10: 0 | G10: =MIN('Pest Base Case'!E64/(('Pest Base Case'!$D$18*C10*D10)+('Pest Base Case'!$D$18*C10/E10)),'Pest Base Case'!F64/(('Pest Base Case'!$D$18*C10*D10)+('Pest Base Case'!$D$18*C10/E10)),'Pest Base Case'!G64/(('Pest Base Case'!$D$18*C10*D10)+('Pest Base Case'!$D$18*C10/E10)),'Pest Base Case'!H64/(('Pest Base Case'!$D$18*C10*D10)+('Pest Base Case'!$D$18*C10/E10)),'Pest Base Case'!I64/(('Pest Base Case'!$D$18*C10*D10)+('Pest Base Case'!$D$18*C10/E10))) | H10: =IF(G10<1,"Breaks cash flow",IF(G10<1.25,"Marginal cushion","Supported in first pass"))
B11: Max rollover / max seller carry | C11: 0.4 | D11: 0.08 | E11: 7 | F11: 0.15 | G11: =MIN('Pest Base Case'!E64/(('Pest Base Case'!$D$18*C11*D11)+('Pest Base Case'!$D$18*C11/E11)),'Pest Base Case'!F64/(('Pest Base Case'!$D$18*C11*D11)+('Pest Base Case'!$D$18*C11/E11)),'Pest Base Case'!G64/(('Pest Base Case'!$D$18*C11*D11)+('Pest Base Case'!$D$18*C11/E11)),'Pest Base Case'!H64/(('Pest Base Case'!$D$18*C11*D11)+('Pest Base Case'!$D$18*C11/E11)),'Pest Base Case'!I64/(('Pest Base Case'!$D$18*C11*D11)+('Pest Base Case'!$D$18*C11/E11))) | H11: =IF(G11<1,"Breaks cash flow",IF(G11<1.25,"Marginal cushion","Supported in first pass"))
B12: Interest shock | C12: 0.3 | D12: 0.09 | E12: 6 | F12: 0.125 | G12: =MIN('Pest Base Case'!E64/(('Pest Base Case'!$D$18*C12*D12)+('Pest Base Case'!$D$18*C12/E12)),'Pest Base Case'!F64/(('Pest Base Case'!$D$18*C12*D12)+('Pest Base Case'!$D$18*C12/E12)),'Pest Base Case'!G64/(('Pest Base Case'!$D$18*C12*D12)+('Pest Base Case'!$D$18*C12/E12)),'Pest Base Case'!H64/(('Pest Base Case'!$D$18*C12*D12)+('Pest Base Case'!$D$18*C12/E12)),'Pest Base Case'!I64/(('Pest Base Case'!$D$18*C12*D12)+('Pest Base Case'!$D$18*C12/E12))) | H12: =IF(G12<1,"Breaks cash flow",IF(G12<1.25,"Marginal cushion","Supported in first pass"))
B16: Cash-flow sensitivity
B18: EBITDA haircut | C18: Min DSCR base structure | D18: Cash after debt Y1 | E18: Cash after debt Y5 | F18: Verdict
B19: 0 | C19: =MIN(('Pest Base Case'!E64*(1-B19))/(('Pest Base Case'!$D$36*'Pest Base Case'!$D$23)+('Pest Base Case'!$D$36/'Pest Base Case'!$D$24)),('Pest Base Case'!F64*(1-B19))/(('Pest Base Case'!$D$36*'Pest Base Case'!$D$23)+('Pest Base Case'!$D$36/'Pest Base Case'!$D$24)),('Pest Base Case'!G64*(1-B19))/(('Pest Base Case'!$D$36*'Pest Base Case'!$D$23)+('Pest Base Case'!$D$36/'Pest Base Case'!$D$24)),('Pest Base Case'!H64*(1-B19))/(('Pest Base Case'!$D$36*'Pest Base Case'!$D$23)+('Pest Base Case'!$D$36/'Pest Base Case'!$D$24)),('Pest Base Case'!I64*(1-B19))/(('Pest Base Case'!$D$36*'Pest Base Case'!$D$23)+('Pest Base Case'!$D$36/'Pest Base Case'!$D$24))) | D19: ='Pest Base Case'!E70*(1-B19) | E19: ='Pest Base Case'!I70*(1-B19) | F19: =IF(C19<1,"Breaks",IF(C19<1.25,"Tight","OK"))
B20: 0.1 | C20: =MIN(('Pest Base Case'!E64*(1-B20))/(('Pest Base Case'!$D$36*'Pest Base Case'!$D$23)+('Pest Base Case'!$D$36/'Pest Base Case'!$D$24)),('Pest Base Case'!F64*(1-B20))/(('Pest Base Case'!$D$36*'Pest Base Case'!$D$23)+('Pest Base Case'!$D$36/'Pest Base Case'!$D$24)),('Pest Base Case'!G64*(1-B20))/(('Pest Base Case'!$D$36*'Pest Base Case'!$D$23)+('Pest Base Case'!$D$36/'Pest Base Case'!$D$24)),('Pest Base Case'!H64*(1-B20))/(('Pest Base Case'!$D$36*'Pest Base Case'!$D$23)+('Pest Base Case'!$D$36/'Pest Base Case'!$D$24)),('Pest Base Case'!I64*(1-B20))/(('Pest Base Case'!$D$36*'Pest Base Case'!$D$23)+('Pest Base Case'!$D$36/'Pest Base Case'!$D$24))) | D20: ='Pest Base Case'!E70*(1-B20) | E20: ='Pest Base Case'!I70*(1-B20) | F20: =IF(C20<1,"Breaks",IF(C20<1.25,"Tight","OK"))
B21: 0.2 | C21: =MIN(('Pest Base Case'!E64*(1-B21))/(('Pest Base Case'!$D$36*'Pest Base Case'!$D$23)+('Pest Base Case'!$D$36/'Pest Base Case'!$D$24)),('Pest Base Case'!F64*(1-B21))/(('Pest Base Case'!$D$36*'Pest Base Case'!$D$23)+('Pest Base Case'!$D$36/'Pest Base Case'!$D$24)),('Pest Base Case'!G64*(1-B21))/(('Pest Base Case'!$D$36*'Pest Base Case'!$D$23)+('Pest Base Case'!$D$36/'Pest Base Case'!$D$24)),('Pest Base Case'!H64*(1-B21))/(('Pest Base Case'!$D$36*'Pest Base Case'!$D$23)+('Pest Base Case'!$D$36/'Pest Base Case'!$D$24)),('Pest Base Case'!I64*(1-B21))/(('Pest Base Case'!$D$36*'Pest Base Case'!$D$23)+('Pest Base Case'!$D$36/'Pest Base Case'!$D$24))) | D21: ='Pest Base Case'!E70*(1-B21) | E21: ='Pest Base Case'!I70*(1-B21) | F21: =IF(C21<1,"Breaks",IF(C21<1.25,"Tight","OK"))
B22: 0.3 | C22: =MIN(('Pest Base Case'!E64*(1-B22))/(('Pest Base Case'!$D$36*'Pest Base Case'!$D$23)+('Pest Base Case'!$D$36/'Pest Base Case'!$D$24)),('Pest Base Case'!F64*(1-B22))/(('Pest Base Case'!$D$36*'Pest Base Case'!$D$23)+('Pest Base Case'!$D$36/'Pest Base Case'!$D$24)),('Pest Base Case'!G64*(1-B22))/(('Pest Base Case'!$D$36*'Pest Base Case'!$D$23)+('Pest Base Case'!$D$36/'Pest Base Case'!$D$24)),('Pest Base Case'!H64*(1-B22))/(('Pest Base Case'!$D$36*'Pest Base Case'!$D$23)+('Pest Base Case'!$D$36/'Pest Base Case'!$D$24)),('Pest Base Case'!I64*(1-B22))/(('Pest Base Case'!$D$36*'Pest Base Case'!$D$23)+('Pest Base Case'!$D$36/'Pest Base Case'!$D$24))) | D22: ='Pest Base Case'!E70*(1-B22) | E22: ='Pest Base Case'!I70*(1-B22) | F22: =IF(C22<1,"Breaks",IF(C22<1.25,"Tight","OK"))

Sheet Investor Questions
B2: Investor-Facing Question Set: Jeff / Anacapa
B5: Topic | C5: Question | D5: Why it matters | E5: Owner / next use
B6: Cap table | C6: If the first pest platform is only ~$500K EBITDA, what cap-table shape would Anacapa support: same committed investor base, smaller first-close syndicate, or reserved follow-on capital? | D6: Melissa says committed capital should bridge the first close to the flywheel; Kay needs investor appetite before overbuilding the strategy. | E6: Jeff / Anacapa
B7: Seller note | C7: At what seller-note quantum does Anacapa become uncomfortable for a small, owner-operated pest platform? | D7: Seller note is the primary lever to make the seller's proceeds work without overloading cash flow. | E7: Jeff / Anacapa
B8: Rollover | C8: Is 10-15% seller rollover acceptable in a search-style cap table if the seller has no governance control? | D8: Jay suggested 10-15% max; Melissa sees low governance risk, but investor support matters. | E8: Jeff / Anacapa
B9: Interest rate | C9: Would Anacapa underwrite a 6-8% seller note today, and what cushion would they require if rates move up? | D9: Debt-service pressure is the gating issue for a small platform. | E9: Jeff / Anacapa
B10: Bank debt | C10: Does the ~$2M EBITDA / ~$5M facility threshold match Anacapa's current lender read for pest services? | D10: Model assumes no bank debt at close and future debt only after scale. | E10: Jeff / Anacapa
B11: Buy-box fit | C11: Is an undersized but high-margin $500K EBITDA pest platform acceptable if the multi-acquisition path is credible? | D11: CIO issue: initial asset is below preferred scale, but could be a wedge into a dense market. | E11: Jeff / Anacapa
B12: Wedge | C12: Does the luxury retail / hospitality discretion wedge make pest more underwritable, or is it too narrow for an investor-backed strategy? | D12: Jay's warning: broad pest is too competitive; specialty is the opening. | E12: Jeff / Anacapa
B13: Diligence | C13: What proof would make the acquisition path real: client count, route density, revenue per technician, retention, pricing uplift, or signed seller interest? | D13: Avoids modeling sophistication without diligence-grade inputs. | E13: Jeff / Anacapa

Sheet Source Notes
B2: Source Notes / Assumption Register
B5: Source | C5: Model use | D5: Fact / guidance used | E5: Status
B6: Melissa Rosenblatt call 2026-06-17 | C6: Core model architecture | D6: Core business: $1.5M revenue, $500K EBITDA, 40% labor/COGS, no office manager, answering service. Build core IS, corporate cost section, M&A schedule, combined IS. | E6: Used
B7: Melissa analysis Google Doc 2026-06-17 | C7: Operating frame | D7: Full analysis reinforced aquihire over de novo, holdco vs branded roll-up as open, and the need for one visible model plus a decision memo. | E7: Used
B8: Melissa transcript Google Doc 2026-06-17 | C8: Transcript check | D8: gog docs cat returned only: Granola transcript unavailable in response. No transcript-only facts were used. | E8: Blocked / explicit limitation
B9: Melissa Rosenblatt call 2026-06-17 | C9: Capital structure | D9: First acquisition likely equity + seller note; no bank debt at this size. Bank debt threshold ~$2M EBITDA, facility ~$5M. Seller note 5-7 years, 6-8% interest. | E9: Used
B10: Melissa Rosenblatt / Jay Davis 2026-06-17 | C10: Rollover | D10: Jay suggested 10-15% max; Melissa confirmed minority stake carries no real governance risk. | E10: Used
B11: Guillermo Lavergne brainstorm 2026-06-17 | C11: Target diligence | D11: NJ/NYC commercial pest company: ~$1.5M revenue, ~$500K EBITDA, 6-person team, 98% retention, Cartier/Chelsea Market/Google proof points. | E11: Used
B12: Carlos check-in 2026-06-17 | C12: Thesis support | D12: Carlos validated small NJ operator / NYC thesis; holding-company structure remains live. | E12: Used
B13: WSN pest calibration 2026-06-17 | C13: Diligence gate | D13: Cash-flow quality and owner draw need verification before more time is spent. | E13: Used as missing-input flag
B14: Jay Davis 2026-06-09 | C14: Market structure | D14: Broad pest is crowded/liquid; specialty/premium wedge is the opening if growth is real. | E14: Used
B15: Premium Pest Scorecard Apr 2026 | C15: Industry context | D15: 19,000+ firms, strong fragmentation, 25-35% EBITDA margins for well-run operators, asset-light service model. | E15: Used as context, not hardcoded forecast
B16: Niche intelligence 2026-05-26 | C16: Market multiple context | D16: PE consolidation deepening; 10-15x platform / 7-10x tuck-in market notes. | E16: Flagged: not used as base valuation because it may not fit G&B's small target
... B18: G&B Financial Model Template.xlsx | C18: Baseline structure | D18: Master template from Manager Documents / G&B Master Templates. Sources/uses, cash flow, debt schedule, returns framework retained and used as the reference single-acquisition structure. | E18: Used as baseline

Sheet Model Template
A2: x | B2: G&B Financial Model Template - Baseline Reference
B4: Instructions
B5: 1. Fill out historical Revenue and EBITDA. Project Revenue and EBITDA for the 5 year period.
B6: 2. Fill out the transaction assumptions with TEV & leverage and other key structure information.
B7: 3. Adjust the remaining assumptions in the yellow boxes for the cash flow statement and debt schedule as appropriate.
B8: 4. Check the "check" to make sure your business has the cash flow profile to support your capital structure.
B9: 5. Modify the deal structure and exit assumptions if needed. Note: If the model is getting errors, turn the circuit breaker to 0 and back to 1.
B10: 6. Evaluate the returns.
B12: $000s unless otherwise indicated | L12: Check | N12: =IF(SUM(F67:J67)>0,"Cash Shortfall","OK") | O12: *Check here to make sure your business has enough cash flow to support the capital structure.
A14: x | B14: Sources | G14: Uses | L14: Transaction Assumptions
C15: Amount | D15: =CONCATENATE("x",$N$16) | E15: % of Total | H15: Amount | I15: =CONCATENATE("x",$N$16) | J15: % of Total | L15: TEV | N15: 8500 | O15: *Refer to the Search Fund Study to understand median multiples, revenue, EBITDA, and more.
B16: Term Debt | C16: =D16*N17 | D16: =N20 | E16: =C16/C25 | G16: TEV | H16: =N15 | I16: =H16/$N$17 | J16: =H16/$H$25 | L16: Entry Multiple | N16: EBITDA
B17: Seller Debt | C17: =N21 | D17: =C17/$N$17 | E17: =C17/C25 | G17: Fees | H17: =H16*N19 | I17: =H17/$N$17 | J17: =H17/$H$25 | L17: =IF(N16="ARR","Ending ARR","LTM EBITDA") | N17: =IF(N16="ARR",E34,E40)
B18: Total Debt | C18: =SUM(C16:C17) | D18: =C18/$N$17 | E18: =C18/$C$25 | G18: Cash to B/S | H18: =N22 | I18: =H18/$N$17 | J18: =H18/$H$25 | L18: LTM Period | N18: 46022 | O18: 2024 Search Fund Study | Stanford Graduate School of Business
L19: Transaction Costs | N19: 0.05
B20: Equity | D20: % of Equity | L20: =CONCATENATE("Term Debt x",N16) | N20: 2.5
B21: Seller Equity Rollover | C21: =D21*C23 | D21: =N25 | E21: =C21/C25 | L21: Seller Debt Quantum | N21: 1000
B22: Investor Equity | C22: =D22*C23 | D22: =1-D21 | E22: =C22/C25 | L22: Cash to B/S | N22: 200 | O22: *Typically, searcher(s) put de minimis cash on the balance sheet.
B23: Total Equity | C23: =C25-C18 | D23: =SUM(C21:C22)/C23 | E23: =C23/C25 | L23: ECF Distribution | N23: 0 | O23: *Toggle this to distribute 1/3 of accumulated cash in Year 3 & 4.
L24: LLC/C-corp | N24: C-corp | O24: *To qualify for QSBS, TEV must be <$70M you must be a C-corp and fit certain industry requirements (many except financial and professional services firms, certain categories of healthcare, and certain other excluded businesses).
B25: Total Sources | C25: =H25 | D25: =C25/$N$17 | E25: =C25/$H$25 | G25: Total Uses | H25: =SUM(H16:H18) | I25: =H25/$N$17 | J25: =H25/$H$25 | L25: Seller Equity Rollover | N25: 0.1 | O25: QSBS | Insights | Holland & Knight
L26: Earnout | N26: 0 | O26: *This is meant to be a simple example of an earnout; earnout structures can vary.
L27: Earnout Amount | N27: 500
B28: Summary Financials | L28: Y1 Revenue Threshold | N28: 5000
E30: TXN Close | J30: TXN + 5
A31: x | B31: Income Statement | L31: Assumptions & BK Growth Notes
C33: =EDATE(D33,-12) | D33: =EDATE(E33,-12) | E33: =N18 | F33: =EDATE(E33,12) | G33: =EDATE(F33,12) | H33: =EDATE(G33,12) | I33: =EDATE(H33,12) | J33: =EDATE(I33,12) | L33: CAGR
B34: Ending ARR | C34: 2684 | D34: 3720 | E34: 4750 | F34: =E34*(1+F35) | G34: =F34*(1+G35) | H34: =G34*(1+H35) | I34: =H34*(1+I35) | J34: =I34*(1+J35) | L34: =_xlfn.RRI(2,C34,E34) | O34: *Use this if you are looking at an ARR multiple deal. Revenue for a period is calculated as the average of beginning and ending ARR.
B35: Growth | D35: =D34/C34-1 | E35: =E34/D34-1 | F35: 0.22894737 | G35: 0.26713062 | H35: 0.29015632 | I35: 0.30762984 | J35: 0.31181256
B37: GAAP Revenue | C37: 2123 | D37: 3202 | E37: 4235 | F37: =IF(N16="ARR",AVERAGE(F34,E34),E37*(1+F38)) | G37: =IF(O16="ARR",AVERAGE(G34,F34),F37*(1+G38)) | H37: =IF(P16="ARR",AVERAGE(H34,G34),G37*(1+H38)) | I37: =IF(Q16="ARR",AVERAGE(I34,H34),H37*(1+I38)) | J37: =IF(R16="ARR",AVERAGE(J34,I34),I37*(1+J38)) | L37: =_xlfn.RRI(2,C37,E37) | O37: *It is difficult to accelerate the growth of a business that is not already consistently growing at a solid pace.
B38: Growth | D38: =D37/C37-1 | E38: =E37/D37-1 | F38: 0.25 | G38: 0.25 | H38: 0.28 | I38: 0.3 | J38: 0.31 | O38: *Forecast revenue here if you are looking at an EBITDA multiple deal. For an ARR deal, you do not need historical revenue numbers.
B40: GAAP EBITDA | C40: 465 | D40: 689 | E40: 1256 | F40: =F41*F37 | G40: =G41*G37 | H40: =H41*H37 | I40: =I41*I37 | J40: =J41*J37 | L40: =_xlfn.RRI(2,C40,E40) | O40: *In the short/medium run, margins in ETA often decline and remain lower than historical margins (see research linked below for more). We rarely see a search fund business of scale with margins greater than 35%.
B41: Margin | C41: =C40/C37 | D41: =D40/D37 | E41: =E40/E37 | F41: 0.22 | G41: 0.22 | H41: 0.25 | I41: 0.28 | J41: 0.29 | O41: Research on EBITDA Margins in ETA - Thomas, Stevens, & Wasserstein
B43: GAAP EBITDA | F43: =F40 | G43: =G40 | H43: =H40 | I43: =I40 | J43: =J40
B44: Depreciation | F44: =-($L$44*F37) | G44: =-($L$44*G37) | H44: =-($L$44*H37) | I44: =-($L$44*I37) | J44: =-($L$44*J37) | L44: 0.01 | M44: % of Revenue | O44: *For asset-light search fund target businesses, depreciation will likely be minimal at around ~1-3% of revenue.
B45: EBIT | F45: =SUM(F43:F44) | G45: =SUM(G43:G44) | H45: =SUM(H43:H44) | I45: =SUM(I43:I44) | J45: =SUM(J43:J44)
B47: Interest | F47: =-F80-F89 | G47: =-G80-G89 | H47: =-H80-H89 | I47: =-I80-I89 | J47: =-J80-J89
B48: EBT | F48: =F45+F47 | G48: =G45+G47 | H48: =H45+H47 | I48: =I45+I47 | J48: =J45+J47
B50: Taxes Owed / Distributed | E50: =IF(N24="LLC",45%,26.5%) | F50: =-$E$50*F48 | G50: =-$E$50*G48 | H50: =-$E$50*H48 | I50: =-$E$50*I48 | J50: =-$E$50*J48
B51: Net Income | F51: =F48+F50 | G51: =G48+G50 | H51: =H48+H50 | I51: =I48+I50 | J51: =J48+J50
A53: x | B53: Cash Flow Statement
B55: Net Income | F55: =F51 | G55: =G51 | H55: =H51 | I55: =I51 | J55: =J51
B56: (+) D&A | F56: =-SUM(F44:F44) | G56: =-SUM(G44:G44) | H56: =-SUM(H44:H44) | I56: =-SUM(I44:I44) | J56: =-SUM(J44:J44) | O56: *You may be able to amortize a portion of the purchase price. This should be further diligenced with your legal counsel.
B57: (+) NWC | F57: =$L$57*F37 | G57: =$L$57*G37 | H57: =$L$57*H37 | I57: =$L$57*I37 | J57: =$L$57*J37 | L57: 0.01 | M57: % of Revenue | O57: *For asset-light search fund target businesses, we recommend modeling this as a 1% of revenue source of cash to be conservative.
B58: (-) CAPEX | F58: =-$L$58*F37 | G58: =-$L$58*G37 | H58: =-$L$58*H37 | I58: =-$L$58*I37 | J58: =-$L$58*J37 | L58: 0.01 | M58: % of Revenue | O58: *For asset-light search fund target businesses, CAPEX will likely be minimal at around ~1-3% of revenue.
B59: (-) Debt Paydown | F59: =F77+F86 | G59: =G77+G86 | H59: =H77+H86 | I59: =I77+I86 | J59: =J77+J86
B60: Cash after Debt | F60: =SUM(F55:F59) | G60: =SUM(G55:G59) | H60: =SUM(H55:H59) | I60: =SUM(I55:I59) | J60: =SUM(J55:J59)
B62: Cash for Earnout | F62: =-F122
B64: Beginning Cash | F64: =N22 | G64: =F70 | H64: =G70 | I64: =H70 | J64: =I70
B65: (+/-) Change in Cash | F65: =F60+F62 | G65: =G60++G62 | H65: =H60++H62 | I65: =I60++I62 | J65: =J60++J62
B66: Ending Cash before Distributions | F66: =SUM(F64:F65) | G66: =SUM(G64:G65) | H66: =SUM(H64:H65) | I66: =SUM(I64:I65) | J66: =SUM(J64:J65)
B67: Check | F67: =IF(F66<0,1,0) | G67: =IF(G66<0,1,0) | H67: =IF(H66<0,1,0) | I67: =IF(I66<0,1,0) | J67: =IF(J66<0,1,0)
B69: (-)Distributions | F69: 0 | G69: 0 | H69: =MAX(IF($N$23=1,1/3*H66,0),0) | I69: =MAX(IF($N$23=1,1/3*I66,0),0) | J69: 0
B70: Ending Cash after Distributions | F70: =F66-F69 | G70: =G66-G69 | H70: =H66-H69 | I70: =I66-I69 | J70: =J66-J69
A73: x | B73: Debt Schedule
B75: Term Loan
B76: Beginning Balance | F76: =C16 | G76: =F78 | H76: =G78 | I76: =H78 | J76: =I78
B77: (-) Mandatory Amortization | F77: =$F$76*-F82 | G77: =$F$76*-G82 | H77: =$F$76*-H82 | I77: =$F$76*-I82 | J77: =$F$76*-J82
B78: Ending Balance | F78: =SUM(F76:F77) | G78: =SUM(G76:G77) | H78: =SUM(H76:H77) | I78: =SUM(I76:I77) | J78: =SUM(J76:J77)
B80: Interest Expense | F80: =F76*$L$80 | G80: =G76*$L$80 | H80: =H76*$L$80 | I80: =I76*$L$80 | J80: =J76*$L$80 | L80: 0.1 | M80: Interest Rate
B82: Amortization Schedule | F82: 0 | G82: 0 | H82: 0 | I82: 0 | J82: 1 | L82: =IF(SUM(F82:J82)=100%,"Check","Paydown doesn't add to 100%") | O82: *Adjust amort schedule to account for term and amort of term loan debt. For bank lenders, we often see amortization schedules of 20%|20%|20%|20%|20% for non bank lenders we often see 0%|0%|0%|0%|100%.
B84: Seller Debt | N84: `
B85: Balance | F85: =C17 | G85: =F87 | H85: =G87 | I85: =H87 | J85: =I87
B86: (-) Paydown | F86: =$F$85*-F91 | G86: =$F$85*-G91 | H86: =$F$85*-H91 | I86: =$F$85*-I91 | J86: =$F$85*-J91
B87: Ending Balance | F87: =SUM(F85:F86) | G87: =SUM(G85:G86) | H87: =SUM(H85:H86) | I87: =SUM(I85:I86) | J87: =SUM(J85:J86)
B89: Interest Expense | F89: =$L$89*F85 | G89: =$L$89*G85 | H89: =$L$89*H85 | I89: =$L$89*I85 | J89: =$L$89*J85 | L89: 0.08 | M89: Interest Rate
B91: Amortization Schedule | F91: 0 | G91: 0 | H91: 0 | I91: 0 | J91: 1 | L91: =IF(SUM(F91:J91)=100%,"Check","Paydown doesn't add to 100%") | O91: *Adjust amort schedule to account for term and amort of seller debt. It is difficult to have seller debt amortize while term loan debt is still outstanding.
B93: Debt Metrics
B94: Total Senior Leverage | F94: =F78/F43 | G94: =G78/G43 | H94: =H78/H43 | I94: =I78/I43 | J94: =J78/J43 | O94: *These are examples of metrics that may be tested as covenants in term loan agreements. These are more typical for EBITDA based debt. ARR debt covenants may include tests of retention, profitability, and liquidity.
B95: Total Leverage | F95: =(F78+F87)/F43 | G95: =(G78+G87)/G43 | H95: =(H78+H87)/H43 | I95: =(I78+I87)/I43 | J95: =(J78+J87)/J43
B96: Fixed Charge Coverage Ratio | F96: =F40/(-F77+F80+-F86+F89-F58-F50+F69-F62) | G96: =G40/(-G77+G80+-G86+G89-G58-G50+G69-G62) | H96: =H40/(-H77+H80+-H86+H89-H58-H50+H69-H62) | I96: =I40/(-I77+I80+-I86+I89-I58-I50+I69-I62) | J96: =J40/(-J77+J80+-J86+J89-J58-J50+J69-J62)
B98: Returns Analysis - 5 Year Hold
A100: x | B100: Deal Structure
B102: Searcher(s) Common Equity | D102: 0.25 | F102: Circuit Breaker (0=Off) | H102: 1 | O102: *If the model is getting errors turn this to 0 and back to 1.
B103: Vested Employee Incentive Pool | D103: 0.05 | O103: *25% equity for solo searches and 30% for partnered searches.
F104: Search Capital | H104: 500
B105: Searcher(s) Equity (at close) | D105: =$D$102/3 | F105: Step-Up | H105: 1.5
B106: Searcher(s) Equity (time vest) | D106: =$D$102/3
B107: Searcher(s) Equity (performance) | D107: =$D$102/3 | F107: Investor Cap Gains Rate | H107: 0.3
B108: Total | D108: =SUM(D105:D107)
B110: Minimum IRR Hurdle | D110: 0.2 | H110: Vested | I110: Total | J110: %
B111: Maximum IRR Hurdle | D111: 0.35 | F111: Preferred Units | H111: =I111 | I111: =F117*1000 | J111: =1-D102
F112: Common Units | H112: =I112*D114/D108 | I112: =I113-I111 | J112: =I112/I113
B113: Vested Performance Equity | D113: =IF(J146>D111,D107,IF(J146<D110,0,(J146-D110)/(D111-D110))*D107) | F113: Total | H113: =SUM(H111:H112) | I113: =I111/J111 | J113: =I113/I113
B114: Total Searcher Vested Equity | D114: =D113+D106+D105
B116: Preferred Equity
B117: Beginning Balance | F117: =C23+(H105*H104) | G117: =F120 | H117: =G120 | I117: =H120 | J117: =I120
B118: (+) Preferred Return | D118: 0.08 | F118: =F117*$D$118 | G118: =G117*$D$118 | H118: =H117*$D$118 | I118: =I117*$D$118 | J118: =J117*$D$118
B119: (-) Distributions | F119: =-F69 | G119: =-G69 | H119: =-H69 | I119: =-I69 | J119: =-J69
B120: Ending Balance | F120: =SUM(F117:F119) | G120: =SUM(G117:G119) | H120: =SUM(H117:H119) | I120: =SUM(I117:I119) | J120: =SUM(J117:J119)
B122: Earnout | F122: =IF(N26=1,IF(F37>N28,N27,0),0)
A124: x | B124: Exit Waterfall & Returns
B126: =CONCATENATE("LTM "&N129&"") | J126: =IF(N128="EBITDA",J40,J34) | L126: Exit Assumptions
B127: (x) Multiple | J127: =N131 | L127: TEV @ Entry | N127: =N15
B128: Total Enterprise Value | J128: =J126*J127 | L128: Multiple @ Entry | N128: =N16
B129: (+) Cash | J129: =J70 | L129: Multiple @ Exit | N129: =N128
B130: (-) Debt | J130: =-J78-J87 | L130: Entry Multiple | N130: =IF(N128="EBITDA",N127/E40,N127/E34)
B131: Total Equity Value | J131: =SUM(J128:J130) | L131: Exit Multiple | N131: =N130 | O131: *For base case, we don't recommend underwriting to multiple expansion; this can be upside at exit.
B132: (-) Preferred Return | J132: =MAX(MIN(J120-F117,J131),0) | L132: Searcher(s) Catch Up | N132: 1
B133: (-) Return of Capital | J133: =MIN(MIN(F117,J131-J132),J120)
...

Sheet Growth
A2: x | B2: G&B Model Template
B4: Instructions
B5: 1. Fill out historical Revenue and EBITDA. Project Revenue and EBITDA for the 5 year period.
B6: 2. Fill out the transaction assumptions with TEV & leverage and other key structure information.
B7: 3. Adjust the remaining assumptions in the yellow boxes for the cash flow statement and debt schedule as appropriate.
B8: 4. Check the "check" to make sure your business has the cash flow profile to support your capital structure.
B9: 5. Modify the deal structure and exit assumptions if needed. Note: If the model is getting errors, turn the circuit breaker to 0 and back to 1.
B10: 6. Evaluate the returns.
B12: $000s unless otherwise indicated | L12: Check | N12: =IF(SUM(F67:J67)>0,"Cash Shortfall","OK") | O12: *Check here to make sure your business has enough cash flow to support the capital structure.
A14: x | B14: Sources | G14: Uses | L14: Transaction Assumptions
C15: Amount | D15: =CONCATENATE("x",$N$16) | E15: % of Total | H15: Amount | I15: =CONCATENATE("x",$N$16) | J15: % of Total | L15: TEV | N15: 15000 | O15: *Refer to the Search Fund Study to understand median multiples, revenue, EBITDA, and more.
B16: Term Debt | C16: =D16*N17 | D16: =N20 | E16: =C16/C25 | G16: TEV | H16: =N15 | I16: =H16/$N$17 | J16: =H16/$H$25 | L16: Entry Multiple | N16: ARR
B17: Seller Debt | C17: =N21 | D17: =C17/$N$17 | E17: =C17/C25 | G17: Fees | H17: =H16*N19 | I17: =H17/$N$17 | J17: =H17/$H$25 | L17: =IF(N16="ARR","Ending ARR","LTM EBITDA") | N17: =IF(N16="ARR",E34,E40)
B18: Total Debt | C18: =SUM(C16:C17) | D18: =C18/$N$17 | E18: =C18/$C$25 | G18: Cash to B/S | H18: =N22 | I18: =H18/$N$17 | J18: =H18/$H$25 | L18: LTM Period | N18: 46022 | O18: 2024 Search Fund Study | Stanford Graduate School of Business
L19: Transaction Costs | N19: 0.05
B20: Equity | D20: % of Equity | L20: =CONCATENATE("Term Debt x",N16) | N20: 0.5
B21: Seller Equity Rollover | C21: =D21*C23 | D21: =N25 | E21: =C21/C25 | L21: Seller Debt Quantum | N21: 1000
B22: Investor Equity | C22: =D22*C23 | D22: =1-D21 | E22: =C22/C25 | L22: Cash to B/S | N22: 350 | O22: *Typically, searcher(s) put de minimis cash on the balance sheet.
B23: Total Equity | C23: =C25-C18 | D23: =SUM(C21:C22)/C23 | E23: =C23/C25 | L23: ECF Distribution | N23: 0 | O23: *Toggle this to distribute 1/3 of accumulated cash in Year 3 & 4.
L24: LLC/C-corp | N24: C-corp | O24: *To qualify for QSBS, TEV must be <$70M you must be a C-corp and fit certain industry requirements (many except financial and professional services firms, certain categories of healthcare, and certain other excluded businesses).
B25: Total Sources | C25: =H25 | D25: =C25/$N$17 | E25: =C25/$H$25 | G25: Total Uses | H25: =SUM(H16:H18) | I25: =H25/$N$17 | J25: =H25/$H$25 | L25: Seller Equity Rollover | N25: 0.1 | O25: QSBS | Insights | Holland & Knight
L26: Earnout | N26: 0 | O26: *This is meant to be a simple example of an earnout; earnout structures can vary.
L27: Earnout Amount | N27: 500
B28: Summary Financials | L28: Y1 Revenue Threshold | N28: 5000
E30: TXN Close | J30: TXN + 5
A31: x | B31: Income Statement | L31: Assumptions & BK Growth Notes
C33: =EDATE(D33,-12) | D33: =EDATE(E33,-12) | E33: =N18 | F33: =EDATE(E33,12) | G33: =EDATE(F33,12) | H33: =EDATE(G33,12) | I33: =EDATE(H33,12) | J33: =EDATE(I33,12) | L33: CAGR
B34: Ending ARR | C34: 2138 | D34: 3392 | E34: 5078 | F34: =E34*(1+F35) | G34: =F34*(1+G35) | H34: =G34*(1+H35) | I34: =H34*(1+I35) | J34: =I34*(1+J35) | L34: =_xlfn.RRI(2,C34,E34) | O34: *Use this if you are looking at an ARR multiple deal. Revenue for a period is calculated as the average of beginning and ending ARR.
B35: Growth | D35: =D34/C34-1 | E35: =E34/D34-1 | F35: 0.4185703 | G35: 0.38690914 | H35: 0.354 | I35: 0.33955411 | J35: 0.28793735
B37: GAAP Revenue | C37: 1657 | D37: 2765 | E37: 4235 | F37: =IF(N16="ARR",AVERAGE(F34,E34),E37*(1+F38)) | G37: =IF(O16="ARR",AVERAGE(G34,F34),F37*(1+G38)) | H37: =IF(P16="ARR",AVERAGE(H34,G34),G37*(1+H38)) | I37: =IF(Q16="ARR",AVERAGE(I34,H34),H37*(1+I38)) | J37: =IF(R16="ARR",AVERAGE(J34,I34),I37*(1+J38)) | L37: =_xlfn.RRI(2,C37,E37) | O37: *It is difficult to accelerate the growth of a business that is not already consistently growing at a solid pace.
B38: Growth | D38: =D37/C37-1 | E38: =E37/D37-1 | F38: 0.45 | G38: 0.4 | H38: 0.36 | I38: 0.34 | J38: 0.31 | O38: *Forecast revenue here if you are looking at an EBITDA multiple deal. For an ARR deal, you do not need historical revenue numbers.
B40: GAAP EBITDA | C40: -34 | D40: 105 | E40: 405 | F40: =F41*F37 | G40: =G41*G37 | H40: =H41*H37 | I40: =I41*I37 | J40: =J41*J37 | L40: =IFERROR(_xlfn.RRI(2,C40,E40),"N/A") | O40: *In the short/medium run, margins in ETA often decline and remain lower than historical margins (see research linked below for more). We rarely see a search fund business of scale with margins greater than 35%.
B41: Margin | C41: =C40/C37 | D41: =D40/D37 | E41: =E40/E37 | F41: 0.03 | G41: 0.05 | H41: 0.114 | I41: 0.12 | J41: 0.14 | O41: Research on EBITDA Margins in ETA - Thomas, Stevens, & Wasserstein
B43: GAAP EBITDA | F43: =F40 | G43: =G40 | H43: =H40 | I43: =I40 | J43: =J40
B44: Depreciation | F44: =-($L$44*F37) | G44: =-($L$44*G37) | H44: =-($L$44*H37) | I44: =-($L$44*I37) | J44: =-($L$44*J37) | L44: 0.01 | M44: % of Revenue | O44: *For asset-light search fund target businesses, depreciation will likely be minimal at around ~1-3% of revenue.
B45: EBIT | F45: =SUM(F43:F44) | G45: =SUM(G43:G44) | H45: =SUM(H43:H44) | I45: =SUM(I43:I44) | J45: =SUM(J43:J44)
B47: Interest | F47: =-F80-F89 | G47: =-G80-G89 | H47: =-H80-H89 | I47: =-I80-I89 | J47: =-J80-J89
B48: EBT | F48: =F45+F47 | G48: =G45+G47 | H48: =H45+H47 | I48: =I45+I47 | J48: =J45+J47
B50: Taxes Owed / Distributed | E50: =IF(N24="LLC",45%,26.5%) | F50: =-$E$50*F48 | G50: =-$E$50*G48 | H50: =-$E$50*H48 | I50: =-$E$50*I48 | J50: =-$E$50*J48
B51: Net Income | F51: =F48+F50 | G51: =G48+G50 | H51: =H48+H50 | I51: =I48+I50 | J51: =J48+J50
A53: x | B53: Cash Flow Statement
B55: Net Income | F55: =F51 | G55: =G51 | H55: =H51 | I55: =I51 | J55: =J51
B56: (+) D&A | F56: =-SUM(F44:F44) | G56: =-SUM(G44:G44) | H56: =-SUM(H44:H44) | I56: =-SUM(I44:I44) | J56: =-SUM(J44:J44) | O56: *You may be able to amortize a portion of the purchase price. This should be further diligenced with your legal counsel.
B57: (+) NWC | F57: =$L$57*F37 | G57: =$L$57*G37 | H57: =$L$57*H37 | I57: =$L$57*I37 | J57: =$L$57*J37 | L57: 0.01 | M57: % of Revenue | O57: *For asset-light search fund target businesses, we recommend modeling this as a 1% of revenue source of cash to be conservative.
B58: (-) CAPEX | F58: =-$L$58*F37 | G58: =-$L$58*G37 | H58: =-$L$58*H37 | I58: =-$L$58*I37 | J58: =-$L$58*J37 | L58: 0.01 | M58: % of Revenue | O58: *For asset-light search fund target businesses, CAPEX will likely be minimal at around ~1-3% of revenue.
B59: (-) Debt Paydown | F59: =F77+F86 | G59: =G77+G86 | H59: =H77+H86 | I59: =I77+I86 | J59: =J77+J86
B60: Cash after Debt | F60: =SUM(F55:F59) | G60: =SUM(G55:G59) | H60: =SUM(H55:H59) | I60: =SUM(I55:I59) | J60: =SUM(J55:J59)
B62: Cash for Earnout | F62: =-F122
B64: Beginning Cash | F64: =N22 | G64: =F70 | H64: =G70 | I64: =H70 | J64: =I70
B65: (+/-) Change in Cash | F65: =F60+F62 | G65: =G60++G62 | H65: =H60++H62 | I65: =I60++I62 | J65: =J60++J62
B66: Ending Cash before Distributions | F66: =SUM(F64:F65) | G66: =SUM(G64:G65) | H66: =SUM(H64:H65) | I66: =SUM(I64:I65) | J66: =SUM(J64:J65)
B67: Check | F67: =IF(F66<0,1,0) | G67: =IF(G66<0,1,0) | H67: =IF(H66<0,1,0) | I67: =IF(I66<0,1,0) | J67: =IF(J66<0,1,0)
B69: (-)Distributions | F69: 0 | G69: 0 | H69: =MAX(IF($N$23=1,1/3*H66,0),0) | I69: =MAX(IF($N$23=1,1/3*I66,0),0) | J69: 0
B70: Ending Cash after Distributions | F70: =F66-F69 | G70: =G66-G69 | H70: =H66-H69 | I70: =I66-I69 | J70: =J66-J69
A73: x | B73: Debt Schedule
B75: Term Loan
B76: Beginning Balance | F76: =C16 | G76: =F78 | H76: =G78 | I76: =H78 | J76: =I78
B77: (-) Mandatory Amortization | F77: =$F$76*-F82 | G77: =$F$76*-G82 | H77: =$F$76*-H82 | I77: =$F$76*-I82 | J77: =$F$76*-J82
B78: Ending Balance | F78: =SUM(F76:F77) | G78: =SUM(G76:G77) | H78: =SUM(H76:H77) | I78: =SUM(I76:I77) | J78: =SUM(J76:J77)
B80: Interest Expense | F80: =F76*$L$80 | G80: =G76*$L$80 | H80: =H76*$L$80 | I80: =I76*$L$80 | J80: =J76*$L$80 | L80: 0.14 | M80: Interest Rate
B82: Amortization Schedule | F82: 0 | G82: 0 | H82: 0.33333333 | I82: 0.33333333 | J82: 0.33333333 | L82: =IF(SUM(F82:J82)=100%,"Check","Paydown doesn't add to 100%") | O82: *Adjust amort schedule to account for term and amort of term loan debt. For bank lenders, we often see amortization schedules of 20%|20%|20%|20%|20% for non bank lenders we often see 0%|0%|0%|0%|100%.
B84: Seller Debt | N84: `
B85: Balance | F85: =C17 | G85: =F87 | H85: =G87 | I85: =H87 | J85: =I87
B86: (-) Paydown | F86: =$F$85*-F91 | G86: =$F$85*-G91 | H86: =$F$85*-H91 | I86: =$F$85*-I91 | J86: =$F$85*-J91
B87: Ending Balance | F87: =SUM(F85:F86) | G87: =SUM(G85:G86) | H87: =SUM(H85:H86) | I87: =SUM(I85:I86) | J87: =SUM(J85:J86)
B89: Interest Expense | F89: =$L$89*F85 | G89: =$L$89*G85 | H89: =$L$89*H85 | I89: =$L$89*I85 | J89: =$L$89*J85 | L89: 0.08 | M89: Interest Rate
B91: Amortization Schedule | F91: 0 | G91: 0 | H91: 0 | I91: 0 | J91: 1 | L91: =IF(SUM(F91:J91)=100%,"Check","Paydown doesn't add to 100%") | O91: *Adjust amort schedule to account for term and amort of seller debt. It is difficult to have seller debt amortize while term loan debt is still outstanding.
B93: Debt Metrics
B94: Total Senior Leverage | F94: =F78/F43 | G94: =G78/G43 | H94: =H78/H43 | I94: =I78/I43 | J94: =J78/J43 | O94: *These are examples of metrics that may be tested as covenants in term loan agreements. These are more typical for EBITDA based debt. ARR debt covenants may include tests of retention, profitability, and liquidity.
B95: Total Leverage | F95: =(F78+F87)/F43 | G95: =(G78+G87)/G43 | H95: =(H78+H87)/H43 | I95: =(I78+I87)/I43 | J95: =(J78+J87)/J43
B96: Fixed Charge Coverage Ratio | F96: =F40/(-F77+F80+-F86+F89-F58-F50+F69-F62) | G96: =G40/(-G77+G80+-G86+G89-G58-G50+G69-G62) | H96: =H40/(-H77+H80+-H86+H89-H58-H50+H69-H62) | I96: =I40/(-I77+I80+-I86+I89-I58-I50+I69-I62) | J96: =J40/(-J77+J80+-J86+J89-J58-J50+J69-J62)
B98: Returns Analysis - 5 Year Hold
A100: x | B100: Deal Structure
B102: Searcher(s) Common Equity | D102: 0.25 | F102: Circuit Breaker (0=Off) | H102: 1 | O102: *If the model is getting errors turn this to 0 and back to 1.
B103: Vested Employee Incentive Pool | D103: 0.05 | O103: *25% equity for solo searches and 30% for partnered searches.
F104: Search Capital | H104: 500
B105: Searcher(s) Equity (at close) | D105: =$D$102/3 | F105: Step-Up | H105: 1.5
B106: Searcher(s) Equity (time vest) | D106: =$D$102/3
B107: Searcher(s) Equity (performance) | D107: =$D$102/3 | F107: Investor Cap Gains Rate | H107: 0.3
B108: Total | D108: =SUM(D105:D107)
B110: Minimum IRR Hurdle | D110: 0.2 | H110: Vested | I110: Total | J110: %
B111: Maximum IRR Hurdle | D111: 0.35 | F111: Preferred Units | H111: =I111 | I111: =F117*1000 | J111: =1-D102
F112: Common Units | H112: =I112*D114/D108 | I112: =I113-I111 | J112: =I112/I113
B113: Vested Performance Equity | D113: =IF(J146>D111,D107,IF(J146<D110,0,(J146-D110)/(D111-D110))*D107) | F113: Total | H113: =SUM(H111:H112) | I113: =I111/J111 | J113: =I113/I113
B114: Total Searcher Vested Equity | D114: =D113+D106+D105
B116: Preferred Equity
B117: Beginning Balance | F117: =C23+(H105*H104) | G117: =F120 | H117: =G120 | I117: =H120 | J117: =I120
B118: (+) Preferred Return | D118: 0.08 | F118: =F117*$D$118 | G118: =G117*$D$118 | H118: =H117*$D$118 | I118: =I117*$D$118 | J118: =J117*$D$118
B119: (-) Distributions | F119: =-F69 | G119: =-G69 | H119: =-H69 | I119: =-I69 | J119: =-J69
B120: Ending Balance | F120: =SUM(F117:F119) | G120: =SUM(G117:G119) | H120: =SUM(H117:H119) | I120: =SUM(I117:I119) | J120: =SUM(J117:J119)
B122: Earnout | F122: =IF(N26=1,IF(F37>N28,N27,0),0)
A124: x | B124: Exit Waterfall & Returns
B126: =CONCATENATE("LTM "&N129&"") | J126: =IF(N128="EBITDA",J40,J34) | L126: Exit Assumptions
B127: (x) Multiple | J127: =N131 | L127: TEV @ Entry | N127: =N15
B128: Total Enterprise Value | J128: =J126*J127 | L128: Multiple @ Entry | N128: =N16
B129: (+) Cash | J129: =J70 | L129: Multiple @ Exit | N129: =N128
B130: (-) Debt | J130: =-J78-J87 | L130: Entry Multiple | N130: =IF(N128="EBITDA",N127/E40,N127/E34)
B131: Total Equity Value | J131: =SUM(J128:J130) | L131: Exit Multiple | N131: =N130 | O131: *For base case, we don't recommend underwriting to multiple expansion; this can be upside at exit.
B132: (-) Preferred Return | J132: =MAX(MIN(J120-F117,J131),0) | L132: Searcher(s) Catch Up | N132: 1
B133: (-) Return of Capital | J133: =MIN(MIN(F117,J131-J132),J120)
...

Sheet Value
A2: x | B2: G&B Model Template
B4: Instructions
B5: 1. Fill out historical Revenue and EBITDA. Project Revenue and EBITDA for the 5 year period.
B6: 2. Fill out the transaction assumptions with TEV & leverage and other key structure information.
B7: 3. Adjust the remaining assumptions in the yellow boxes for the cash flow statement and debt schedule as appropriate.
B8: 4. Check the "check" to make sure your business has the cash flow profile to support your capital structure.
B9: 5. Modify the deal structure and exit assumptions if needed. Note: If the model is getting errors, turn the circuit breaker to 0 and back to 1.
B10: 6. Evaluate the returns.
B12: $000s unless otherwise indicated | L12: Check | N12: =IF(SUM(F67:J67)>0,"Cash Shortfall","OK") | O12: *Check here to make sure your business has enough cash flow to support the capital structure.
A14: x | B14: Sources | G14: Uses | L14: Transaction Assumptions
C15: Amount | D15: =CONCATENATE("x",$N$16) | E15: % of Total | H15: Amount | I15: =CONCATENATE("x",$N$16) | J15: % of Total | L15: TEV | N15: =E40*8 | O15: *Refer to the Search Fund Study to understand median multiples, revenue, EBITDA, and more.
B16: Term Debt | C16: =D16*E40 | D16: =N20 | E16: =C16/C25 | G16: TEV | H16: =N15 | I16: =H16/$N$17 | J16: =H16/$H$25 | L16: Entry Multiple | N16: EBITDA
B17: Seller Debt | C17: =N21 | D17: =C17/$N$17 | E17: =C17/C25 | G17: Fees | H17: =H16*N19 | I17: =H17/$N$17 | J17: =H17/$H$25 | L17: =IF(N16="ARR","Ending ARR","LTM EBITDA") | N17: =IF(N16="ARR",E34,E40)
B18: Total Debt | C18: =SUM(C16:C17) | D18: =C18/$N$17 | E18: =C18/$C$25 | G18: Cash to B/S | H18: =N22 | I18: =H18/$N$17 | J18: =H18/$H$25 | L18: LTM Period | N18: 46022 | O18: 2024 Search Fund Study | Stanford Graduate School of Business
L19: Transaction Costs | N19: 0.05
B20: Equity | D20: % of Equity | L20: =CONCATENATE("Term Debt x",N16) | N20: 3
B21: Seller Equity Rollover | C21: =D21*C23 | D21: =N25 | E21: =C21/C25 | L21: Seller Debt Quantum | N21: 1500
B22: Investor Equity | C22: =D22*C23 | D22: =1-D21 | E22: =C22/C25 | L22: Cash to B/S | N22: 200 | O22: *Typically, searcher(s) put de minimis cash on the balance sheet.
B23: Total Equity | C23: =C25-C18 | D23: =SUM(C21:C22)/C23 | E23: =C23/C25 | L23: ECF Distribution | N23: 0 | O23: *Toggle this to distribute 1/3 of accumulated cash in Year 3 & 4.
L24: LLC/C-corp | N24: C-corp | O24: *To qualify for QSBS, TEV must be <$70M you must be a C-corp and fit certain industry requirements (many except financial and professional services firms, certain categories of healthcare, and certain other excluded businesses).
B25: Total Sources | C25: =H25 | D25: =C25/$N$17 | E25: =C25/$H$25 | G25: Total Uses | H25: =SUM(H16:H18) | I25: =H25/$N$17 | J25: =H25/$H$25 | L25: Seller Equity Rollover | N25: 0.1 | O25: QSBS | Insights | Holland & Knight
L26: Earnout | N26: 0 | O26: *This is meant to be a simple example of an earnout; earnout structures can vary.
L27: Earnout Amount | N27: 500
B28: Summary Financials | L28: Y1 Revenue Threshold | N28: 6000
E30: TXN Close | J30: TXN + 5
A31: x | B31: Income Statement | L31: Assumptions & BK Growth Notes
C33: =EDATE(D33,-12) | D33: =EDATE(E33,-12) | E33: =N18 | F33: =EDATE(E33,12) | G33: =EDATE(F33,12) | H33: =EDATE(G33,12) | I33: =EDATE(H33,12) | J33: =EDATE(I33,12) | L33: CAGR
B34: Ending ARR | C34: 9796 | D34: 11304 | E34: 12700 | F34: =E34*(1+F35) | G34: =F34*(1+G35) | H34: =G34*(1+H35) | I34: =H34*(1+I35) | J34: =I34*(1+J35) | L34: =_xlfn.RRI(2,C34,E34) | O34: *Use this if you are looking at an ARR multiple deal. Revenue for a period is calculated as the average of beginning and ending ARR.
B35: Growth | D35: =D34/C34-1 | E35: =E34/D34-1 | F35: 0.060185827 | G35: 0.17641857 | H35: 0.10904284 | I35: 0.20594697 | J35: 0.12189968
B37: GAAP Revenue | C37: 8000 | D37: 9000 | E37: 10000 | F37: =IF(N16="ARR",AVERAGE(F34,E34),E37*(1+F38)) | G37: =IF(O16="ARR",AVERAGE(G34,F34),F37*(1+G38)) | H37: =IF(P16="ARR",AVERAGE(H34,G34),G37*(1+H38)) | I37: =IF(Q16="ARR",AVERAGE(I34,H34),H37*(1+I38)) | J37: =IF(R16="ARR",AVERAGE(J34,I34),I37*(1+J38)) | L37: =_xlfn.RRI(2,C37,E37) | O37: *It is difficult to accelerate the growth of a business that is not already consistently growing at a solid pace.
B38: Growth | D38: =D37/C37-1 | E38: =E37/D37-1 | F38: 0.05 | G38: 0.2 | H38: 0.2 | I38: 0.2 | J38: 0.2 | O38: *Forecast revenue here if you are looking at an EBITDA multiple deal. For an ARR deal, you do not need historical revenue numbers.
B40: GAAP EBITDA | C40: 1800 | D40: 1900 | E40: 2000 | F40: =F41*F37 | G40: =G41*G37 | H40: =H41*H37 | I40: =I41*I37 | J40: =J41*J37 | L40: =_xlfn.RRI(2,C40,E40) | O40: *In the short/medium run, margins in ETA often decline and remain lower than historical margins (see research linked below for more). We rarely see a search fund business of scale with margins greater than 35%.
B41: Margin | C41: =C40/C37 | D41: =D40/D37 | E41: =E40/E37 | F41: 0.2 | G41: 0.25 | H41: 0.25 | I41: 0.3 | J41: 0.33 | O41: Research on EBITDA Margins in ETA - Thomas, Stevens, & Wasserstein
B43: GAAP EBITDA | F43: =F40 | G43: =G40 | H43: =H40 | I43: =I40 | J43: =J40
B44: Depreciation | F44: =-($L$44*F37) | G44: =-($L$44*G37) | H44: =-($L$44*H37) | I44: =-($L$44*I37) | J44: =-($L$44*J37) | L44: 0.01 | M44: % of Revenue | O44: *For asset-light search fund target businesses, depreciation will likely be minimal at around ~1-3% of revenue.
B45: EBIT | F45: =SUM(F43:F44) | G45: =SUM(G43:G44) | H45: =SUM(H43:H44) | I45: =SUM(I43:I44) | J45: =SUM(J43:J44)
B47: Interest | F47: =-F80-F89 | G47: =-G80-G89 | H47: =-H80-H89 | I47: =-I80-I89 | J47: =-J80-J89
B48: EBT | F48: =F45+F47 | G48: =G45+G47 | H48: =H45+H47 | I48: =I45+I47 | J48: =J45+J47
B50: Taxes Owed / Distributed | E50: =IF(N24="LLC",45%,26.5%) | F50: =-$E$50*F48 | G50: =-$E$50*G48 | H50: =-$E$50*H48 | I50: =-$E$50*I48 | J50: =-$E$50*J48
B51: Net Income | F51: =F48+F50 | G51: =G48+G50 | H51: =H48+H50 | I51: =I48+I50 | J51: =J48+J50
A53: x | B53: Cash Flow Statement
B55: Net Income | F55: =F51 | G55: =G51 | H55: =H51 | I55: =I51 | J55: =J51
B56: (+) D&A | F56: =-SUM(F44:F44) | G56: =-SUM(G44:G44) | H56: =-SUM(H44:H44) | I56: =-SUM(I44:I44) | J56: =-SUM(J44:J44) | O56: *You may be able to amortize a portion of the purchase price. This should be further diligenced with your legal counsel.
B57: (+) NWC | F57: =$L$57*F37 | G57: =$L$57*G37 | H57: =$L$57*H37 | I57: =$L$57*I37 | J57: =$L$57*J37 | L57: 0.01 | M57: % of Revenue | O57: *For asset-light search fund target businesses, we recommend modeling this as a 1% of revenue source of cash to be conservative.
B58: (-) CAPEX | F58: =-$L$58*F37 | G58: =-$L$58*G37 | H58: =-$L$58*H37 | I58: =-$L$58*I37 | J58: =-$L$58*J37 | L58: 0.01 | M58: % of Revenue | O58: *For asset-light search fund target businesses, CAPEX will likely be minimal at around ~1-3% of revenue.
B59: (-) Debt Paydown | F59: =F77+F86 | G59: =G77+G86 | H59: =H77+H86 | I59: =I77+I86 | J59: =J77+J86
B60: Cash after Debt | F60: =SUM(F55:F59) | G60: =SUM(G55:G59) | H60: =SUM(H55:H59) | I60: =SUM(I55:I59) | J60: =SUM(J55:J59)
B62: Cash for Earnout | F62: =-F122
B64: Beginning Cash | F64: =N22 | G64: =F70 | H64: =G70 | I64: =H70 | J64: =I70
B65: (+/-) Change in Cash | F65: =F60+F62 | G65: =G60++G62 | H65: =H60++H62 | I65: =I60++I62 | J65: =J60++J62
B66: Ending Cash before Distributions | F66: =SUM(F64:F65) | G66: =SUM(G64:G65) | H66: =SUM(H64:H65) | I66: =SUM(I64:I65) | J66: =SUM(J64:J65)
B67: Check | F67: =IF(F66<0,1,0) | G67: =IF(G66<0,1,0) | H67: =IF(H66<0,1,0) | I67: =IF(I66<0,1,0) | J67: =IF(J66<0,1,0)
B69: (-)Distributions | F69: 0 | G69: 0 | H69: =MAX(IF($N$23=1,1/3*H66,0),0) | I69: =MAX(IF($N$23=1,1/3*I66,0),0) | J69: 0
B70: Ending Cash after Distributions | F70: =F66-F69 | G70: =G66-G69 | H70: =H66-H69 | I70: =I66-I69 | J70: =J66-J69
A73: x | B73: Debt Schedule
B75: Term Loan
B76: Beginning Balance | F76: =C16 | G76: =F78 | H76: =G78 | I76: =H78 | J76: =I78
B77: (-) Mandatory Amortization | F77: =$F$76*-F82 | G77: =$F$76*-G82 | H77: =$F$76*-H82 | I77: =$F$76*-I82 | J77: =$F$76*-J82
B78: Ending Balance | F78: =SUM(F76:F77) | G78: =SUM(G76:G77) | H78: =SUM(H76:H77) | I78: =SUM(I76:I77) | J78: =SUM(J76:J77)
B80: Interest Expense | F80: =F76*$L$80 | G80: =G76*$L$80 | H80: =H76*$L$80 | I80: =I76*$L$80 | J80: =J76*$L$80 | L80: 0.12 | M80: Interest Rate
B82: Amortization Schedule | F82: 0 | G82: 0 | H82: 0 | I82: 0 | J82: 1 | L82: =IF(SUM(F82:J82)=100%,"Check","Paydown doesn't add to 100%") | O82: *Adjust amort schedule to account for term and amort of term loan debt. For bank lenders, we often see amortization schedules of 20%|20%|20%|20%|20% for non bank lenders we often see 0%|0%|0%|0%|100%.
B84: Seller Debt | N84: `
B85: Balance | F85: =C17 | G85: =F87 | H85: =G87 | I85: =H87 | J85: =I87
B86: (-) Paydown | F86: =$F$85*-F91 | G86: =$F$85*-G91 | H86: =$F$85*-H91 | I86: =$F$85*-I91 | J86: =$F$85*-J91
B87: Ending Balance | F87: =SUM(F85:F86) | G87: =SUM(G85:G86) | H87: =SUM(H85:H86) | I87: =SUM(I85:I86) | J87: =SUM(J85:J86)
B89: Interest Expense | F89: =$L$89*F85 | G89: =$L$89*G85 | H89: =$L$89*H85 | I89: =$L$89*I85 | J89: =$L$89*J85 | L89: 0.08 | M89: Interest Rate
B91: Amortization Schedule | F91: 0 | G91: 0 | H91: 0 | I91: 0 | J91: 1 | L91: =IF(SUM(F91:J91)=100%,"Check","Paydown doesn't add to 100%") | O91: *Adjust amort schedule to account for term and amort of seller debt. It is difficult to have seller debt amortize while term loan debt is still outstanding.
B93: Debt Metrics
B94: Total Senior Leverage | F94: =F78/F43 | G94: =G78/G43 | H94: =H78/H43 | I94: =I78/I43 | J94: =J78/J43 | O94: *These are examples of metrics that may be tested as covenants in term loan agreements. These are more typical for EBITDA based debt. ARR debt covenants may include tests of retention, profitability, and liquidity.
B95: Total Leverage | F95: =(F78+F87)/F43 | G95: =(G78+G87)/G43 | H95: =(H78+H87)/H43 | I95: =(I78+I87)/I43 | J95: =(J78+J87)/J43
B96: Fixed Charge Coverage Ratio | F96: =F40/(-F77+F80+-F86+F89-F58-F50+F69-F62) | G96: =G40/(-G77+G80+-G86+G89-G58-G50+G69-G62) | H96: =H40/(-H77+H80+-H86+H89-H58-H50+H69-H62) | I96: =I40/(-I77+I80+-I86+I89-I58-I50+I69-I62) | J96: =J40/(-J77+J80+-J86+J89-J58-J50+J69-J62)
B98: Returns Analysis - 5 Year Hold
A100: x | B100: Deal Structure
B102: Searcher(s) Common Equity | D102: 0.25 | F102: Circuit Breaker (0=Off) | H102: 1 | O102: *If the model is getting errors turn this to 0 and back to 1.
B103: Vested Employee Incentive Pool | D103: 0.05 | O103: *25% equity for solo searches and 30% for partnered searches.
F104: Search Capital | H104: 500
B105: Searcher(s) Equity (at close) | D105: =$D$102/3 | F105: Step-Up | H105: 1.5
B106: Searcher(s) Equity (time vest) | D106: =$D$102/3
B107: Searcher(s) Equity (performance) | D107: =$D$102/3 | F107: Investor Cap Gains Rate | H107: 0.3
B108: Total | D108: =SUM(D105:D107)
B110: Minimum IRR Hurdle | D110: 0.2 | H110: Vested | I110: Total | J110: %
B111: Maximum IRR Hurdle | D111: 0.35 | F111: Preferred Units | H111: =I111 | I111: =F117*1000 | J111: =1-D102
F112: Common Units | H112: =I112*D114/D108 | I112: =I113-I111 | J112: =I112/I113
B113: Vested Performance Equity | D113: =IF(J146>D111,D107,IF(J146<D110,0,(J146-D110)/(D111-D110))*D107) | F113: Total | H113: =SUM(H111:H112) | I113: =I111/J111 | J113: =I113/I113
B114: Total Searcher Vested Equity | D114: =D113+D106+D105
B116: Preferred Equity
B117: Beginning Balance | F117: =C23+(H105*H104) | G117: =F120 | H117: =G120 | I117: =H120 | J117: =I120
B118: (+) Preferred Return | D118: 0.08 | F118: =F117*$D$118 | G118: =G117*$D$118 | H118: =H117*$D$118 | I118: =I117*$D$118 | J118: =J117*$D$118
B119: (-) Distributions | F119: =-F69 | G119: =-G69 | H119: =-H69 | I119: =-I69 | J119: =-J69
B120: Ending Balance | F120: =SUM(F117:F119) | G120: =SUM(G117:G119) | H120: =SUM(H117:H119) | I120: =SUM(I117:I119) | J120: =SUM(J117:J119)
B122: Earnout | F122: =IF(N26=1,IF(F37>N28,N27,0),0)
A124: x | B124: Exit Waterfall & Returns
B126: =CONCATENATE("LTM "&N129&"") | J126: =IF(N128="EBITDA",J40,J34) | L126: Exit Assumptions
B127: (x) Multiple | J127: =N131 | L127: TEV @ Entry | N127: =N15
B128: Total Enterprise Value | J128: =J126*J127 | L128: Multiple @ Entry | N128: =N16
B129: (+) Cash | J129: =J70 | L129: Multiple @ Exit | N129: =N128
B130: (-) Debt | J130: =-J78-J87 | L130: Entry Multiple | N130: =IF(N128="EBITDA",N127/E40,N127/E34)
B131: Total Equity Value | J131: =SUM(J128:J130) | L131: Exit Multiple | N131: 8 | O131: *For base case, we don't recommend underwriting to multiple expansion; this can be upside at exit.
B132: (-) Preferred Return | J132: =MAX(MIN(J120-F117,J131),0) | L132: Searcher(s) Catch Up | N132: 1
B133: (-) Return of Capital | J133: =MIN(MIN(F117,J131-J132),J120)
...
