Workbook

Sheet Summary
A1: TPFO Household Protection Binder - Launch Test Budget
A3: Decision | B3: Current Launch Assumption
A4: Product | B4: TPFO Household Protection Binder
A5: First test price | B5: 49
A6: Sales platform | B6: Gumroad direct checkout
A7: Advertising budget | B7: 0
A8: Initial channel | B8: Pinterest organic + owned-site SEO
A9: Optional marketplace test | B9: Etsy, not approved yet
A10: Publication status | B10: Not published
A11: Payment status | B11: Not enabled
A14: Per-Sale Economics
A15: Direct Gumroad sale gross | B15: =Assumptions!B4
A16: Estimated direct-sale fees | B16: ='Per-Sale Economics'!B8
A17: Estimated net per direct sale before income taxes | B17: ='Per-Sale Economics'!B9
A18: Gumroad Discover sale gross | B18: =Assumptions!B4
A19: Estimated Discover fees | B19: ='Per-Sale Economics'!C8
A20: Estimated net per Discover sale before income taxes | B20: ='Per-Sale Economics'!C9
A23: Monthly Bridge Target Scenarios
A24: Target net before income taxes | B24: Direct sales needed | C24: Discover sales needed
A25: 10000 | B25: =ROUNDUP(A25/'Per-Sale Economics'!B9,0) | C25: =ROUNDUP(A25/'Per-Sale Economics'!C9,0)
A26: 20000 | B26: =ROUNDUP(A26/'Per-Sale Economics'!B9,0) | C26: =ROUNDUP(A26/'Per-Sale Economics'!C9,0)

Sheet Assumptions
A1: Assumptions
A3: Input | B3: Value | C3: Source / Note
A4: Product name | B4: TPFO Household Protection Binder | C4: Approved launch name
A5: First test price | B5: 49 | C5: Approved launch price
A6: Gumroad direct platform fee | B6: 0.1 | C6: Gumroad direct sales fee
A7: Gumroad direct fixed fee | B7: 0.5 | C7: Gumroad direct sales fixed fee
A8: Card processing percentage | B8: 0.029 | C8: Gumroad help page lists credit card processing separately
A9: Card processing fixed fee | B9: 0.3 | C9: Gumroad help page lists credit card processing separately
A10: Gumroad Discover fee | B10: 0.3 | C10: Gumroad Discover flat fee includes processing
A11: Advertising budget | B11: 0 | C11: Approved recommendation for initial test
A12: Optional Etsy listing fee | B12: 0.2 | C12: Not approved; included only for optional scenario
A13: Optional domain estimate - low | B13: 10 | C13: Annual estimate; only if buying a domain now
A14: Optional domain estimate - high | B14: 25 | C14: Annual estimate; only if buying a domain now

Sheet Per-Sale Economics
A1: Per-Sale Economics
A3: Line Item | B3: Gumroad Direct | C3: Gumroad Discover
A4: Gross sale price | B4: =Assumptions!B4 | C4: =Assumptions!B4
A5: Gumroad platform fee | B5: =B4*Assumptions!B5 | C5: =C4*Assumptions!B9
A6: Gumroad fixed fee | B6: =Assumptions!B6 | C6: =0
A7: Card processing | B7: =B4*Assumptions!B7+Assumptions!B8 | C7: =0
A8: Total fees | B8: =SUM(B5:B7) | C8: =SUM(C5:C7)
A9: Net before income taxes | B9: =B4-B8 | C9: =C4-C8
A10: Effective fee rate | B10: =B8/B4 | C10: =C8/C4

Sheet Bridge Targets
A1: Bridge Target Scenarios
A3: Monthly net target before income taxes | B3: Direct net per sale | C3: Direct sales needed | D3: Discover net per sale | E3: Discover sales needed
A4: 2500 | B4: ='Per-Sale Economics'!B9 | C4: =ROUNDUP(A4/B4,0) | D4: ='Per-Sale Economics'!C9 | E4: =ROUNDUP(A4/D4,0)
A5: 5000 | B5: ='Per-Sale Economics'!B9 | C5: =ROUNDUP(A5/B5,0) | D5: ='Per-Sale Economics'!C9 | E5: =ROUNDUP(A5/D5,0)
A6: 10000 | B6: ='Per-Sale Economics'!B9 | C6: =ROUNDUP(A6/B6,0) | D6: ='Per-Sale Economics'!C9 | E6: =ROUNDUP(A6/D6,0)
A7: 15000 | B7: ='Per-Sale Economics'!B9 | C7: =ROUNDUP(A7/B7,0) | D7: ='Per-Sale Economics'!C9 | E7: =ROUNDUP(A7/D7,0)
A8: 20000 | B8: ='Per-Sale Economics'!B9 | C8: =ROUNDUP(A8/B8,0) | D8: ='Per-Sale Economics'!C9 | E8: =ROUNDUP(A8/D8,0)
A9: 30000 | B9: ='Per-Sale Economics'!B9 | C9: =ROUNDUP(A9/B9,0) | D9: ='Per-Sale Economics'!C9 | E9: =ROUNDUP(A9/D9,0)

Sheet Optional Costs
A1: Optional Costs And Status
A3: Cost Item | B3: Estimated Cost | C3: Timing | D3: Status / Note
A4: Gumroad monthly subscription | B4: 0 | C4: Monthly | D4: No monthly fee listed for standard direct sales
A5: Initial advertising budget | B5: 0 | C5: Launch test | D5: Approved recommendation: no ad spend for first test
A6: Domain | B6: 10-25 | C6: Annual | D6: Optional; only if buying a domain now
A7: Etsy listing fee | B7: 0.2 | C7: Per listing | D7: Optional; not approved yet
A8: Pinterest organic posting | B8: 0 | C8: Launch test | D8: No ad spend required
A9: Pinterest ads | B9: TBD | C9: Optional | D9: Do not use without approval

Sheet Sources
A1: Sources And Notes
A3: Source | B3: URL | C3: Note
A4: Gumroad fees | B4: https://gumroad.com/help/article/66-gumroads-fees | C4: Direct fee: 10% + $0.50 plus payment processing. Discover: 30% including processing.
A5: Gumroad pricing | B5: https://gumroad.com/pricing | C5: No monthly fee; merchant of record language.
A6: Etsy seller fees | B6: https://help.etsy.com/hc/en-us/articles/115014483627-What-are-the-Fees-and-Taxes-for-Selling-on-Etsy | C6: Listing, transaction, payment processing, and optional ad fee categories.
A7: Pinterest budgets | B7: https://help.pinterest.com/en/business/article/set-up-campaign-budgets | C7: Ad budgets are optional; organic posting does not require ad spend.
A8: Important boundary | C8: This workbook estimates launch-test economics. It is not a sales forecast, accounting advice, tax advice, or a cash-flow plan.
